{
  "team_games": [
    {
      "Unnamed_0": 33206,
      "Tm": "STL",
      "Home_Away": "@",
      "Opp": "MIL",
      "W_or_L": "L",
      "R": 4.0,
      "RA": 5.0,
      "Inn": 9.0,
      "Record": "0-1",
      "Rank": 4.0,
      "GB": "1.0",
      "Win": "Chac\u00edn",
      "Loss": "Mikolas",
      "Save": "Hader",
      "Time": "2:36",
      "Attendance": 45304.0,
      "Streak": -1.0,
      "Year": 2019,
      "Date": "2019-03-28",
      "Winner": "MIL"
    },
    {
      "Unnamed_0": 33207,
      "Tm": "STL",
      "Home_Away": "@",
      "Opp": "MIL",
      "W_or_L": "W",
      "R": 9.0,
      "RA": 5.0,
      "Inn": 9.0,
      "Record": "1-1",
      "Rank": 3.0,
      "GB": "0.5",
      "Win": "Gant",
      "Loss": "Williams",
      "Save": null,
      "Time": "3:41",
      "Attendance": 30157.0,
      "Streak": 1.0,
      "Year": 2019,
      "Date": "2019-03-29",
      "Winner": "STL"
    },
    {
      "Unnamed_0": 33208,
      "Tm": "STL",
      "Home_Away": "@",
      "Opp": "MIL",
      "W_or_L": "L",
      "R": 2.0,
      "RA": 4.0,
      "Inn": 9.0,
      "Record": "1-2",
      "Rank": 4.0,
      "GB": "1.0",
      "Win": "Woodruff",
      "Loss": "Hudson",
      "Save": "Hader",
      "Time": "3:07",
      "Attendance": 36655.0,
      "Streak": -1.0,
      "Year": 2019,
      "Date": "2019-03-30",
      "Winner": "MIL"
    },
    {
      "Unnamed_0": 33209,
      "Tm": "STL",
      "Home_Away": "@",
      "Opp": "MIL",
      "W_or_L": "L-wo",
      "R": 4.0,
      "RA": 5.0,
      "Inn": 9.0,
      "Record": "1-3",
      "Rank": 5.0,
      "GB": "2.0",
      "Win": "Barnes",
      "Loss": "Hicks",
      "Save": null,
      "Time": "2:54",
      "Attendance": 35042.0,
      "Streak": -2.0,
      "Year": 2019,
      "Date": "2019-03-31",
      "Winner": "MIL-wo"
    },
    {
      "Unnamed_0": 33210,
      "Tm": "STL",
      "Home_Away": "@",
      "Opp": "PIT",
      "W_or_L": "W",
      "R": 6.0,
      "RA": 5.0,
      "Inn": 11.0,
      "Record": "2-3",
      "Rank": 2.0,
      "GB": "2.0",
      "Win": "Hicks",
      "Loss": "Brault",
      "Save": "Gant",
      "Time": "4:50",
      "Attendance": 37336.0,
      "Streak": 1.0,
      "Year": 2019,
      "Date": "2019-04-01",
      "Winner": "STL"
    },
    {
      "Unnamed_0": 33211,
      "Tm": "STL",
      "Home_Away": "@",
      "Opp": "PIT",
      "W_or_L": "W",
      "R": 5.0,
      "RA": 4.0,
      "Inn": 10.0,
      "Record": "3-3",
      "Rank": 2.0,
      "GB": "2.5",
      "Win": "Gant",
      "Loss": "Burdi",
      "Save": "Hudson",
      "Time": "3:30",
      "Attendance": 23954.0,
      "Streak": 2.0,
      "Year": 2019,
      "Date": "2019-04-03",
      "Winner": "STL"
    },
    {
      "Unnamed_0": 33212,
      "Tm": "STL",
      "Home_Away": "Home",
      "Opp": "SDP",
      "W_or_L": "L",
      "R": 3.0,
      "RA": 5.0,
      "Inn": 9.0,
      "Record": "3-4",
      "Rank": 3.0,
      "GB": "3.5",
      "Win": "Stock",
      "Loss": "Reyes",
      "Save": "Yates",
      "Time": "2:54",
      "Attendance": 46615.0,
      "Streak": -1.0,
      "Year": 2019,
      "Date": "2019-04-05",
      "Winner": "SDP"
    },
    {
      "Unnamed_0": 33213,
      "Tm": "STL",
      "Home_Away": "Home",
      "Opp": "SDP",
      "W_or_L": "L",
      "R": 4.0,
      "RA": 6.0,
      "Inn": 9.0,
      "Record": "3-5",
      "Rank": 3.0,
      "GB": "3.5",
      "Win": "Wisler",
      "Loss": "Miller",
      "Save": "Yates",
      "Time": "3:37",
      "Attendance": 44492.0,
      "Streak": -2.0,
      "Year": 2019,
      "Date": "2019-04-06",
      "Winner": "SDP"
    },
    {
      "Unnamed_0": 33214,
      "Tm": "STL",
      "Home_Away": "Home",
      "Opp": "SDP",
      "W_or_L": "W",
      "R": 4.0,
      "RA": 1.0,
      "Inn": 9.0,
      "Record": "4-5",
      "Rank": 3.0,
      "GB": "3.5",
      "Win": "Wainwright",
      "Loss": "Strahm",
      "Save": "Hicks",
      "Time": "3:08",
      "Attendance": 44340.0,
      "Streak": 1.0,
      "Year": 2019,
      "Date": "2019-04-07",
      "Winner": "STL"
    },
    {
      "Unnamed_0": 33215,
      "Tm": "STL",
      "Home_Away": "Home",
      "Opp": "LAD",
      "W_or_L": "W",
      "R": 4.0,
      "RA": 3.0,
      "Inn": 9.0,
      "Record": "5-5",
      "Rank": 3.0,
      "GB": "2.5",
      "Win": "Mikolas",
      "Loss": "Kelly",
      "Save": "Hicks",
      "Time": "2:41",
      "Attendance": 35858.0,
      "Streak": 2.0,
      "Year": 2019,
      "Date": "2019-04-08",
      "Winner": "STL"
    },
    {
      "Unnamed_0": 33216,
      "Tm": "STL",
      "Home_Away": "Home",
      "Opp": "LAD",
      "W_or_L": "W",
      "R": 4.0,
      "RA": 0.0,
      "Inn": 9.0,
      "Record": "6-5",
      "Rank": 2.0,
      "GB": "1.5",
      "Win": "Brebbia",
      "Loss": "Stripling",
      "Save": null,
      "Time": "3:17",
      "Attendance": 36353.0,
      "Streak": 3.0,
      "Year": 2019,
      "Date": "2019-04-09",
      "Winner": "STL"
    },
    {
      "Unnamed_0": 33217,
      "Tm": "STL",
      "Home_Away": "Home",
      "Opp": "LAD",
      "W_or_L": "W",
      "R": 7.0,
      "RA": 2.0,
      "Inn": 9.0,
      "Record": "7-5",
      "Rank": 2.0,
      "GB": "0.5",
      "Win": "Flaherty",
      "Loss": "Maeda",
      "Save": null,
      "Time": "2:52",
      "Attendance": 36244.0,
      "Streak": 4.0,
      "Year": 2019,
      "Date": "2019-04-10",
      "Winner": "STL"
    },
    {
      "Unnamed_0": 33218,
      "Tm": "STL",
      "Home_Away": "Home",
      "Opp": "LAD",
      "W_or_L": "W",
      "R": 11.0,
      "RA": 7.0,
      "Inn": 9.0,
      "Record": "8-5",
      "Rank": 1.0,
      "GB": "Tied",
      "Win": "Gallegos",
      "Loss": "B\u00e1ez",
      "Save": null,
      "Time": "3:12",
      "Attendance": 38200.0,
      "Streak": 5.0,
      "Year": 2019,
      "Date": "2019-04-11",
      "Winner": "STL"
    },
    {
      "Unnamed_0": 33219,
      "Tm": "STL",
      "Home_Away": "@",
      "Opp": "CIN",
      "W_or_L": "L",
      "R": 2.0,
      "RA": 5.0,
      "Inn": 9.0,
      "Record": "8-6",
      "Rank": 2.0,
      "GB": "1.5",
      "Win": "Hughes",
      "Loss": "Wainwright",
      "Save": "Iglesias",
      "Time": "3:08",
      "Attendance": 16886.0,
      "Streak": -1.0,
      "Year": 2019,
      "Date": "2019-04-13",
      "Winner": "CIN"
    },
    {
      "Unnamed_0": 33220,
      "Tm": "STL",
      "Home_Away": "@",
      "Opp": "CIN",
      "W_or_L": "W",
      "R": 9.0,
      "RA": 5.0,
      "Inn": 9.0,
      "Record": "9-6",
      "Rank": 2.0,
      "GB": "0.5",
      "Win": "Gant",
      "Loss": "Garrett",
      "Save": "Hicks",
      "Time": "3:19",
      "Attendance": 16793.0,
      "Streak": 1.0,
      "Year": 2019,
      "Date": "2019-04-14",
      "Winner": "STL"
    },
    {
      "Unnamed_0": 33221,
      "Tm": "STL",
      "Home_Away": "@",
      "Opp": "MIL",
      "W_or_L": "L",
      "R": 7.0,
      "RA": 10.0,
      "Inn": 9.0,
      "Record": "9-7",
      "Rank": 2.0,
      "GB": "1.5",
      "Win": "Guerra",
      "Loss": "Mayers",
      "Save": null,
      "Time": "3:51",
      "Attendance": 28199.0,
      "Streak": -1.0,
      "Year": 2019,
      "Date": "2019-04-15",
      "Winner": "MIL"
    },
    {
      "Unnamed_0": 33222,
      "Tm": "STL",
      "Home_Away": "@",
      "Opp": "MIL",
      "W_or_L": "L",
      "R": 4.0,
      "RA": 8.0,
      "Inn": 9.0,
      "Record": "9-8",
      "Rank": 3.0,
      "GB": "2.5",
      "Win": "Woodruff",
      "Loss": "Flaherty",
      "Save": null,
      "Time": "3:13",
      "Attendance": 30260.0,
      "Streak": -2.0,
      "Year": 2019,
      "Date": "2019-04-16",
      "Winner": "MIL"
    },
    {
      "Unnamed_0": 33223,
      "Tm": "STL",
      "Home_Away": "@",
      "Opp": "MIL",
      "W_or_L": "W",
      "R": 6.0,
      "RA": 3.0,
      "Inn": 9.0,
      "Record": "10-8",
      "Rank": 3.0,
      "GB": "1.5",
      "Win": "Wacha",
      "Loss": "Burnes",
      "Save": "Hicks",
      "Time": "2:55",
      "Attendance": 29817.0,
      "Streak": 1.0,
      "Year": 2019,
      "Date": "2019-04-17",
      "Winner": "STL"
    },
    {
      "Unnamed_0": 33224,
      "Tm": "STL",
      "Home_Away": "Home",
      "Opp": "NYM",
      "W_or_L": "L",
      "R": 4.0,
      "RA": 5.0,
      "Inn": 9.0,
      "Record": "10-9",
      "Rank": 3.0,
      "GB": "2.0",
      "Win": "Lugo",
      "Loss": "Wainwright",
      "Save": "D\u00edaz",
      "Time": "3:31",
      "Attendance": 40413.0,
      "Streak": -1.0,
      "Year": 2019,
      "Date": "2019-04-19",
      "Winner": "NYM"
    },
    {
      "Unnamed_0": 33225,
      "Tm": "STL",
      "Home_Away": "Home",
      "Opp": "NYM",
      "W_or_L": "W",
      "R": 10.0,
      "RA": 2.0,
      "Inn": 9.0,
      "Record": "11-9",
      "Rank": 3.0,
      "GB": "2.0",
      "Win": "Mikolas",
      "Loss": "Flexen",
      "Save": null,
      "Time": "2:45",
      "Attendance": 47059.0,
      "Streak": 1.0,
      "Year": 2019,
      "Date": "2019-04-20",
      "Winner": "STL"
    },
    {
      "Unnamed_0": 33226,
      "Tm": "STL",
      "Home_Away": "Home",
      "Opp": "NYM",
      "W_or_L": "W",
      "R": 6.0,
      "RA": 4.0,
      "Inn": 9.0,
      "Record": "12-9",
      "Rank": 2.0,
      "GB": "1.0",
      "Win": "Hudson",
      "Loss": "Syndergaard",
      "Save": "Hicks",
      "Time": "3:07",
      "Attendance": 42765.0,
      "Streak": 2.0,
      "Year": 2019,
      "Date": "2019-04-21",
      "Winner": "STL"
    },
    {
      "Unnamed_0": 33227,
      "Tm": "STL",
      "Home_Away": "Home",
      "Opp": "MIL",
      "W_or_L": "W",
      "R": 13.0,
      "RA": 5.0,
      "Inn": 9.0,
      "Record": "13-9",
      "Rank": 1.0,
      "GB": "Tied",
      "Win": "Flaherty",
      "Loss": "Houser",
      "Save": null,
      "Time": "3:12",
      "Attendance": 35819.0,
      "Streak": 3.0,
      "Year": 2019,
      "Date": "2019-04-22",
      "Winner": "STL"
    },
    {
      "Unnamed_0": 33228,
      "Tm": "STL",
      "Home_Away": "Home",
      "Opp": "MIL",
      "W_or_L": "W",
      "R": 4.0,
      "RA": 3.0,
      "Inn": 9.0,
      "Record": "14-9",
      "Rank": 1.0,
      "GB": "up 1.0",
      "Win": "Miller",
      "Loss": "Wilson",
      "Save": "Hicks",
      "Time": "3:00",
      "Attendance": 38474.0,
      "Streak": 4.0,
      "Year": 2019,
      "Date": "2019-04-23",
      "Winner": "STL"
    },
    {
      "Unnamed_0": 33229,
      "Tm": "STL",
      "Home_Away": "Home",
      "Opp": "MIL",
      "W_or_L": "W",
      "R": 5.0,
      "RA": 2.0,
      "Inn": 9.0,
      "Record": "15-9",
      "Rank": 1.0,
      "GB": "up 2.0",
      "Win": "Wainwright",
      "Loss": "Chac\u00edn",
      "Save": "Hicks",
      "Time": "2:51",
      "Attendance": 36878.0,
      "Streak": 5.0,
      "Year": 2019,
      "Date": "2019-04-24",
      "Winner": "STL"
    },
    {
      "Unnamed_0": 33230,
      "Tm": "STL",
      "Home_Away": "Home",
      "Opp": "CIN",
      "W_or_L": "L",
      "R": 1.0,
      "RA": 12.0,
      "Inn": 9.0,
      "Record": "15-10",
      "Rank": 1.0,
      "GB": "up 2.0",
      "Win": "DeSclafani",
      "Loss": "Mikolas",
      "Save": null,
      "Time": "2:55",
      "Attendance": 45087.0,
      "Streak": -1.0,
      "Year": 2019,
      "Date": "2019-04-26",
      "Winner": "CIN"
    },
    {
      "Unnamed_0": 33231,
      "Tm": "STL",
      "Home_Away": "Home",
      "Opp": "CIN",
      "W_or_L": "W",
      "R": 6.0,
      "RA": 3.0,
      "Inn": 9.0,
      "Record": "16-10",
      "Rank": 1.0,
      "GB": "up 2.0",
      "Win": "Hudson",
      "Loss": "Mahle",
      "Save": "Hicks",
      "Time": "2:32",
      "Attendance": 44197.0,
      "Streak": 1.0,
      "Year": 2019,
      "Date": "2019-04-27",
      "Winner": "STL"
    },
    {
      "Unnamed_0": 33232,
      "Tm": "STL",
      "Home_Away": "Home",
      "Opp": "CIN",
      "W_or_L": "W",
      "R": 5.0,
      "RA": 2.0,
      "Inn": 9.0,
      "Record": "17-10",
      "Rank": 1.0,
      "GB": "up 2.5",
      "Win": "Flaherty",
      "Loss": "Gray",
      "Save": "Gant",
      "Time": "2:53",
      "Attendance": 45701.0,
      "Streak": 2.0,
      "Year": 2019,
      "Date": "2019-04-28",
      "Winner": "STL"
    },
    {
      "Unnamed_0": 33233,
      "Tm": "STL",
      "Home_Away": "@",
      "Opp": "WSN",
      "W_or_L": "W",
      "R": 6.0,
      "RA": 3.0,
      "Inn": 9.0,
      "Record": "18-10",
      "Rank": 1.0,
      "GB": "up 3.0",
      "Win": "Wacha",
      "Loss": "Corbin",
      "Save": "Hicks",
      "Time": "3:05",
      "Attendance": 17890.0,
      "Streak": 3.0,
      "Year": 2019,
      "Date": "2019-04-29",
      "Winner": "STL"
    },
    {
      "Unnamed_0": 33234,
      "Tm": "STL",
      "Home_Away": "@",
      "Opp": "WSN",
      "W_or_L": "W",
      "R": 3.0,
      "RA": 2.0,
      "Inn": 9.0,
      "Record": "19-10",
      "Rank": 1.0,
      "GB": "up 3.0",
      "Win": "Wainwright",
      "Loss": "S\u00e1nchez",
      "Save": "Miller",
      "Time": "3:09",
      "Attendance": 19753.0,
      "Streak": 4.0,
      "Year": 2019,
      "Date": "2019-04-30",
      "Winner": "STL"
    },
    {
      "Unnamed_0": 33235,
      "Tm": "STL",
      "Home_Away": "@",
      "Opp": "WSN",
      "W_or_L": "W",
      "R": 5.0,
      "RA": 1.0,
      "Inn": 9.0,
      "Record": "20-10",
      "Rank": 1.0,
      "GB": "up 3.0",
      "Win": "Mikolas",
      "Loss": "Scherzer",
      "Save": null,
      "Time": "3:02",
      "Attendance": 22157.0,
      "Streak": 5.0,
      "Year": 2019,
      "Date": "2019-05-01",
      "Winner": "STL"
    },
    {
      "Unnamed_0": 33236,
      "Tm": "STL",
      "Home_Away": "@",
      "Opp": "WSN",
      "W_or_L": "L",
      "R": 1.0,
      "RA": 2.0,
      "Inn": 9.0,
      "Record": "20-11",
      "Rank": 1.0,
      "GB": "up 2.5",
      "Win": "Strasburg",
      "Loss": "Hudson",
      "Save": "Doolittle",
      "Time": "3:00",
      "Attendance": 24338.0,
      "Streak": -1.0,
      "Year": 2019,
      "Date": "2019-05-02",
      "Winner": "WSN"
    },
    {
      "Unnamed_0": 33237,
      "Tm": "STL",
      "Home_Away": "@",
      "Opp": "CHC",
      "W_or_L": "L",
      "R": 0.0,
      "RA": 4.0,
      "Inn": 9.0,
      "Record": "20-12",
      "Rank": 1.0,
      "GB": "up 1.5",
      "Win": "Hendricks",
      "Loss": "Flaherty",
      "Save": null,
      "Time": "2:28",
      "Attendance": 34978.0,
      "Streak": -2.0,
      "Year": 2019,
      "Date": "2019-05-03",
      "Winner": "CHC"
    },
    {
      "Unnamed_0": 33238,
      "Tm": "STL",
      "Home_Away": "@",
      "Opp": "CHC",
      "W_or_L": "L",
      "R": 5.0,
      "RA": 6.0,
      "Inn": 9.0,
      "Record": "20-13",
      "Rank": 1.0,
      "GB": "up 0.5",
      "Win": "Kintzler",
      "Loss": "Brebbia",
      "Save": "Strop",
      "Time": "3:03",
      "Attendance": 39601.0,
      "Streak": -3.0,
      "Year": 2019,
      "Date": "2019-05-04",
      "Winner": "CHC"
    },
    {
      "Unnamed_0": 33239,
      "Tm": "STL",
      "Home_Away": "@",
      "Opp": "CHC",
      "W_or_L": "L",
      "R": 5.0,
      "RA": 13.0,
      "Inn": 9.0,
      "Record": "20-14",
      "Rank": 2.0,
      "GB": "0.5",
      "Win": "Quintana",
      "Loss": "Wainwright",
      "Save": null,
      "Time": "3:21",
      "Attendance": 36499.0,
      "Streak": -4.0,
      "Year": 2019,
      "Date": "2019-05-05",
      "Winner": "CHC"
    },
    {
      "Unnamed_0": 33240,
      "Tm": "STL",
      "Home_Away": "Home",
      "Opp": "PHI",
      "W_or_L": "W",
      "R": 6.0,
      "RA": 0.0,
      "Inn": 9.0,
      "Record": "21-14",
      "Rank": 1.0,
      "GB": "up 0.5",
      "Win": "Mikolas",
      "Loss": "Velasquez",
      "Save": null,
      "Time": "2:52",
      "Attendance": 38419.0,
      "Streak": 1.0,
      "Year": 2019,
      "Date": "2019-05-06",
      "Winner": "STL"
    },
    {
      "Unnamed_0": 33241,
      "Tm": "STL",
      "Home_Away": "Home",
      "Opp": "PHI",
      "W_or_L": "L",
      "R": 1.0,
      "RA": 11.0,
      "Inn": 9.0,
      "Record": "21-15",
      "Rank": 2.0,
      "GB": "0.5",
      "Win": "Nola",
      "Loss": "Hudson",
      "Save": null,
      "Time": "3:04",
      "Attendance": 38562.0,
      "Streak": -1.0,
      "Year": 2019,
      "Date": "2019-05-07",
      "Winner": "PHI"
    },
    {
      "Unnamed_0": 33242,
      "Tm": "STL",
      "Home_Away": "Home",
      "Opp": "PHI",
      "W_or_L": "L",
      "R": 0.0,
      "RA": 5.0,
      "Inn": 9.0,
      "Record": "21-16",
      "Rank": 3.0,
      "GB": "1.5",
      "Win": "Eickhoff",
      "Loss": "Flaherty",
      "Save": null,
      "Time": "2:41",
      "Attendance": 42309.0,
      "Streak": -2.0,
      "Year": 2019,
      "Date": "2019-05-08",
      "Winner": "PHI"
    },
    {
      "Unnamed_0": 33243,
      "Tm": "STL",
      "Home_Away": "Home",
      "Opp": "PIT",
      "W_or_L": "W",
      "R": 17.0,
      "RA": 4.0,
      "Inn": 9.0,
      "Record": "22-16",
      "Rank": 3.0,
      "GB": "1.5",
      "Win": "Wacha",
      "Loss": "Musgrove",
      "Save": null,
      "Time": "3:30",
      "Attendance": 38925.0,
      "Streak": 1.0,
      "Year": 2019,
      "Date": "2019-05-09",
      "Winner": "STL"
    },
    {
      "Unnamed_0": 33244,
      "Tm": "STL",
      "Home_Away": "Home",
      "Opp": "PIT",
      "W_or_L": "L",
      "R": 1.0,
      "RA": 2.0,
      "Inn": 9.0,
      "Record": "22-17",
      "Rank": 3.0,
      "GB": "1.5",
      "Win": "Williams",
      "Loss": "Miller",
      "Save": "Vazquez",
      "Time": "2:54",
      "Attendance": 45060.0,
      "Streak": -1.0,
      "Year": 2019,
      "Date": "2019-05-10",
      "Winner": "PIT"
    },
    {
      "Unnamed_0": 33245,
      "Tm": "STL",
      "Home_Away": "Home",
      "Opp": "PIT",
      "W_or_L": "L",
      "R": 1.0,
      "RA": 2.0,
      "Inn": 9.0,
      "Record": "22-18",
      "Rank": 3.0,
      "GB": "2.5",
      "Win": "Lyles",
      "Loss": "Mikolas",
      "Save": "Vazquez",
      "Time": "2:42",
      "Attendance": 43011.0,
      "Streak": -2.0,
      "Year": 2019,
      "Date": "2019-05-11",
      "Winner": "PIT"
    },
    {
      "Unnamed_0": 33246,
      "Tm": "STL",
      "Home_Away": "Home",
      "Opp": "PIT",
      "W_or_L": "L",
      "R": 6.0,
      "RA": 10.0,
      "Inn": 9.0,
      "Record": "22-19",
      "Rank": 3.0,
      "GB": "3.5",
      "Win": "Stratton",
      "Loss": "Brebbia",
      "Save": null,
      "Time": "3:29",
      "Attendance": 48555.0,
      "Streak": -3.0,
      "Year": 2019,
      "Date": "2019-05-12",
      "Winner": "PIT"
    },
    {
      "Unnamed_0": 33247,
      "Tm": "STL",
      "Home_Away": "@",
      "Opp": "ATL",
      "W_or_L": "W",
      "R": 14.0,
      "RA": 3.0,
      "Inn": 9.0,
      "Record": "23-19",
      "Rank": 3.0,
      "GB": "3.5",
      "Win": "Flaherty",
      "Loss": "Foltynewicz",
      "Save": null,
      "Time": "3:00",
      "Attendance": 23718.0,
      "Streak": 1.0,
      "Year": 2019,
      "Date": "2019-05-14",
      "Winner": "STL"
    },
    {
      "Unnamed_0": 33248,
      "Tm": "STL",
      "Home_Away": "@",
      "Opp": "ATL",
      "W_or_L": "L",
      "R": 0.0,
      "RA": 4.0,
      "Inn": 9.0,
      "Record": "23-20",
      "Rank": 3.0,
      "GB": "3.5",
      "Win": "Soroka",
      "Loss": "Wacha",
      "Save": "Jackson",
      "Time": "2:40",
      "Attendance": 23367.0,
      "Streak": -1.0,
      "Year": 2019,
      "Date": "2019-05-15",
      "Winner": "ATL"
    },
    {
      "Unnamed_0": 33249,
      "Tm": "STL",
      "Home_Away": "@",
      "Opp": "ATL",
      "W_or_L": "L",
      "R": 2.0,
      "RA": 10.0,
      "Inn": 9.0,
      "Record": "23-21",
      "Rank": 3.0,
      "GB": "3.5",
      "Win": "Teheran",
      "Loss": "Wainwright",
      "Save": null,
      "Time": "3:16",
      "Attendance": 28783.0,
      "Streak": -2.0,
      "Year": 2019,
      "Date": "2019-05-16",
      "Winner": "ATL"
    },
    {
      "Unnamed_0": 33250,
      "Tm": "STL",
      "Home_Away": "@",
      "Opp": "TEX",
      "W_or_L": "L",
      "R": 3.0,
      "RA": 7.0,
      "Inn": 9.0,
      "Record": "23-22",
      "Rank": 4.0,
      "GB": "4.5",
      "Win": "Sampson",
      "Loss": "Mikolas",
      "Save": null,
      "Time": "2:59",
      "Attendance": 34398.0,
      "Streak": -3.0,
      "Year": 2019,
      "Date": "2019-05-17",
      "Winner": "TEX"
    },
    {
      "Unnamed_0": 33251,
      "Tm": "STL",
      "Home_Away": "@",
      "Opp": "TEX",
      "W_or_L": "W",
      "R": 8.0,
      "RA": 2.0,
      "Inn": 9.0,
      "Record": "24-22",
      "Rank": 4.0,
      "GB": "3.5",
      "Win": "Hudson",
      "Loss": "Jurado",
      "Save": null,
      "Time": "3:14",
      "Attendance": 30967.0,
      "Streak": 1.0,
      "Year": 2019,
      "Date": "2019-05-18",
      "Winner": "STL"
    },
    {
      "Unnamed_0": 33252,
      "Tm": "STL",
      "Home_Away": "@",
      "Opp": "TEX",
      "W_or_L": "L-wo",
      "R": 4.0,
      "RA": 5.0,
      "Inn": 10.0,
      "Record": "24-23",
      "Rank": 4.0,
      "GB": "4.5",
      "Win": "G\u00f3mez",
      "Loss": "Hicks",
      "Save": null,
      "Time": "3:41",
      "Attendance": 32112.0,
      "Streak": -1.0,
      "Year": 2019,
      "Date": "2019-05-19",
      "Winner": "TEX-wo"
    },
    {
      "Unnamed_0": 33253,
      "Tm": "STL",
      "Home_Away": "Home",
      "Opp": "KCR",
      "W_or_L": "L",
      "R": 2.0,
      "RA": 8.0,
      "Inn": 9.0,
      "Record": "24-24",
      "Rank": 4.0,
      "GB": "5.0",
      "Win": "Keller",
      "Loss": "Wacha",
      "Save": null,
      "Time": "2:44",
      "Attendance": 42725.0,
      "Streak": -2.0,
      "Year": 2019,
      "Date": "2019-05-22",
      "Winner": "KCR"
    },
    {
      "Unnamed_0": 33254,
      "Tm": "STL",
      "Home_Away": "Home",
      "Opp": "KCR",
      "W_or_L": "W",
      "R": 10.0,
      "RA": 3.0,
      "Inn": 9.0,
      "Record": "25-24",
      "Rank": 4.0,
      "GB": "5.0",
      "Win": "Wainwright",
      "Loss": "Bailey",
      "Save": null,
      "Time": "3:30",
      "Attendance": 42529.0,
      "Streak": 1.0,
      "Year": 2019,
      "Date": "2019-05-22",
      "Winner": "STL"
    },
    {
      "Unnamed_0": 33255,
      "Tm": "STL",
      "Home_Away": "Home",
      "Opp": "ATL",
      "W_or_L": "L",
      "R": 2.0,
      "RA": 5.0,
      "Inn": 9.0,
      "Record": "25-25",
      "Rank": 4.0,
      "GB": "4.5",
      "Win": "Foltynewicz",
      "Loss": "Mikolas",
      "Save": null,
      "Time": "2:44",
      "Attendance": 44630.0,
      "Streak": -1.0,
      "Year": 2019,
      "Date": "2019-05-24",
      "Winner": "ATL"
    },
    {
      "Unnamed_0": 33256,
      "Tm": "STL",
      "Home_Away": "Home",
      "Opp": "ATL",
      "W_or_L": "W",
      "R": 6.0,
      "RA": 3.0,
      "Inn": 9.0,
      "Record": "26-25",
      "Rank": 3.0,
      "GB": "4.5",
      "Win": "Miller",
      "Loss": "Winkler",
      "Save": "Hicks",
      "Time": "2:40",
      "Attendance": 45760.0,
      "Streak": 1.0,
      "Year": 2019,
      "Date": "2019-05-25",
      "Winner": "STL"
    },
    {
      "Unnamed_0": 33257,
      "Tm": "STL",
      "Home_Away": "Home",
      "Opp": "ATL",
      "W_or_L": "L",
      "R": 3.0,
      "RA": 4.0,
      "Inn": 10.0,
      "Record": "26-26",
      "Rank": 3.0,
      "GB": "4.5",
      "Win": "Webb",
      "Loss": "Webb",
      "Save": "Jackson",
      "Time": "4:07",
      "Attendance": 45152.0,
      "Streak": -1.0,
      "Year": 2019,
      "Date": "2019-05-26",
      "Winner": "ATL"
    },
    {
      "Unnamed_0": 33258,
      "Tm": "STL",
      "Home_Away": "@",
      "Opp": "PHI",
      "W_or_L": "L",
      "R": 3.0,
      "RA": 4.0,
      "Inn": 9.0,
      "Record": "26-27",
      "Rank": 3.0,
      "GB": "4.0",
      "Win": "Pivetta",
      "Loss": "Wainwright",
      "Save": "Neris",
      "Time": "2:28",
      "Attendance": 29084.0,
      "Streak": -2.0,
      "Year": 2019,
      "Date": "2019-05-28",
      "Winner": "PHI"
    },
    {
      "Unnamed_0": 33259,
      "Tm": "STL",
      "Home_Away": "@",
      "Opp": "PHI",
      "W_or_L": "L",
      "R": 4.0,
      "RA": 11.0,
      "Inn": 9.0,
      "Record": "26-28",
      "Rank": 4.0,
      "GB": "5.0",
      "Win": "Nola",
      "Loss": "Cabrera",
      "Save": null,
      "Time": "3:01",
      "Attendance": 30486.0,
      "Streak": -3.0,
      "Year": 2019,
      "Date": "2019-05-29",
      "Winner": "PHI"
    },
    {
      "Unnamed_0": 33260,
      "Tm": "STL",
      "Home_Away": "@",
      "Opp": "PHI",
      "W_or_L": "W",
      "R": 5.0,
      "RA": 3.0,
      "Inn": 9.0,
      "Record": "27-28",
      "Rank": 3.0,
      "GB": "4.5",
      "Win": "Hudson",
      "Loss": "Eickhoff",
      "Save": "Hicks",
      "Time": "3:01",
      "Attendance": 31206.0,
      "Streak": 1.0,
      "Year": 2019,
      "Date": "2019-05-30",
      "Winner": "STL"
    },
    {
      "Unnamed_0": 33261,
      "Tm": "STL",
      "Home_Away": "Home",
      "Opp": "CHC",
      "W_or_L": "W-wo",
      "R": 2.0,
      "RA": 1.0,
      "Inn": 10.0,
      "Record": "28-28",
      "Rank": 3.0,
      "GB": "3.5",
      "Win": "Hicks",
      "Loss": "Montgomery",
      "Save": null,
      "Time": "3:24",
      "Attendance": 45321.0,
      "Streak": 2.0,
      "Year": 2019,
      "Date": "2019-05-31",
      "Winner": "STL-wo"
    },
    {
      "Unnamed_0": 33262,
      "Tm": "STL",
      "Home_Away": "Home",
      "Opp": "CHC",
      "W_or_L": "W",
      "R": 7.0,
      "RA": 4.0,
      "Inn": 9.0,
      "Record": "29-28",
      "Rank": 3.0,
      "GB": "3.0",
      "Win": "Gant",
      "Loss": "Chatwood",
      "Save": "Martinez",
      "Time": "3:04",
      "Attendance": 46297.0,
      "Streak": 3.0,
      "Year": 2019,
      "Date": "2019-06-01",
      "Winner": "STL"
    },
    {
      "Unnamed_0": 33263,
      "Tm": "STL",
      "Home_Away": "Home",
      "Opp": "CHC",
      "W_or_L": "W",
      "R": 2.0,
      "RA": 1.0,
      "Inn": 9.0,
      "Record": "30-28",
      "Rank": 3.0,
      "GB": "3.0",
      "Win": "Wainwright",
      "Loss": "Hamels",
      "Save": "Gant",
      "Time": "2:38",
      "Attendance": 46053.0,
      "Streak": 4.0,
      "Year": 2019,
      "Date": "2019-06-02",
      "Winner": "STL"
    },
    {
      "Unnamed_0": 33264,
      "Tm": "STL",
      "Home_Away": "Home",
      "Opp": "CIN",
      "W_or_L": "L",
      "R": 1.0,
      "RA": 4.0,
      "Inn": 9.0,
      "Record": "30-29",
      "Rank": 3.0,
      "GB": "3.0",
      "Win": "Castillo",
      "Loss": "Cabrera",
      "Save": "Iglesias",
      "Time": "2:56",
      "Attendance": 40649.0,
      "Streak": -1.0,
      "Year": 2019,
      "Date": "2019-06-04",
      "Winner": "CIN"
    },
    {
      "Unnamed_0": 33265,
      "Tm": "STL",
      "Home_Away": "Home",
      "Opp": "CIN",
      "W_or_L": "W",
      "R": 3.0,
      "RA": 1.0,
      "Inn": 9.0,
      "Record": "31-29",
      "Rank": 3.0,
      "GB": "2.5",
      "Win": "Gant",
      "Loss": "Lorenzen",
      "Save": "Hicks",
      "Time": "2:58",
      "Attendance": 44654.0,
      "Streak": 1.0,
      "Year": 2019,
      "Date": "2019-06-06",
      "Winner": "STL"
    },
    {
      "Unnamed_0": 33266,
      "Tm": "STL",
      "Home_Away": "@",
      "Opp": "CHC",
      "W_or_L": "L",
      "R": 1.0,
      "RA": 3.0,
      "Inn": 9.0,
      "Record": "31-30",
      "Rank": 3.0,
      "GB": "3.5",
      "Win": "Hamels",
      "Loss": "Mikolas",
      "Save": "Strop",
      "Time": "2:39",
      "Attendance": 40671.0,
      "Streak": -1.0,
      "Year": 2019,
      "Date": "2019-06-07",
      "Winner": "CHC"
    },
    {
      "Unnamed_0": 33267,
      "Tm": "STL",
      "Home_Away": "@",
      "Opp": "CHC",
      "W_or_L": "L",
      "R": 4.0,
      "RA": 9.0,
      "Inn": 9.0,
      "Record": "31-31",
      "Rank": 3.0,
      "GB": "4.5",
      "Win": "Lester",
      "Loss": "Brebbia",
      "Save": null,
      "Time": "3:27",
      "Attendance": 41005.0,
      "Streak": -2.0,
      "Year": 2019,
      "Date": "2019-06-08",
      "Winner": "CHC"
    },
    {
      "Unnamed_0": 33268,
      "Tm": "STL",
      "Home_Away": "@",
      "Opp": "CHC",
      "W_or_L": "L",
      "R": 1.0,
      "RA": 5.0,
      "Inn": 9.0,
      "Record": "31-32",
      "Rank": 3.0,
      "GB": "5.5",
      "Win": "Hendricks",
      "Loss": "Wainwright",
      "Save": "Strop",
      "Time": "2:48",
      "Attendance": 39545.0,
      "Streak": -3.0,
      "Year": 2019,
      "Date": "2019-06-09",
      "Winner": "CHC"
    },
    {
      "Unnamed_0": 33269,
      "Tm": "STL",
      "Home_Away": "@",
      "Opp": "MIA",
      "W_or_L": "W",
      "R": 4.0,
      "RA": 1.0,
      "Inn": 9.0,
      "Record": "32-32",
      "Rank": 3.0,
      "GB": "5.0",
      "Win": "Wacha",
      "Loss": "Alcantara",
      "Save": "Hicks",
      "Time": "2:49",
      "Attendance": 6585.0,
      "Streak": 1.0,
      "Year": 2019,
      "Date": "2019-06-10",
      "Winner": "STL"
    },
    {
      "Unnamed_0": 33270,
      "Tm": "STL",
      "Home_Away": "@",
      "Opp": "MIA",
      "W_or_L": "W",
      "R": 7.0,
      "RA": 1.0,
      "Inn": 9.0,
      "Record": "33-32",
      "Rank": 3.0,
      "GB": "4.0",
      "Win": "Hudson",
      "Loss": "Hern\u00e1ndez",
      "Save": null,
      "Time": "3:12",
      "Attendance": 6308.0,
      "Streak": 2.0,
      "Year": 2019,
      "Date": "2019-06-11",
      "Winner": "STL"
    },
    {
      "Unnamed_0": 33271,
      "Tm": "STL",
      "Home_Away": "@",
      "Opp": "MIA",
      "W_or_L": "L",
      "R": 0.0,
      "RA": 9.0,
      "Inn": 9.0,
      "Record": "33-33",
      "Rank": 3.0,
      "GB": "5.0",
      "Win": "Yamamoto",
      "Loss": "Mikolas",
      "Save": null,
      "Time": "2:34",
      "Attendance": 7001.0,
      "Streak": -1.0,
      "Year": 2019,
      "Date": "2019-06-12",
      "Winner": "MIA"
    },
    {
      "Unnamed_0": 33272,
      "Tm": "STL",
      "Home_Away": "@",
      "Opp": "NYM",
      "W_or_L": "W",
      "R": 5.0,
      "RA": 4.0,
      "Inn": 10.0,
      "Record": "34-33",
      "Rank": 3.0,
      "GB": "4.5",
      "Win": "Martinez",
      "Loss": "D\u00edaz",
      "Save": "Hicks",
      "Time": "3:02",
      "Attendance": 31862.0,
      "Streak": 1.0,
      "Year": 2019,
      "Date": "2019-06-13",
      "Winner": "STL"
    },
    {
      "Unnamed_0": 33273,
      "Tm": "STL",
      "Home_Away": "@",
      "Opp": "NYM",
      "W_or_L": "W",
      "R": 9.0,
      "RA": 5.0,
      "Inn": 9.0,
      "Record": "35-33",
      "Rank": 3.0,
      "GB": "3.5",
      "Win": "Gant",
      "Loss": "Familia",
      "Save": null,
      "Time": "3:05",
      "Attendance": 28560.0,
      "Streak": 2.0,
      "Year": 2019,
      "Date": "2019-06-14",
      "Winner": "STL"
    },
    {
      "Unnamed_0": 33274,
      "Tm": "STL",
      "Home_Away": "@",
      "Opp": "NYM",
      "W_or_L": "L",
      "R": 7.0,
      "RA": 8.0,
      "Inn": 9.0,
      "Record": "35-34",
      "Rank": 3.0,
      "GB": "3.5",
      "Win": "Syndergaard",
      "Loss": "Wacha",
      "Save": "D\u00edaz",
      "Time": "3:33",
      "Attendance": 32589.0,
      "Streak": -1.0,
      "Year": 2019,
      "Date": "2019-06-15",
      "Winner": "NYM"
    },
    {
      "Unnamed_0": 33275,
      "Tm": "STL",
      "Home_Away": "@",
      "Opp": "NYM",
      "W_or_L": "W",
      "R": 4.0,
      "RA": 3.0,
      "Inn": 9.0,
      "Record": "36-34",
      "Rank": 3.0,
      "GB": "3.5",
      "Win": "Miller",
      "Loss": "Flexen",
      "Save": "Martinez",
      "Time": "3:09",
      "Attendance": 37054.0,
      "Streak": 1.0,
      "Year": 2019,
      "Date": "2019-06-16",
      "Winner": "STL"
    },
    {
      "Unnamed_0": 33276,
      "Tm": "STL",
      "Home_Away": "Home",
      "Opp": "MIA",
      "W_or_L": "W",
      "R": 5.0,
      "RA": 0.0,
      "Inn": 9.0,
      "Record": "37-34",
      "Rank": 3.0,
      "GB": "2.5",
      "Win": "Mikolas",
      "Loss": "Hern\u00e1ndez",
      "Save": null,
      "Time": "2:39",
      "Attendance": 41274.0,
      "Streak": 2.0,
      "Year": 2019,
      "Date": "2019-06-17",
      "Winner": "STL"
    },
    {
      "Unnamed_0": 33277,
      "Tm": "STL",
      "Home_Away": "Home",
      "Opp": "MIA",
      "W_or_L": "L",
      "R": 0.0,
      "RA": 6.0,
      "Inn": 9.0,
      "Record": "37-35",
      "Rank": 3.0,
      "GB": "2.5",
      "Win": "Yamamoto",
      "Loss": "Flaherty",
      "Save": null,
      "Time": "2:43",
      "Attendance": 41467.0,
      "Streak": -1.0,
      "Year": 2019,
      "Date": "2019-06-18",
      "Winner": "MIA"
    },
    {
      "Unnamed_0": 33278,
      "Tm": "STL",
      "Home_Away": "Home",
      "Opp": "MIA",
      "W_or_L": "W-wo",
      "R": 2.0,
      "RA": 1.0,
      "Inn": 11.0,
      "Record": "38-35",
      "Rank": 3.0,
      "GB": "2.0",
      "Win": "Gant",
      "Loss": "Conley",
      "Save": null,
      "Time": "3:34",
      "Attendance": 40126.0,
      "Streak": 1.0,
      "Year": 2019,
      "Date": "2019-06-19",
      "Winner": "STL-wo"
    },
    {
      "Unnamed_0": 33279,
      "Tm": "STL",
      "Home_Away": "Home",
      "Opp": "MIA",
      "W_or_L": "L",
      "R": 6.0,
      "RA": 7.0,
      "Inn": 11.0,
      "Record": "38-36",
      "Rank": 3.0,
      "GB": "3.0",
      "Win": "Garc\u00eda",
      "Loss": "Miller",
      "Save": "Romo",
      "Time": "4:31",
      "Attendance": 42446.0,
      "Streak": -1.0,
      "Year": 2019,
      "Date": "2019-06-20",
      "Winner": "MIA"
    },
    {
      "Unnamed_0": 33280,
      "Tm": "STL",
      "Home_Away": "Home",
      "Opp": "LAA",
      "W_or_L": "W",
      "R": 5.0,
      "RA": 1.0,
      "Inn": 9.0,
      "Record": "39-36",
      "Rank": 3.0,
      "GB": "2.0",
      "Win": "Wacha",
      "Loss": "Canning",
      "Save": null,
      "Time": "3:24",
      "Attendance": 48423.0,
      "Streak": 1.0,
      "Year": 2019,
      "Date": "2019-06-21",
      "Winner": "STL"
    },
    {
      "Unnamed_0": 33281,
      "Tm": "STL",
      "Home_Away": "Home",
      "Opp": "LAA",
      "W_or_L": "W",
      "R": 4.0,
      "RA": 2.0,
      "Inn": 9.0,
      "Record": "40-36",
      "Rank": 3.0,
      "GB": "1.0",
      "Win": "Hudson",
      "Loss": "Pe\u00f1a",
      "Save": "Webb",
      "Time": "2:59",
      "Attendance": 46711.0,
      "Streak": 2.0,
      "Year": 2019,
      "Date": "2019-06-22",
      "Winner": "STL"
    },
    {
      "Unnamed_0": 33282,
      "Tm": "STL",
      "Home_Away": "Home",
      "Opp": "LAA",
      "W_or_L": "L",
      "R": 4.0,
      "RA": 6.0,
      "Inn": 9.0,
      "Record": "40-37",
      "Rank": 3.0,
      "GB": "2.0",
      "Win": "Skaggs",
      "Loss": "Mikolas",
      "Save": null,
      "Time": "3:42",
      "Attendance": 47114.0,
      "Streak": -1.0,
      "Year": 2019,
      "Date": "2019-06-23",
      "Winner": "LAA"
    },
    {
      "Unnamed_0": 33283,
      "Tm": "STL",
      "Home_Away": "Home",
      "Opp": "OAK",
      "W_or_L": "L",
      "R": 3.0,
      "RA": 7.0,
      "Inn": 9.0,
      "Record": "40-38",
      "Rank": 3.0,
      "GB": "2.5",
      "Win": "Wendelken",
      "Loss": "Flaherty",
      "Save": null,
      "Time": "3:28",
      "Attendance": 40556.0,
      "Streak": -2.0,
      "Year": 2019,
      "Date": "2019-06-25",
      "Winner": "OAK"
    },
    {
      "Unnamed_0": 33284,
      "Tm": "STL",
      "Home_Away": "Home",
      "Opp": "OAK",
      "W_or_L": "L",
      "R": 0.0,
      "RA": 2.0,
      "Inn": 9.0,
      "Record": "40-39",
      "Rank": 3.0,
      "GB": "2.5",
      "Win": "Mengden",
      "Loss": "Wainwright",
      "Save": "Hendriks",
      "Time": "2:46",
      "Attendance": 44871.0,
      "Streak": -3.0,
      "Year": 2019,
      "Date": "2019-06-26",
      "Winner": "OAK"
    },
    {
      "Unnamed_0": 33285,
      "Tm": "STL",
      "Home_Away": "@",
      "Opp": "SDP",
      "W_or_L": "L",
      "R": 1.0,
      "RA": 3.0,
      "Inn": 9.0,
      "Record": "40-40",
      "Rank": 3.0,
      "GB": "3.0",
      "Win": "Quantrill",
      "Loss": "Wacha",
      "Save": "Yates",
      "Time": "2:49",
      "Attendance": 33329.0,
      "Streak": -4.0,
      "Year": 2019,
      "Date": "2019-06-28",
      "Winner": "SDP"
    },
    {
      "Unnamed_0": 33286,
      "Tm": "STL",
      "Home_Away": "@",
      "Opp": "SDP",
      "W_or_L": "L",
      "R": 2.0,
      "RA": 12.0,
      "Inn": 9.0,
      "Record": "40-41",
      "Rank": 3.0,
      "GB": "4.0",
      "Win": "Paddack",
      "Loss": "Hudson",
      "Save": null,
      "Time": "3:05",
      "Attendance": 44407.0,
      "Streak": -5.0,
      "Year": 2019,
      "Date": "2019-06-29",
      "Winner": "SDP"
    },
    {
      "Unnamed_0": 33287,
      "Tm": "STL",
      "Home_Away": "@",
      "Opp": "SDP",
      "W_or_L": "W",
      "R": 5.0,
      "RA": 3.0,
      "Inn": 11.0,
      "Record": "41-41",
      "Rank": 3.0,
      "GB": "3.0",
      "Win": "Martinez",
      "Loss": "Wieck",
      "Save": "Leone",
      "Time": "4:07",
      "Attendance": 32575.0,
      "Streak": 1.0,
      "Year": 2019,
      "Date": "2019-06-30",
      "Winner": "STL"
    },
    {
      "Unnamed_0": 33288,
      "Tm": "STL",
      "Home_Away": "@",
      "Opp": "SEA",
      "W_or_L": "L",
      "R": 4.0,
      "RA": 5.0,
      "Inn": 9.0,
      "Record": "41-42",
      "Rank": 3.0,
      "GB": "3.5",
      "Win": "Adams",
      "Loss": "Gallegos",
      "Save": "El\u00edas",
      "Time": "3:18",
      "Attendance": 20173.0,
      "Streak": -1.0,
      "Year": 2019,
      "Date": "2019-07-02",
      "Winner": "SEA"
    },
    {
      "Unnamed_0": 33289,
      "Tm": "STL",
      "Home_Away": "@",
      "Opp": "SEA",
      "W_or_L": "W",
      "R": 5.0,
      "RA": 2.0,
      "Inn": 9.0,
      "Record": "42-42",
      "Rank": 3.0,
      "GB": "2.5",
      "Win": "Brebbia",
      "Loss": "Adams",
      "Save": null,
      "Time": "2:58",
      "Attendance": 31876.0,
      "Streak": 1.0,
      "Year": 2019,
      "Date": "2019-07-03",
      "Winner": "STL"
    },
    {
      "Unnamed_0": 33290,
      "Tm": "STL",
      "Home_Away": "@",
      "Opp": "SEA",
      "W_or_L": "W",
      "R": 5.0,
      "RA": 4.0,
      "Inn": 9.0,
      "Record": "43-42",
      "Rank": 3.0,
      "GB": "1.5",
      "Win": "Ponce\u00a0de\u00a0Leon",
      "Loss": "Milone",
      "Save": "Martinez",
      "Time": "2:45",
      "Attendance": 26673.0,
      "Streak": 2.0,
      "Year": 2019,
      "Date": "2019-07-04",
      "Winner": "STL"
    },
    {
      "Unnamed_0": 33291,
      "Tm": "STL",
      "Home_Away": "@",
      "Opp": "SFG",
      "W_or_L": "W",
      "R": 9.0,
      "RA": 4.0,
      "Inn": 9.0,
      "Record": "44-42",
      "Rank": 3.0,
      "GB": "1.5",
      "Win": "Hudson",
      "Loss": "Pomeranz",
      "Save": null,
      "Time": "3:23",
      "Attendance": 37603.0,
      "Streak": 3.0,
      "Year": 2019,
      "Date": "2019-07-05",
      "Winner": "STL"
    },
    {
      "Unnamed_0": 33292,
      "Tm": "STL",
      "Home_Away": "@",
      "Opp": "SFG",
      "W_or_L": "L",
      "R": 4.0,
      "RA": 8.0,
      "Inn": 9.0,
      "Record": "44-43",
      "Rank": 3.0,
      "GB": "2.0",
      "Win": "Dyson",
      "Loss": "Mikolas",
      "Save": null,
      "Time": "3:13",
      "Attendance": 32487.0,
      "Streak": -1.0,
      "Year": 2019,
      "Date": "2019-07-06",
      "Winner": "SFG"
    },
    {
      "Unnamed_0": 33293,
      "Tm": "STL",
      "Home_Away": "@",
      "Opp": "SFG",
      "W_or_L": "L",
      "R": 0.0,
      "RA": 1.0,
      "Inn": 9.0,
      "Record": "44-44",
      "Rank": 3.0,
      "GB": "2.0",
      "Win": "Samardzija",
      "Loss": "Flaherty",
      "Save": "Smith",
      "Time": "2:19",
      "Attendance": 33841.0,
      "Streak": -2.0,
      "Year": 2019,
      "Date": "2019-07-07",
      "Winner": "SFG"
    },
    {
      "Unnamed_0": 33294,
      "Tm": "STL",
      "Home_Away": "Home",
      "Opp": "ARI",
      "W_or_L": "L",
      "R": 2.0,
      "RA": 4.0,
      "Inn": 9.0,
      "Record": "44-45",
      "Rank": 3.0,
      "GB": "3.0",
      "Win": "Ray",
      "Loss": "Miller",
      "Save": "Holland",
      "Time": "2:56",
      "Attendance": 44960.0,
      "Streak": -3.0,
      "Year": 2019,
      "Date": "2019-07-12",
      "Winner": "ARI"
    },
    {
      "Unnamed_0": 33295,
      "Tm": "STL",
      "Home_Away": "Home",
      "Opp": "ARI",
      "W_or_L": "W",
      "R": 4.0,
      "RA": 2.0,
      "Inn": 9.0,
      "Record": "45-45",
      "Rank": 3.0,
      "GB": "3.0",
      "Win": "Hudson",
      "Loss": "Kelly",
      "Save": "Martinez",
      "Time": "3:04",
      "Attendance": 46152.0,
      "Streak": 1.0,
      "Year": 2019,
      "Date": "2019-07-13",
      "Winner": "STL"
    },
    {
      "Unnamed_0": 33296,
      "Tm": "STL",
      "Home_Away": "Home",
      "Opp": "ARI",
      "W_or_L": "W",
      "R": 5.0,
      "RA": 2.0,
      "Inn": 9.0,
      "Record": "46-45",
      "Rank": 3.0,
      "GB": "3.0",
      "Win": "Wainwright",
      "Loss": "Greinke",
      "Save": "Martinez",
      "Time": "2:52",
      "Attendance": 43439.0,
      "Streak": 2.0,
      "Year": 2019,
      "Date": "2019-07-14",
      "Winner": "STL"
    },
    {
      "Unnamed_0": 33297,
      "Tm": "STL",
      "Home_Away": "Home",
      "Opp": "PIT",
      "W_or_L": "W",
      "R": 7.0,
      "RA": 0.0,
      "Inn": 9.0,
      "Record": "47-45",
      "Rank": 2.0,
      "GB": "2.0",
      "Win": "Mikolas",
      "Loss": "Musgrove",
      "Save": null,
      "Time": "3:00",
      "Attendance": 41965.0,
      "Streak": 3.0,
      "Year": 2019,
      "Date": "2019-07-15",
      "Winner": "STL"
    },
    {
      "Unnamed_0": 33298,
      "Tm": "STL",
      "Home_Away": "Home",
      "Opp": "PIT",
      "W_or_L": "L",
      "R": 1.0,
      "RA": 3.0,
      "Inn": 9.0,
      "Record": "47-46",
      "Rank": 3.0,
      "GB": "3.0",
      "Win": "Liriano",
      "Loss": "Martinez",
      "Save": "Vazquez",
      "Time": "3:04",
      "Attendance": 43777.0,
      "Streak": -1.0,
      "Year": 2019,
      "Date": "2019-07-16",
      "Winner": "PIT"
    },
    {
      "Unnamed_0": 33299,
      "Tm": "STL",
      "Home_Away": "Home",
      "Opp": "PIT",
      "W_or_L": "W",
      "R": 6.0,
      "RA": 5.0,
      "Inn": 9.0,
      "Record": "48-46",
      "Rank": 3.0,
      "GB": "3.0",
      "Win": "Brebbia",
      "Loss": "Liriano",
      "Save": "Martinez",
      "Time": "3:11",
      "Attendance": 43186.0,
      "Streak": 1.0,
      "Year": 2019,
      "Date": "2019-07-17",
      "Winner": "STL"
    },
    {
      "Unnamed_0": 33300,
      "Tm": "STL",
      "Home_Away": "@",
      "Opp": "CIN",
      "W_or_L": "W",
      "R": 7.0,
      "RA": 4.0,
      "Inn": 9.0,
      "Record": "49-46",
      "Rank": 3.0,
      "GB": "2.5",
      "Win": "Hudson",
      "Loss": "Stephenson",
      "Save": "Miller",
      "Time": "3:17",
      "Attendance": 32359.0,
      "Streak": 2.0,
      "Year": 2019,
      "Date": "2019-07-18",
      "Winner": "STL"
    },
    {
      "Unnamed_0": 33301,
      "Tm": "STL",
      "Home_Away": "@",
      "Opp": "CIN",
      "W_or_L": "W",
      "R": 12.0,
      "RA": 11.0,
      "Inn": 9.0,
      "Record": "50-46",
      "Rank": 2.0,
      "GB": "2.5",
      "Win": "Wacha",
      "Loss": "Hughes",
      "Save": "Martinez",
      "Time": "3:49",
      "Attendance": 37652.0,
      "Streak": 3.0,
      "Year": 2019,
      "Date": "2019-07-19",
      "Winner": "STL"
    },
    {
      "Unnamed_0": 33302,
      "Tm": "STL",
      "Home_Away": "@",
      "Opp": "CIN",
      "W_or_L": "L",
      "R": 2.0,
      "RA": 3.0,
      "Inn": 9.0,
      "Record": "50-47",
      "Rank": 3.0,
      "GB": "3.5",
      "Win": "Garrett",
      "Loss": "Mikolas",
      "Save": "Lorenzen",
      "Time": "2:36",
      "Attendance": 38427.0,
      "Streak": -1.0,
      "Year": 2019,
      "Date": "2019-07-20",
      "Winner": "CIN"
    },
    {
      "Unnamed_0": 33303,
      "Tm": "STL",
      "Home_Away": "@",
      "Opp": "CIN",
      "W_or_L": "W",
      "R": 3.0,
      "RA": 1.0,
      "Inn": 9.0,
      "Record": "51-47",
      "Rank": 3.0,
      "GB": "2.5",
      "Win": "Gallegos",
      "Loss": "DeSclafani",
      "Save": "Martinez",
      "Time": "3:22",
      "Attendance": 28763.0,
      "Streak": 1.0,
      "Year": 2019,
      "Date": "2019-07-21",
      "Winner": "STL"
    },
    {
      "Unnamed_0": 33304,
      "Tm": "STL",
      "Home_Away": "@",
      "Opp": "PIT",
      "W_or_L": "W",
      "R": 6.0,
      "RA": 5.0,
      "Inn": 10.0,
      "Record": "52-47",
      "Rank": 2.0,
      "GB": "1.5",
      "Win": "Shreve",
      "Loss": "Holmes",
      "Save": "Martinez",
      "Time": "4:05",
      "Attendance": 13096.0,
      "Streak": 2.0,
      "Year": 2019,
      "Date": "2019-07-22",
      "Winner": "STL"
    },
    {
      "Unnamed_0": 33305,
      "Tm": "STL",
      "Home_Away": "@",
      "Opp": "PIT",
      "W_or_L": "W",
      "R": 4.0,
      "RA": 3.0,
      "Inn": 9.0,
      "Record": "53-47",
      "Rank": 2.0,
      "GB": "0.5",
      "Win": "Hudson",
      "Loss": "Archer",
      "Save": "Miller",
      "Time": "2:46",
      "Attendance": 15778.0,
      "Streak": 3.0,
      "Year": 2019,
      "Date": "2019-07-23",
      "Winner": "STL"
    },
    {
      "Unnamed_0": 33306,
      "Tm": "STL",
      "Home_Away": "@",
      "Opp": "PIT",
      "W_or_L": "W",
      "R": 14.0,
      "RA": 8.0,
      "Inn": 9.0,
      "Record": "54-47",
      "Rank": 2.0,
      "GB": "0.5",
      "Win": "Wainwright",
      "Loss": "Lyles",
      "Save": null,
      "Time": "3:17",
      "Attendance": 18675.0,
      "Streak": 4.0,
      "Year": 2019,
      "Date": "2019-07-24",
      "Winner": "STL"
    },
    {
      "Unnamed_0": 33307,
      "Tm": "STL",
      "Home_Away": "@",
      "Opp": "PIT",
      "W_or_L": "W",
      "R": 6.0,
      "RA": 3.0,
      "Inn": 9.0,
      "Record": "55-47",
      "Rank": 1.0,
      "GB": "Tied",
      "Win": "Mikolas",
      "Loss": "Musgrove",
      "Save": null,
      "Time": "2:45",
      "Attendance": 24534.0,
      "Streak": 5.0,
      "Year": 2019,
      "Date": "2019-07-25",
      "Winner": "STL"
    },
    {
      "Unnamed_0": 33308,
      "Tm": "STL",
      "Home_Away": "Home",
      "Opp": "HOU",
      "W_or_L": "W",
      "R": 5.0,
      "RA": 3.0,
      "Inn": 9.0,
      "Record": "56-47",
      "Rank": 1.0,
      "GB": "up 1.0",
      "Win": "Miller",
      "Loss": "Pressly",
      "Save": "Martinez",
      "Time": "3:09",
      "Attendance": 44724.0,
      "Streak": 6.0,
      "Year": 2019,
      "Date": "2019-07-26",
      "Winner": "STL"
    },
    {
      "Unnamed_0": 33309,
      "Tm": "STL",
      "Home_Away": "Home",
      "Opp": "HOU",
      "W_or_L": "L",
      "R": 2.0,
      "RA": 8.0,
      "Inn": 9.0,
      "Record": "56-48",
      "Rank": 1.0,
      "GB": "up 1.0",
      "Win": "Cole",
      "Loss": "Ponce\u00a0de\u00a0Leon",
      "Save": null,
      "Time": "3:07",
      "Attendance": 46518.0,
      "Streak": -1.0,
      "Year": 2019,
      "Date": "2019-07-27",
      "Winner": "HOU"
    },
    {
      "Unnamed_0": 33310,
      "Tm": "STL",
      "Home_Away": "Home",
      "Opp": "HOU",
      "W_or_L": "L",
      "R": 2.0,
      "RA": 6.0,
      "Inn": 9.0,
      "Record": "56-49",
      "Rank": 1.0,
      "GB": "Tied",
      "Win": "Miley",
      "Loss": "Hudson",
      "Save": null,
      "Time": "3:24",
      "Attendance": 46714.0,
      "Streak": -2.0,
      "Year": 2019,
      "Date": "2019-07-28",
      "Winner": "HOU"
    },
    {
      "Unnamed_0": 33311,
      "Tm": "STL",
      "Home_Away": "Home",
      "Opp": "CHC",
      "W_or_L": "W",
      "R": 2.0,
      "RA": 1.0,
      "Inn": 9.0,
      "Record": "57-49",
      "Rank": 1.0,
      "GB": "up 1.0",
      "Win": "Gallegos",
      "Loss": "Darvish",
      "Save": "Martinez",
      "Time": "3:05",
      "Attendance": 46123.0,
      "Streak": 1.0,
      "Year": 2019,
      "Date": "2019-07-30",
      "Winner": "STL"
    },
    {
      "Unnamed_0": 33312,
      "Tm": "STL",
      "Home_Away": "Home",
      "Opp": "CHC",
      "W_or_L": "L",
      "R": 0.0,
      "RA": 2.0,
      "Inn": 9.0,
      "Record": "57-50",
      "Rank": 1.0,
      "GB": "Tied",
      "Win": "Hendricks",
      "Loss": "Mikolas",
      "Save": "Kimbrel",
      "Time": "3:14",
      "Attendance": 43750.0,
      "Streak": -1.0,
      "Year": 2019,
      "Date": "2019-07-31",
      "Winner": "CHC"
    },
    {
      "Unnamed_0": 33313,
      "Tm": "STL",
      "Home_Away": "Home",
      "Opp": "CHC",
      "W_or_L": "W",
      "R": 8.0,
      "RA": 0.0,
      "Inn": 9.0,
      "Record": "58-50",
      "Rank": 1.0,
      "GB": "up 1.0",
      "Win": "Flaherty",
      "Loss": "Lester",
      "Save": null,
      "Time": "2:53",
      "Attendance": 46811.0,
      "Streak": 1.0,
      "Year": 2019,
      "Date": "2019-08-01",
      "Winner": "STL"
    },
    {
      "Unnamed_0": 33314,
      "Tm": "STL",
      "Home_Away": "@",
      "Opp": "OAK",
      "W_or_L": "L",
      "R": 3.0,
      "RA": 8.0,
      "Inn": 9.0,
      "Record": "58-51",
      "Rank": 2.0,
      "GB": "0.5",
      "Win": "Fiers",
      "Loss": "Hudson",
      "Save": null,
      "Time": "3:37",
      "Attendance": 24851.0,
      "Streak": -1.0,
      "Year": 2019,
      "Date": "2019-08-03",
      "Winner": "OAK"
    },
    {
      "Unnamed_0": 33315,
      "Tm": "STL",
      "Home_Away": "@",
      "Opp": "OAK",
      "W_or_L": "L",
      "R": 2.0,
      "RA": 4.0,
      "Inn": 9.0,
      "Record": "58-52",
      "Rank": 2.0,
      "GB": "1.5",
      "Win": "Roark",
      "Loss": "Wainwright",
      "Save": "Hendriks",
      "Time": "3:14",
      "Attendance": 24603.0,
      "Streak": -2.0,
      "Year": 2019,
      "Date": "2019-08-04",
      "Winner": "OAK"
    },
    {
      "Unnamed_0": 33316,
      "Tm": "STL",
      "Home_Away": "@",
      "Opp": "LAD",
      "W_or_L": "L",
      "R": 0.0,
      "RA": 8.0,
      "Inn": 9.0,
      "Record": "58-53",
      "Rank": 2.0,
      "GB": "2.5",
      "Win": "Gonsolin",
      "Loss": "Wacha",
      "Save": null,
      "Time": "2:59",
      "Attendance": 45254.0,
      "Streak": -3.0,
      "Year": 2019,
      "Date": "2019-08-05",
      "Winner": "LAD"
    },
    {
      "Unnamed_0": 33317,
      "Tm": "STL",
      "Home_Away": "@",
      "Opp": "LAD",
      "W_or_L": "L",
      "R": 1.0,
      "RA": 3.0,
      "Inn": 9.0,
      "Record": "58-54",
      "Rank": 2.0,
      "GB": "2.5",
      "Win": "Kershaw",
      "Loss": "Mikolas",
      "Save": "Jansen",
      "Time": "2:55",
      "Attendance": 53070.0,
      "Streak": -4.0,
      "Year": 2019,
      "Date": "2019-08-06",
      "Winner": "LAD"
    },
    {
      "Unnamed_0": 33318,
      "Tm": "STL",
      "Home_Away": "@",
      "Opp": "LAD",
      "W_or_L": "L-wo",
      "R": 1.0,
      "RA": 2.0,
      "Inn": 9.0,
      "Record": "58-55",
      "Rank": 3.0,
      "GB": "3.5",
      "Win": "Sadler",
      "Loss": "Martinez",
      "Save": null,
      "Time": "3:01",
      "Attendance": 48994.0,
      "Streak": -5.0,
      "Year": 2019,
      "Date": "2019-08-07",
      "Winner": "LAD-wo"
    },
    {
      "Unnamed_0": 33319,
      "Tm": "STL",
      "Home_Away": "Home",
      "Opp": "PIT",
      "W_or_L": "W",
      "R": 6.0,
      "RA": 2.0,
      "Inn": 9.0,
      "Record": "59-55",
      "Rank": 3.0,
      "GB": "3.0",
      "Win": "Martinez",
      "Loss": "Rodr\u00edguez",
      "Save": null,
      "Time": "2:52",
      "Attendance": 42757.0,
      "Streak": 1.0,
      "Year": 2019,
      "Date": "2019-08-09",
      "Winner": "STL"
    },
    {
      "Unnamed_0": 33320,
      "Tm": "STL",
      "Home_Away": "Home",
      "Opp": "PIT",
      "W_or_L": "W",
      "R": 3.0,
      "RA": 1.0,
      "Inn": 9.0,
      "Record": "60-55",
      "Rank": 3.0,
      "GB": "2.0",
      "Win": "Wainwright",
      "Loss": "Musgrove",
      "Save": "Martinez",
      "Time": "2:40",
      "Attendance": 45026.0,
      "Streak": 2.0,
      "Year": 2019,
      "Date": "2019-08-10",
      "Winner": "STL"
    },
    {
      "Unnamed_0": 33321,
      "Tm": "STL",
      "Home_Away": "Home",
      "Opp": "PIT",
      "W_or_L": "W",
      "R": 11.0,
      "RA": 9.0,
      "Inn": 9.0,
      "Record": "61-55",
      "Rank": 2.0,
      "GB": "2.0",
      "Win": "Gant",
      "Loss": "Crick",
      "Save": "Miller",
      "Time": "3:40",
      "Attendance": 43912.0,
      "Streak": 3.0,
      "Year": 2019,
      "Date": "2019-08-11",
      "Winner": "STL"
    },
    {
      "Unnamed_0": 33322,
      "Tm": "STL",
      "Home_Away": "@",
      "Opp": "KCR",
      "W_or_L": "W",
      "R": 2.0,
      "RA": 0.0,
      "Inn": 9.0,
      "Record": "62-55",
      "Rank": 2.0,
      "GB": "1.0",
      "Win": "Flaherty",
      "Loss": "Sparkman",
      "Save": "Martinez",
      "Time": "2:54",
      "Attendance": 23563.0,
      "Streak": 4.0,
      "Year": 2019,
      "Date": "2019-08-13",
      "Winner": "STL"
    },
    {
      "Unnamed_0": 33323,
      "Tm": "STL",
      "Home_Away": "@",
      "Opp": "KCR",
      "W_or_L": "W",
      "R": 6.0,
      "RA": 0.0,
      "Inn": 9.0,
      "Record": "63-55",
      "Rank": 1.0,
      "GB": "Tied",
      "Win": "Hudson",
      "Loss": "Keller",
      "Save": null,
      "Time": "2:38",
      "Attendance": 22494.0,
      "Streak": 5.0,
      "Year": 2019,
      "Date": "2019-08-14",
      "Winner": "STL"
    },
    {
      "Unnamed_0": 33324,
      "Tm": "STL",
      "Home_Away": "@",
      "Opp": "CIN",
      "W_or_L": "L",
      "R": 1.0,
      "RA": 2.0,
      "Inn": 9.0,
      "Record": "63-56",
      "Rank": 1.0,
      "GB": "Tied",
      "Win": "Gray",
      "Loss": "Wacha",
      "Save": "Iglesias",
      "Time": "3:01",
      "Attendance": 14891.0,
      "Streak": -1.0,
      "Year": 2019,
      "Date": "2019-08-15",
      "Winner": "CIN"
    },
    {
      "Unnamed_0": 33325,
      "Tm": "STL",
      "Home_Away": "@",
      "Opp": "CIN",
      "W_or_L": "W",
      "R": 13.0,
      "RA": 4.0,
      "Inn": 9.0,
      "Record": "64-56",
      "Rank": 1.0,
      "GB": "up 1.0",
      "Win": "Wainwright",
      "Loss": "Castillo",
      "Save": null,
      "Time": "3:03",
      "Attendance": 24118.0,
      "Streak": 1.0,
      "Year": 2019,
      "Date": "2019-08-16",
      "Winner": "STL"
    },
    {
      "Unnamed_0": 33326,
      "Tm": "STL",
      "Home_Away": "@",
      "Opp": "CIN",
      "W_or_L": "L",
      "R": 1.0,
      "RA": 6.0,
      "Inn": 9.0,
      "Record": "64-57",
      "Rank": 1.0,
      "GB": "Tied",
      "Win": "DeSclafani",
      "Loss": "Mikolas",
      "Save": null,
      "Time": "2:59",
      "Attendance": 37698.0,
      "Streak": -1.0,
      "Year": 2019,
      "Date": "2019-08-17",
      "Winner": "CIN"
    },
    {
      "Unnamed_0": 33327,
      "Tm": "STL",
      "Home_Away": "@",
      "Opp": "CIN",
      "W_or_L": "W",
      "R": 5.0,
      "RA": 4.0,
      "Inn": 9.0,
      "Record": "65-57",
      "Rank": 1.0,
      "GB": "Tied",
      "Win": "Flaherty",
      "Loss": "Wood",
      "Save": "Martinez",
      "Time": "3:03",
      "Attendance": 21525.0,
      "Streak": 1.0,
      "Year": 2019,
      "Date": "2019-08-18",
      "Winner": "STL"
    },
    {
      "Unnamed_0": 33328,
      "Tm": "STL",
      "Home_Away": "Home",
      "Opp": "MIL",
      "W_or_L": "W",
      "R": 3.0,
      "RA": 0.0,
      "Inn": 9.0,
      "Record": "66-57",
      "Rank": 1.0,
      "GB": "up 0.5",
      "Win": "Hudson",
      "Loss": "Davies",
      "Save": "Miller",
      "Time": "2:43",
      "Attendance": 44843.0,
      "Streak": 2.0,
      "Year": 2019,
      "Date": "2019-08-19",
      "Winner": "STL"
    },
    {
      "Unnamed_0": 33329,
      "Tm": "STL",
      "Home_Away": "Home",
      "Opp": "MIL",
      "W_or_L": "W",
      "R": 9.0,
      "RA": 4.0,
      "Inn": 9.0,
      "Record": "67-57",
      "Rank": 1.0,
      "GB": "up 0.5",
      "Win": "Webb",
      "Loss": "Jeffress",
      "Save": null,
      "Time": "3:42",
      "Attendance": 37823.0,
      "Streak": 3.0,
      "Year": 2019,
      "Date": "2019-08-20",
      "Winner": "STL"
    },
    {
      "Unnamed_0": 33330,
      "Tm": "STL",
      "Home_Away": "Home",
      "Opp": "MIL",
      "W_or_L": "L",
      "R": 3.0,
      "RA": 5.0,
      "Inn": 8.0,
      "Record": "67-58",
      "Rank": 2.0,
      "GB": "0.5",
      "Win": "Houser",
      "Loss": "Wainwright",
      "Save": "Guerra",
      "Time": "2:54",
      "Attendance": 40250.0,
      "Streak": -1.0,
      "Year": 2019,
      "Date": "2019-08-21",
      "Winner": "MIL"
    },
    {
      "Unnamed_0": 33331,
      "Tm": "STL",
      "Home_Away": "Home",
      "Opp": "COL",
      "W_or_L": "W",
      "R": 6.0,
      "RA": 5.0,
      "Inn": 9.0,
      "Record": "68-58",
      "Rank": 2.0,
      "GB": "0.5",
      "Win": "Leone",
      "Loss": "Almonte",
      "Save": "Martinez",
      "Time": "2:52",
      "Attendance": 36465.0,
      "Streak": 1.0,
      "Year": 2019,
      "Date": "2019-08-22",
      "Winner": "STL"
    },
    {
      "Unnamed_0": 33332,
      "Tm": "STL",
      "Home_Away": "Home",
      "Opp": "COL",
      "W_or_L": "W",
      "R": 8.0,
      "RA": 3.0,
      "Inn": 9.0,
      "Record": "69-58",
      "Rank": 1.0,
      "GB": "up 0.5",
      "Win": "Flaherty",
      "Loss": "Lambert",
      "Save": null,
      "Time": "3:02",
      "Attendance": 40829.0,
      "Streak": 2.0,
      "Year": 2019,
      "Date": "2019-08-23",
      "Winner": "STL"
    },
    {
      "Unnamed_0": 33333,
      "Tm": "STL",
      "Home_Away": "Home",
      "Opp": "COL",
      "W_or_L": "W",
      "R": 6.0,
      "RA": 0.0,
      "Inn": 9.0,
      "Record": "70-58",
      "Rank": 1.0,
      "GB": "up 1.5",
      "Win": "Hudson",
      "Loss": "Gonz\u00e1lez",
      "Save": null,
      "Time": "2:59",
      "Attendance": 42102.0,
      "Streak": 3.0,
      "Year": 2019,
      "Date": "2019-08-24",
      "Winner": "STL"
    },
    {
      "Unnamed_0": 33334,
      "Tm": "STL",
      "Home_Away": "Home",
      "Opp": "COL",
      "W_or_L": "W",
      "R": 11.0,
      "RA": 4.0,
      "Inn": 9.0,
      "Record": "71-58",
      "Rank": 1.0,
      "GB": "up 2.5",
      "Win": "Helsley",
      "Loss": "Senzatela",
      "Save": null,
      "Time": "3:31",
      "Attendance": 45551.0,
      "Streak": 4.0,
      "Year": 2019,
      "Date": "2019-08-25",
      "Winner": "STL"
    },
    {
      "Unnamed_0": 33335,
      "Tm": "STL",
      "Home_Away": "@",
      "Opp": "MIL",
      "W_or_L": "W",
      "R": 12.0,
      "RA": 2.0,
      "Inn": 9.0,
      "Record": "72-58",
      "Rank": 1.0,
      "GB": "up 3.0",
      "Win": "Gant",
      "Loss": "Gonzalez",
      "Save": null,
      "Time": "3:34",
      "Attendance": 29475.0,
      "Streak": 5.0,
      "Year": 2019,
      "Date": "2019-08-26",
      "Winner": "STL"
    },
    {
      "Unnamed_0": 33336,
      "Tm": "STL",
      "Home_Away": "@",
      "Opp": "MIL",
      "W_or_L": "W",
      "R": 6.0,
      "RA": 3.0,
      "Inn": 9.0,
      "Record": "73-58",
      "Rank": 1.0,
      "GB": "up 3.0",
      "Win": "Mikolas",
      "Loss": "Albers",
      "Save": "Martinez",
      "Time": "3:27",
      "Attendance": 36690.0,
      "Streak": 6.0,
      "Year": 2019,
      "Date": "2019-08-27",
      "Winner": "STL"
    },
    {
      "Unnamed_0": 33337,
      "Tm": "STL",
      "Home_Away": "@",
      "Opp": "MIL",
      "W_or_L": "L",
      "R": 1.0,
      "RA": 4.0,
      "Inn": 9.0,
      "Record": "73-59",
      "Rank": 1.0,
      "GB": "up 2.0",
      "Win": "Lyles",
      "Loss": "Flaherty",
      "Save": "Hader",
      "Time": "2:50",
      "Attendance": 33045.0,
      "Streak": -1.0,
      "Year": 2019,
      "Date": "2019-08-28",
      "Winner": "MIL"
    },
    {
      "Unnamed_0": 33338,
      "Tm": "STL",
      "Home_Away": "Home",
      "Opp": "CIN",
      "W_or_L": "W",
      "R": 10.0,
      "RA": 6.0,
      "Inn": 9.0,
      "Record": "74-59",
      "Rank": 1.0,
      "GB": "up 2.5",
      "Win": "Hudson",
      "Loss": "Bauer",
      "Save": null,
      "Time": "3:10",
      "Attendance": 44738.0,
      "Streak": 1.0,
      "Year": 2019,
      "Date": "2019-08-31",
      "Winner": "STL"
    },
    {
      "Unnamed_0": 33339,
      "Tm": "STL",
      "Home_Away": "Home",
      "Opp": "CIN",
      "W_or_L": "W-wo",
      "R": 3.0,
      "RA": 2.0,
      "Inn": 9.0,
      "Record": "75-59",
      "Rank": 1.0,
      "GB": "up 2.5",
      "Win": "Gant",
      "Loss": "Iglesias",
      "Save": null,
      "Time": "2:53",
      "Attendance": 42074.0,
      "Streak": 2.0,
      "Year": 2019,
      "Date": "2019-08-31",
      "Winner": "STL-wo"
    },
    {
      "Unnamed_0": 33340,
      "Tm": "STL",
      "Home_Away": "Home",
      "Opp": "CIN",
      "W_or_L": "W-wo",
      "R": 4.0,
      "RA": 3.0,
      "Inn": 9.0,
      "Record": "76-59",
      "Rank": 1.0,
      "GB": "up 3.0",
      "Win": "Martinez",
      "Loss": "Lorenzen",
      "Save": null,
      "Time": "2:58",
      "Attendance": 43692.0,
      "Streak": 3.0,
      "Year": 2019,
      "Date": "2019-09-01",
      "Winner": "STL-wo"
    },
    {
      "Unnamed_0": 33341,
      "Tm": "STL",
      "Home_Away": "Home",
      "Opp": "CIN",
      "W_or_L": "L",
      "R": 3.0,
      "RA": 5.0,
      "Inn": 9.0,
      "Record": "76-60",
      "Rank": 1.0,
      "GB": "up 3.0",
      "Win": "Castillo",
      "Loss": "Ponce\u00a0de\u00a0Leon",
      "Save": "Iglesias",
      "Time": "3:04",
      "Attendance": 38665.0,
      "Streak": -1.0,
      "Year": 2019,
      "Date": "2019-09-01",
      "Winner": "CIN"
    },
    {
      "Unnamed_0": 33342,
      "Tm": "STL",
      "Home_Away": "Home",
      "Opp": "SFG",
      "W_or_L": "W",
      "R": 3.0,
      "RA": 1.0,
      "Inn": 9.0,
      "Record": "77-60",
      "Rank": 1.0,
      "GB": "up 3.0",
      "Win": "Wainwright",
      "Loss": "Beede",
      "Save": "Martinez",
      "Time": "2:43",
      "Attendance": 40732.0,
      "Streak": 1.0,
      "Year": 2019,
      "Date": "2019-09-02",
      "Winner": "STL"
    },
    {
      "Unnamed_0": 33343,
      "Tm": "STL",
      "Home_Away": "Home",
      "Opp": "SFG",
      "W_or_L": "W",
      "R": 1.0,
      "RA": 0.0,
      "Inn": 9.0,
      "Record": "78-60",
      "Rank": 1.0,
      "GB": "up 3.0",
      "Win": "Flaherty",
      "Loss": "Rodr\u00edguez",
      "Save": "Martinez",
      "Time": "2:11",
      "Attendance": 38259.0,
      "Streak": 2.0,
      "Year": 2019,
      "Date": "2019-09-03",
      "Winner": "STL"
    },
    {
      "Unnamed_0": 33344,
      "Tm": "STL",
      "Home_Away": "Home",
      "Opp": "SFG",
      "W_or_L": "L",
      "R": 8.0,
      "RA": 9.0,
      "Inn": 9.0,
      "Record": "78-61",
      "Rank": 1.0,
      "GB": "up 2.5",
      "Win": "Rogers",
      "Loss": "Gallegos",
      "Save": "Smith",
      "Time": "4:05",
      "Attendance": 41945.0,
      "Streak": -1.0,
      "Year": 2019,
      "Date": "2019-09-04",
      "Winner": "SFG"
    },
    {
      "Unnamed_0": 33345,
      "Tm": "STL",
      "Home_Away": "Home",
      "Opp": "SFG",
      "W_or_L": "W",
      "R": 10.0,
      "RA": 0.0,
      "Inn": 9.0,
      "Record": "79-61",
      "Rank": 1.0,
      "GB": "up 2.5",
      "Win": "Hudson",
      "Loss": "Webb",
      "Save": "Cabrera",
      "Time": "2:54",
      "Attendance": 36800.0,
      "Streak": 1.0,
      "Year": 2019,
      "Date": "2019-09-05",
      "Winner": "STL"
    },
    {
      "Unnamed_0": 33346,
      "Tm": "STL",
      "Home_Away": "@",
      "Opp": "PIT",
      "W_or_L": "L",
      "R": 4.0,
      "RA": 9.0,
      "Inn": 9.0,
      "Record": "79-62",
      "Rank": 1.0,
      "GB": "up 2.5",
      "Win": "Wang",
      "Loss": "Miller",
      "Save": "Vazquez",
      "Time": "3:28",
      "Attendance": 19090.0,
      "Streak": -1.0,
      "Year": 2019,
      "Date": "2019-09-06",
      "Winner": "PIT"
    },
    {
      "Unnamed_0": 33347,
      "Tm": "STL",
      "Home_Away": "@",
      "Opp": "PIT",
      "W_or_L": "W",
      "R": 10.0,
      "RA": 1.0,
      "Inn": 9.0,
      "Record": "80-62",
      "Rank": 1.0,
      "GB": "up 3.5",
      "Win": "Wainwright",
      "Loss": "Brault",
      "Save": null,
      "Time": "3:24",
      "Attendance": 23996.0,
      "Streak": 1.0,
      "Year": 2019,
      "Date": "2019-09-07",
      "Winner": "STL"
    },
    {
      "Unnamed_0": 33348,
      "Tm": "STL",
      "Home_Away": "@",
      "Opp": "PIT",
      "W_or_L": "W",
      "R": 2.0,
      "RA": 0.0,
      "Inn": 9.0,
      "Record": "81-62",
      "Rank": 1.0,
      "GB": "up 4.5",
      "Win": "Flaherty",
      "Loss": "Marvel",
      "Save": "Martinez",
      "Time": "2:50",
      "Attendance": 18363.0,
      "Streak": 2.0,
      "Year": 2019,
      "Date": "2019-09-08",
      "Winner": "STL"
    },
    {
      "Unnamed_0": 33349,
      "Tm": "STL",
      "Home_Away": "@",
      "Opp": "COL",
      "W_or_L": "L",
      "R": 1.0,
      "RA": 2.0,
      "Inn": 9.0,
      "Record": "81-63",
      "Rank": 1.0,
      "GB": "up 4.0",
      "Win": "Gonz\u00e1lez",
      "Loss": "Wacha",
      "Save": "D\u00edaz",
      "Time": "2:36",
      "Attendance": 31514.0,
      "Streak": -1.0,
      "Year": 2019,
      "Date": "2019-09-10",
      "Winner": "COL"
    },
    {
      "Unnamed_0": 33350,
      "Tm": "STL",
      "Home_Away": "@",
      "Opp": "COL",
      "W_or_L": "L",
      "R": 1.0,
      "RA": 2.0,
      "Inn": 9.0,
      "Record": "81-64",
      "Rank": 1.0,
      "GB": "up 4.0",
      "Win": "Senzatela",
      "Loss": "Hudson",
      "Save": "D\u00edaz",
      "Time": "3:01",
      "Attendance": 31931.0,
      "Streak": -2.0,
      "Year": 2019,
      "Date": "2019-09-11",
      "Winner": "COL"
    },
    {
      "Unnamed_0": 33351,
      "Tm": "STL",
      "Home_Away": "@",
      "Opp": "COL",
      "W_or_L": "W",
      "R": 10.0,
      "RA": 3.0,
      "Inn": 9.0,
      "Record": "82-64",
      "Rank": 1.0,
      "GB": "up 4.0",
      "Win": "Mikolas",
      "Loss": "Melville",
      "Save": null,
      "Time": "3:56",
      "Attendance": 27618.0,
      "Streak": 1.0,
      "Year": 2019,
      "Date": "2019-09-12",
      "Winner": "STL"
    },
    {
      "Unnamed_0": 33352,
      "Tm": "STL",
      "Home_Away": "Home",
      "Opp": "MIL",
      "W_or_L": "W",
      "R": 10.0,
      "RA": 0.0,
      "Inn": 9.0,
      "Record": "83-64",
      "Rank": 1.0,
      "GB": "up 4.0",
      "Win": "Wainwright",
      "Loss": "Houser",
      "Save": null,
      "Time": "3:12",
      "Attendance": 47075.0,
      "Streak": 2.0,
      "Year": 2019,
      "Date": "2019-09-13",
      "Winner": "STL"
    },
    {
      "Unnamed_0": 33353,
      "Tm": "STL",
      "Home_Away": "Home",
      "Opp": "MIL",
      "W_or_L": "L",
      "R": 2.0,
      "RA": 5.0,
      "Inn": 9.0,
      "Record": "83-65",
      "Rank": 1.0,
      "GB": "up 3.0",
      "Win": "Lyles",
      "Loss": "Flaherty",
      "Save": "Hader",
      "Time": "2:59",
      "Attendance": 46665.0,
      "Streak": -1.0,
      "Year": 2019,
      "Date": "2019-09-14",
      "Winner": "MIL"
    },
    {
      "Unnamed_0": 33354,
      "Tm": "STL",
      "Home_Away": "Home",
      "Opp": "MIL",
      "W_or_L": "L",
      "R": 6.0,
      "RA": 7.0,
      "Inn": 9.0,
      "Record": "83-66",
      "Rank": 1.0,
      "GB": "up 2.0",
      "Win": "Albers",
      "Loss": "Gant",
      "Save": "Hader",
      "Time": "3:26",
      "Attendance": 46722.0,
      "Streak": -2.0,
      "Year": 2019,
      "Date": "2019-09-15",
      "Winner": "MIL"
    },
    {
      "Unnamed_0": 33355,
      "Tm": "STL",
      "Home_Away": "Home",
      "Opp": "WSN",
      "W_or_L": "W",
      "R": 4.0,
      "RA": 2.0,
      "Inn": 9.0,
      "Record": "84-66",
      "Rank": 1.0,
      "GB": "up 2.0",
      "Win": "Hudson",
      "Loss": "Doolittle",
      "Save": "Martinez",
      "Time": "3:04",
      "Attendance": 42812.0,
      "Streak": 1.0,
      "Year": 2019,
      "Date": "2019-09-16",
      "Winner": "STL"
    },
    {
      "Unnamed_0": 33356,
      "Tm": "STL",
      "Home_Away": "Home",
      "Opp": "WSN",
      "W_or_L": "L",
      "R": 2.0,
      "RA": 6.0,
      "Inn": 9.0,
      "Record": "84-67",
      "Rank": 1.0,
      "GB": "up 2.0",
      "Win": "Corbin",
      "Loss": "Mikolas",
      "Save": "Hudson",
      "Time": "3:21",
      "Attendance": 44061.0,
      "Streak": -1.0,
      "Year": 2019,
      "Date": "2019-09-17",
      "Winner": "WSN"
    },
    {
      "Unnamed_0": 33357,
      "Tm": "STL",
      "Home_Away": "Home",
      "Opp": "WSN",
      "W_or_L": "W",
      "R": 5.0,
      "RA": 1.0,
      "Inn": 9.0,
      "Record": "85-67",
      "Rank": 1.0,
      "GB": "up 3.0",
      "Win": "Wainwright",
      "Loss": "Scherzer",
      "Save": "Martinez",
      "Time": "2:55",
      "Attendance": 37669.0,
      "Streak": 1.0,
      "Year": 2019,
      "Date": "2019-09-18",
      "Winner": "STL"
    },
    {
      "Unnamed_0": 33358,
      "Tm": "STL",
      "Home_Away": "@",
      "Opp": "CHC",
      "W_or_L": "W",
      "R": 5.0,
      "RA": 4.0,
      "Inn": 10.0,
      "Record": "86-67",
      "Rank": 1.0,
      "GB": "up 3.0",
      "Win": "Miller",
      "Loss": "Kimbrel",
      "Save": "Gallegos",
      "Time": "3:40",
      "Attendance": 39524.0,
      "Streak": 2.0,
      "Year": 2019,
      "Date": "2019-09-19",
      "Winner": "STL"
    },
    {
      "Unnamed_0": 33359,
      "Tm": "STL",
      "Home_Away": "@",
      "Opp": "CHC",
      "W_or_L": "W",
      "R": 2.0,
      "RA": 1.0,
      "Inn": 9.0,
      "Record": "87-67",
      "Rank": 1.0,
      "GB": "up 3.0",
      "Win": "Helsley",
      "Loss": "Phelps",
      "Save": "Martinez",
      "Time": "3:55",
      "Attendance": 39106.0,
      "Streak": 3.0,
      "Year": 2019,
      "Date": "2019-09-20",
      "Winner": "STL"
    },
    {
      "Unnamed_0": 33360,
      "Tm": "STL",
      "Home_Away": "@",
      "Opp": "CHC",
      "W_or_L": "W",
      "R": 9.0,
      "RA": 8.0,
      "Inn": 9.0,
      "Record": "88-67",
      "Rank": 1.0,
      "GB": "up 3.0",
      "Win": "Gant",
      "Loss": "Kimbrel",
      "Save": "Martinez",
      "Time": "4:24",
      "Attendance": 40071.0,
      "Streak": 4.0,
      "Year": 2019,
      "Date": "2019-09-21",
      "Winner": "STL"
    },
    {
      "Unnamed_0": 33361,
      "Tm": "STL",
      "Home_Away": "@",
      "Opp": "CHC",
      "W_or_L": "W",
      "R": 3.0,
      "RA": 2.0,
      "Inn": 9.0,
      "Record": "89-67",
      "Rank": 1.0,
      "GB": "up 3.0",
      "Win": "Webb",
      "Loss": "Darvish",
      "Save": "Miller",
      "Time": "3:03",
      "Attendance": 38606.0,
      "Streak": 5.0,
      "Year": 2019,
      "Date": "2019-09-22",
      "Winner": "STL"
    },
    {
      "Unnamed_0": 33362,
      "Tm": "STL",
      "Home_Away": "@",
      "Opp": "ARI",
      "W_or_L": "W",
      "R": 9.0,
      "RA": 7.0,
      "Inn": 9.0,
      "Record": "90-67",
      "Rank": 1.0,
      "GB": "up 3.5",
      "Win": "Wainwright",
      "Loss": "Young",
      "Save": "Martinez",
      "Time": "3:29",
      "Attendance": 24826.0,
      "Streak": 6.0,
      "Year": 2019,
      "Date": "2019-09-23",
      "Winner": "STL"
    },
    {
      "Unnamed_0": 33363,
      "Tm": "STL",
      "Home_Away": "@",
      "Opp": "ARI",
      "W_or_L": "L-wo",
      "R": 2.0,
      "RA": 3.0,
      "Inn": 19.0,
      "Record": "90-68",
      "Rank": 1.0,
      "GB": "up 2.5",
      "Win": "Ginkel",
      "Loss": "Brebbia",
      "Save": null,
      "Time": "6:53",
      "Attendance": 26097.0,
      "Streak": -1.0,
      "Year": 2019,
      "Date": "2019-09-24",
      "Winner": "ARI-wo"
    },
    {
      "Unnamed_0": 33364,
      "Tm": "STL",
      "Home_Away": "@",
      "Opp": "ARI",
      "W_or_L": "L",
      "R": 7.0,
      "RA": 9.0,
      "Inn": 9.0,
      "Record": "90-69",
      "Rank": 1.0,
      "GB": "up 1.5",
      "Win": "Kelly",
      "Loss": "Fern\u00e1ndez",
      "Save": "Bradley",
      "Time": "3:52",
      "Attendance": 21420.0,
      "Streak": -2.0,
      "Year": 2019,
      "Date": "2019-09-25",
      "Winner": "ARI"
    },
    {
      "Unnamed_0": 33365,
      "Tm": "STL",
      "Home_Away": "Home",
      "Opp": "CHC",
      "W_or_L": "L",
      "R": 2.0,
      "RA": 8.0,
      "Inn": 9.0,
      "Record": "90-70",
      "Rank": 1.0,
      "GB": "up 1.0",
      "Win": "Wieck",
      "Loss": "Miller",
      "Save": null,
      "Time": "4:04",
      "Attendance": 46530.0,
      "Streak": -3.0,
      "Year": 2019,
      "Date": "2019-09-27",
      "Winner": "CHC"
    },
    {
      "Unnamed_0": 33366,
      "Tm": "STL",
      "Home_Away": "Home",
      "Opp": "CHC",
      "W_or_L": "L",
      "R": 6.0,
      "RA": 8.0,
      "Inn": 9.0,
      "Record": "90-71",
      "Rank": 1.0,
      "GB": "up 1.0",
      "Win": "Cishek",
      "Loss": "Wainwright",
      "Save": "Kintzler",
      "Time": "3:46",
      "Attendance": 46971.0,
      "Streak": -4.0,
      "Year": 2019,
      "Date": "2019-09-28",
      "Winner": "CHC"
    },
    {
      "Unnamed_0": 33367,
      "Tm": "STL",
      "Home_Away": "Home",
      "Opp": "CHC",
      "W_or_L": "W",
      "R": 9.0,
      "RA": 0.0,
      "Inn": 9.0,
      "Record": "91-71",
      "Rank": 1.0,
      "GB": "up 2.0",
      "Win": "Flaherty",
      "Loss": "Holland",
      "Save": null,
      "Time": "2:30",
      "Attendance": 47212.0,
      "Streak": 1.0,
      "Year": 2019,
      "Date": "2019-09-29",
      "Winner": "STL"
    }
  ]
}
