{"team_games": [
    {
        "Unnamed_0": 7130,
        "Tm": "MIA",
        "Home_Away": "Home",
        "Opp": "COL",
        "W_or_L": "W",
        "R": 10.0,
        "RA": 1.0,
        "Inn": 9.0,
        "Record": "1-0",
        "Rank": 1.0,
        "GB": "Tied",
        "Win": "Fern\u00e1ndez",
        "Loss": "De\u00a0La\u00a0Rosa",
        "Save": null,
        "Time": "2:58",
        "Attendance": 37116.0,
        "Streak": 1.0,
        "Year": 2014,
        "Date": "2014-03-31",
        "Winner": "MIA"
    },
    {
        "Unnamed_0": 7131,
        "Tm": "MIA",
        "Home_Away": "Home",
        "Opp": "COL",
        "W_or_L": "W",
        "R": 4.0,
        "RA": 3.0,
        "Inn": 9.0,
        "Record": "2-0",
        "Rank": 1.0,
        "GB": "up 0.5",
        "Win": "Eovaldi",
        "Loss": "Anderson",
        "Save": "Cishek",
        "Time": "2:24",
        "Attendance": 15906.0,
        "Streak": 2.0,
        "Year": 2014,
        "Date": "2014-04-01",
        "Winner": "MIA"
    },
    {
        "Unnamed_0": 7132,
        "Tm": "MIA",
        "Home_Away": "Home",
        "Opp": "COL",
        "W_or_L": "L",
        "R": 5.0,
        "RA": 6.0,
        "Inn": 9.0,
        "Record": "2-1",
        "Rank": 2.0,
        "GB": "0.5",
        "Win": "Lyles",
        "Loss": "Alvarez",
        "Save": "Hawkins",
        "Time": "3:23",
        "Attendance": 15866.0,
        "Streak": -1.0,
        "Year": 2014,
        "Date": "2014-04-02",
        "Winner": "COL"
    },
    {
        "Unnamed_0": 7133,
        "Tm": "MIA",
        "Home_Away": "Home",
        "Opp": "COL",
        "W_or_L": "W",
        "R": 8.0,
        "RA": 5.0,
        "Inn": 9.0,
        "Record": "3-1",
        "Rank": 2.0,
        "GB": "0.5",
        "Win": "Ramos",
        "Loss": "Belisle",
        "Save": "Cishek",
        "Time": "3:14",
        "Attendance": 15378.0,
        "Streak": 1.0,
        "Year": 2014,
        "Date": "2014-04-03",
        "Winner": "MIA"
    },
    {
        "Unnamed_0": 7134,
        "Tm": "MIA",
        "Home_Away": "Home",
        "Opp": "SDP",
        "W_or_L": "W",
        "R": 8.0,
        "RA": 2.0,
        "Inn": 9.0,
        "Record": "4-1",
        "Rank": 1.0,
        "GB": "up 0.5",
        "Win": "Koehler",
        "Loss": "Stults",
        "Save": "Hand",
        "Time": "2:37",
        "Attendance": 17783.0,
        "Streak": 2.0,
        "Year": 2014,
        "Date": "2014-04-04",
        "Winner": "MIA"
    },
    {
        "Unnamed_0": 7135,
        "Tm": "MIA",
        "Home_Away": "Home",
        "Opp": "SDP",
        "W_or_L": "W",
        "R": 5.0,
        "RA": 0.0,
        "Inn": 9.0,
        "Record": "5-1",
        "Rank": 1.0,
        "GB": "up 0.5",
        "Win": "Fern\u00e1ndez",
        "Loss": "Cashner",
        "Save": null,
        "Time": "2:49",
        "Attendance": 35188.0,
        "Streak": 3.0,
        "Year": 2014,
        "Date": "2014-04-05",
        "Winner": "MIA"
    },
    {
        "Unnamed_0": 7136,
        "Tm": "MIA",
        "Home_Away": "Home",
        "Opp": "SDP",
        "W_or_L": "L",
        "R": 2.0,
        "RA": 4.0,
        "Inn": 9.0,
        "Record": "5-2",
        "Rank": 1.0,
        "GB": "up 0.5",
        "Win": "Kennedy",
        "Loss": "Eovaldi",
        "Save": "Street",
        "Time": "2:44",
        "Attendance": 22496.0,
        "Streak": -1.0,
        "Year": 2014,
        "Date": "2014-04-06",
        "Winner": "SDP"
    },
    {
        "Unnamed_0": 7137,
        "Tm": "MIA",
        "Home_Away": "@",
        "Opp": "WSN",
        "W_or_L": "L",
        "R": 0.0,
        "RA": 5.0,
        "Inn": 9.0,
        "Record": "5-3",
        "Rank": 2.0,
        "GB": "0.5",
        "Win": "Gonzalez",
        "Loss": "Alvarez",
        "Save": null,
        "Time": "2:58",
        "Attendance": 21728.0,
        "Streak": -2.0,
        "Year": 2014,
        "Date": "2014-04-08",
        "Winner": "WSN"
    },
    {
        "Unnamed_0": 7138,
        "Tm": "MIA",
        "Home_Away": "@",
        "Opp": "WSN",
        "W_or_L": "L",
        "R": 7.0,
        "RA": 10.0,
        "Inn": 9.0,
        "Record": "5-4",
        "Rank": 3.0,
        "GB": "1.5",
        "Win": "Clippard",
        "Loss": "Marmol",
        "Save": "Soriano",
        "Time": "3:56",
        "Attendance": 21190.0,
        "Streak": -3.0,
        "Year": 2014,
        "Date": "2014-04-09",
        "Winner": "WSN"
    },
    {
        "Unnamed_0": 7139,
        "Tm": "MIA",
        "Home_Away": "@",
        "Opp": "WSN",
        "W_or_L": "L",
        "R": 1.0,
        "RA": 7.0,
        "Inn": 9.0,
        "Record": "5-5",
        "Rank": 3.0,
        "GB": "2.5",
        "Win": "Strasburg",
        "Loss": "Koehler",
        "Save": null,
        "Time": "2:53",
        "Attendance": 20869.0,
        "Streak": -4.0,
        "Year": 2014,
        "Date": "2014-04-10",
        "Winner": "WSN"
    },
    {
        "Unnamed_0": 7140,
        "Tm": "MIA",
        "Home_Away": "@",
        "Opp": "PHI",
        "W_or_L": "L",
        "R": 3.0,
        "RA": 6.0,
        "Inn": 9.0,
        "Record": "5-6",
        "Rank": 3.0,
        "GB": "2.5",
        "Win": "Diekman",
        "Loss": "Fern\u00e1ndez",
        "Save": "Papelbon",
        "Time": "3:15",
        "Attendance": 22283.0,
        "Streak": -5.0,
        "Year": 2014,
        "Date": "2014-04-11",
        "Winner": "PHI"
    },
    {
        "Unnamed_0": 7141,
        "Tm": "MIA",
        "Home_Away": "@",
        "Opp": "PHI",
        "W_or_L": "L-wo",
        "R": 4.0,
        "RA": 5.0,
        "Inn": 10.0,
        "Record": "5-7",
        "Rank": 5.0,
        "GB": "2.5",
        "Win": "Rosenberg",
        "Loss": "Jennings",
        "Save": null,
        "Time": "3:29",
        "Attendance": 27760.0,
        "Streak": -6.0,
        "Year": 2014,
        "Date": "2014-04-12",
        "Winner": "PHI-wo"
    },
    {
        "Unnamed_0": 7142,
        "Tm": "MIA",
        "Home_Away": "@",
        "Opp": "PHI",
        "W_or_L": "L",
        "R": 3.0,
        "RA": 4.0,
        "Inn": 9.0,
        "Record": "5-8",
        "Rank": 5.0,
        "GB": "3.5",
        "Win": "Bastardo",
        "Loss": "Dunn",
        "Save": "Papelbon",
        "Time": "3:12",
        "Attendance": 34272.0,
        "Streak": -7.0,
        "Year": 2014,
        "Date": "2014-04-13",
        "Winner": "PHI"
    },
    {
        "Unnamed_0": 7143,
        "Tm": "MIA",
        "Home_Away": "Home",
        "Opp": "WSN",
        "W_or_L": "L",
        "R": 2.0,
        "RA": 9.0,
        "Inn": 9.0,
        "Record": "5-9",
        "Rank": 5.0,
        "GB": "4.5",
        "Win": "Zimmermann",
        "Loss": "Hand",
        "Save": null,
        "Time": "2:56",
        "Attendance": 18788.0,
        "Streak": -8.0,
        "Year": 2014,
        "Date": "2014-04-14",
        "Winner": "WSN"
    },
    {
        "Unnamed_0": 7144,
        "Tm": "MIA",
        "Home_Away": "Home",
        "Opp": "WSN",
        "W_or_L": "W",
        "R": 11.0,
        "RA": 2.0,
        "Inn": 9.0,
        "Record": "6-9",
        "Rank": 5.0,
        "GB": "4.0",
        "Win": "Koehler",
        "Loss": "Strasburg",
        "Save": null,
        "Time": "2:54",
        "Attendance": 19931.0,
        "Streak": 1.0,
        "Year": 2014,
        "Date": "2014-04-15",
        "Winner": "MIA"
    },
    {
        "Unnamed_0": 7145,
        "Tm": "MIA",
        "Home_Away": "Home",
        "Opp": "WSN",
        "W_or_L": "L",
        "R": 3.0,
        "RA": 6.0,
        "Inn": 9.0,
        "Record": "6-10",
        "Rank": 5.0,
        "GB": "5.0",
        "Win": "Storen",
        "Loss": "Dunn",
        "Save": "Soriano",
        "Time": "2:37",
        "Attendance": 20178.0,
        "Streak": -1.0,
        "Year": 2014,
        "Date": "2014-04-16",
        "Winner": "WSN"
    },
    {
        "Unnamed_0": 7146,
        "Tm": "MIA",
        "Home_Away": "Home",
        "Opp": "SEA",
        "W_or_L": "W-wo",
        "R": 8.0,
        "RA": 4.0,
        "Inn": 9.0,
        "Record": "7-10",
        "Rank": 5.0,
        "GB": "4.5",
        "Win": "Cishek",
        "Loss": "Medina",
        "Save": null,
        "Time": "3:09",
        "Attendance": 21388.0,
        "Streak": 1.0,
        "Year": 2014,
        "Date": "2014-04-18",
        "Winner": "MIA-wo"
    },
    {
        "Unnamed_0": 7147,
        "Tm": "MIA",
        "Home_Away": "Home",
        "Opp": "SEA",
        "W_or_L": "W",
        "R": 7.0,
        "RA": 0.0,
        "Inn": 9.0,
        "Record": "8-10",
        "Rank": 4.0,
        "GB": "4.5",
        "Win": "Alvarez",
        "Loss": "El\u00edas",
        "Save": null,
        "Time": "2:20",
        "Attendance": 24003.0,
        "Streak": 2.0,
        "Year": 2014,
        "Date": "2014-04-19",
        "Winner": "MIA"
    },
    {
        "Unnamed_0": 7148,
        "Tm": "MIA",
        "Home_Away": "Home",
        "Opp": "SEA",
        "W_or_L": "W",
        "R": 3.0,
        "RA": 2.0,
        "Inn": 9.0,
        "Record": "9-10",
        "Rank": 4.0,
        "GB": "3.5",
        "Win": "Dunn",
        "Loss": "Wilhelmsen",
        "Save": "Cishek",
        "Time": "2:58",
        "Attendance": 20228.0,
        "Streak": 3.0,
        "Year": 2014,
        "Date": "2014-04-20",
        "Winner": "MIA"
    },
    {
        "Unnamed_0": 7149,
        "Tm": "MIA",
        "Home_Away": "@",
        "Opp": "ATL",
        "W_or_L": "L-wo",
        "R": 2.0,
        "RA": 4.0,
        "Inn": 10.0,
        "Record": "9-11",
        "Rank": 5.0,
        "GB": "4.5",
        "Win": "Varvaro",
        "Loss": "Caminero",
        "Save": null,
        "Time": "3:41",
        "Attendance": 16055.0,
        "Streak": -1.0,
        "Year": 2014,
        "Date": "2014-04-21",
        "Winner": "ATL-wo"
    },
    {
        "Unnamed_0": 7150,
        "Tm": "MIA",
        "Home_Away": "@",
        "Opp": "ATL",
        "W_or_L": "W",
        "R": 1.0,
        "RA": 0.0,
        "Inn": 9.0,
        "Record": "10-11",
        "Rank": 5.0,
        "GB": "3.5",
        "Win": "Fern\u00e1ndez",
        "Loss": "Wood",
        "Save": "Cishek",
        "Time": "2:08",
        "Attendance": 18275.0,
        "Streak": 1.0,
        "Year": 2014,
        "Date": "2014-04-22",
        "Winner": "MIA"
    },
    {
        "Unnamed_0": 7151,
        "Tm": "MIA",
        "Home_Away": "@",
        "Opp": "ATL",
        "W_or_L": "L",
        "R": 1.0,
        "RA": 3.0,
        "Inn": 9.0,
        "Record": "10-12",
        "Rank": 5.0,
        "GB": "4.5",
        "Win": "Carpenter",
        "Loss": "Dunn",
        "Save": "Kimbrel",
        "Time": "3:01",
        "Attendance": 21508.0,
        "Streak": -1.0,
        "Year": 2014,
        "Date": "2014-04-23",
        "Winner": "ATL"
    },
    {
        "Unnamed_0": 7152,
        "Tm": "MIA",
        "Home_Away": "@",
        "Opp": "NYM",
        "W_or_L": "L-wo",
        "R": 3.0,
        "RA": 4.0,
        "Inn": 9.0,
        "Record": "10-13",
        "Rank": 5.0,
        "GB": "5.5",
        "Win": "Familia",
        "Loss": "Cishek",
        "Save": null,
        "Time": "2:59",
        "Attendance": 21171.0,
        "Streak": -2.0,
        "Year": 2014,
        "Date": "2014-04-25",
        "Winner": "NYM-wo"
    },
    {
        "Unnamed_0": 7153,
        "Tm": "MIA",
        "Home_Away": "@",
        "Opp": "NYM",
        "W_or_L": "W",
        "R": 7.0,
        "RA": 6.0,
        "Inn": 10.0,
        "Record": "11-13",
        "Rank": 5.0,
        "GB": "5.5",
        "Win": "Dunn",
        "Loss": "Farnsworth",
        "Save": "Cishek",
        "Time": "3:35",
        "Attendance": 21492.0,
        "Streak": 1.0,
        "Year": 2014,
        "Date": "2014-04-26",
        "Winner": "MIA"
    },
    {
        "Unnamed_0": 7154,
        "Tm": "MIA",
        "Home_Away": "@",
        "Opp": "NYM",
        "W_or_L": "L",
        "R": 0.0,
        "RA": 4.0,
        "Inn": 9.0,
        "Record": "11-14",
        "Rank": 5.0,
        "GB": "6.5",
        "Win": "Gee",
        "Loss": "Koehler",
        "Save": null,
        "Time": "2:42",
        "Attendance": 26861.0,
        "Streak": -1.0,
        "Year": 2014,
        "Date": "2014-04-27",
        "Winner": "NYM"
    },
    {
        "Unnamed_0": 7155,
        "Tm": "MIA",
        "Home_Away": "Home",
        "Opp": "ATL",
        "W_or_L": "W",
        "R": 9.0,
        "RA": 0.0,
        "Inn": 9.0,
        "Record": "12-14",
        "Rank": 5.0,
        "GB": "5.5",
        "Win": "Fern\u00e1ndez",
        "Loss": "Wood",
        "Save": null,
        "Time": "2:07",
        "Attendance": 21992.0,
        "Streak": 1.0,
        "Year": 2014,
        "Date": "2014-04-29",
        "Winner": "MIA"
    },
    {
        "Unnamed_0": 7156,
        "Tm": "MIA",
        "Home_Away": "Home",
        "Opp": "ATL",
        "W_or_L": "W",
        "R": 9.0,
        "RA": 3.0,
        "Inn": 9.0,
        "Record": "13-14",
        "Rank": 5.0,
        "GB": "4.5",
        "Win": "Eovaldi",
        "Loss": "Harang",
        "Save": null,
        "Time": "2:50",
        "Attendance": 15558.0,
        "Streak": 2.0,
        "Year": 2014,
        "Date": "2014-04-30",
        "Winner": "MIA"
    },
    {
        "Unnamed_0": 7157,
        "Tm": "MIA",
        "Home_Away": "Home",
        "Opp": "ATL",
        "W_or_L": "W",
        "R": 5.0,
        "RA": 4.0,
        "Inn": 9.0,
        "Record": "14-14",
        "Rank": 4.0,
        "GB": "3.5",
        "Win": "Dunn",
        "Loss": "Thomas",
        "Save": "Cishek",
        "Time": "2:54",
        "Attendance": 17836.0,
        "Streak": 3.0,
        "Year": 2014,
        "Date": "2014-05-01",
        "Winner": "MIA"
    },
    {
        "Unnamed_0": 7158,
        "Tm": "MIA",
        "Home_Away": "Home",
        "Opp": "LAD",
        "W_or_L": "W",
        "R": 6.0,
        "RA": 3.0,
        "Inn": 9.0,
        "Record": "15-14",
        "Rank": 4.0,
        "GB": "2.5",
        "Win": "Koehler",
        "Loss": "Beckett",
        "Save": null,
        "Time": "3:08",
        "Attendance": 20722.0,
        "Streak": 4.0,
        "Year": 2014,
        "Date": "2014-05-02",
        "Winner": "MIA"
    },
    {
        "Unnamed_0": 7159,
        "Tm": "MIA",
        "Home_Away": "Home",
        "Opp": "LAD",
        "W_or_L": "L",
        "R": 7.0,
        "RA": 9.0,
        "Inn": 11.0,
        "Record": "15-15",
        "Rank": 4.0,
        "GB": "2.5",
        "Win": "League",
        "Loss": "Marmol",
        "Save": null,
        "Time": "4:07",
        "Attendance": 24104.0,
        "Streak": -1.0,
        "Year": 2014,
        "Date": "2014-05-03",
        "Winner": "LAD"
    },
    {
        "Unnamed_0": 7160,
        "Tm": "MIA",
        "Home_Away": "Home",
        "Opp": "LAD",
        "W_or_L": "W-wo",
        "R": 5.0,
        "RA": 4.0,
        "Inn": 9.0,
        "Record": "16-15",
        "Rank": 4.0,
        "GB": "1.5",
        "Win": "Ramos",
        "Loss": "Wright",
        "Save": null,
        "Time": "3:06",
        "Attendance": 30145.0,
        "Streak": 1.0,
        "Year": 2014,
        "Date": "2014-05-04",
        "Winner": "MIA-wo"
    },
    {
        "Unnamed_0": 7161,
        "Tm": "MIA",
        "Home_Away": "Home",
        "Opp": "NYM",
        "W_or_L": "W-wo",
        "R": 4.0,
        "RA": 3.0,
        "Inn": 9.0,
        "Record": "17-15",
        "Rank": 3.0,
        "GB": "1.0",
        "Win": "Cishek",
        "Loss": "Rice",
        "Save": null,
        "Time": "2:53",
        "Attendance": 20606.0,
        "Streak": 2.0,
        "Year": 2014,
        "Date": "2014-05-05",
        "Winner": "MIA-wo"
    },
    {
        "Unnamed_0": 7162,
        "Tm": "MIA",
        "Home_Away": "Home",
        "Opp": "NYM",
        "W_or_L": "W",
        "R": 3.0,
        "RA": 0.0,
        "Inn": 9.0,
        "Record": "18-15",
        "Rank": 2.0,
        "GB": "0.5",
        "Win": "Alvarez",
        "Loss": "Colon",
        "Save": null,
        "Time": "2:08",
        "Attendance": 18315.0,
        "Streak": 3.0,
        "Year": 2014,
        "Date": "2014-05-06",
        "Winner": "MIA"
    },
    {
        "Unnamed_0": 7163,
        "Tm": "MIA",
        "Home_Away": "Home",
        "Opp": "NYM",
        "W_or_L": "W-wo",
        "R": 1.0,
        "RA": 0.0,
        "Inn": 9.0,
        "Record": "19-15",
        "Rank": 1.0,
        "GB": "Tied",
        "Win": "Cishek",
        "Loss": "Torres",
        "Save": null,
        "Time": "2:40",
        "Attendance": 18010.0,
        "Streak": 4.0,
        "Year": 2014,
        "Date": "2014-05-07",
        "Winner": "MIA-wo"
    },
    {
        "Unnamed_0": 7164,
        "Tm": "MIA",
        "Home_Away": "@",
        "Opp": "SDP",
        "W_or_L": "W",
        "R": 3.0,
        "RA": 1.0,
        "Inn": 11.0,
        "Record": "20-15",
        "Rank": 1.0,
        "GB": "up 0.5",
        "Win": "Ramos",
        "Loss": "Thayer",
        "Save": "Cishek",
        "Time": "3:22",
        "Attendance": 17832.0,
        "Streak": 5.0,
        "Year": 2014,
        "Date": "2014-05-08",
        "Winner": "MIA"
    },
    {
        "Unnamed_0": 7165,
        "Tm": "MIA",
        "Home_Away": "@",
        "Opp": "SDP",
        "W_or_L": "L",
        "R": 1.0,
        "RA": 10.0,
        "Inn": 9.0,
        "Record": "20-16",
        "Rank": 1.0,
        "GB": "Tied",
        "Win": "Ross",
        "Loss": "Fern\u00e1ndez",
        "Save": null,
        "Time": "2:54",
        "Attendance": 22553.0,
        "Streak": -1.0,
        "Year": 2014,
        "Date": "2014-05-09",
        "Winner": "SDP"
    },
    {
        "Unnamed_0": 7166,
        "Tm": "MIA",
        "Home_Away": "@",
        "Opp": "SDP",
        "W_or_L": "L",
        "R": 3.0,
        "RA": 9.0,
        "Inn": 9.0,
        "Record": "20-17",
        "Rank": 2.0,
        "GB": "1.0",
        "Win": "Stults",
        "Loss": "Marmol",
        "Save": null,
        "Time": "3:21",
        "Attendance": 27719.0,
        "Streak": -2.0,
        "Year": 2014,
        "Date": "2014-05-10",
        "Winner": "SDP"
    },
    {
        "Unnamed_0": 7167,
        "Tm": "MIA",
        "Home_Away": "@",
        "Opp": "SDP",
        "W_or_L": "L",
        "R": 4.0,
        "RA": 5.0,
        "Inn": 9.0,
        "Record": "20-18",
        "Rank": 2.0,
        "GB": "2.0",
        "Win": "Erlin",
        "Loss": "Alvarez",
        "Save": "Street",
        "Time": "3:29",
        "Attendance": 17682.0,
        "Streak": -3.0,
        "Year": 2014,
        "Date": "2014-05-11",
        "Winner": "SDP"
    },
    {
        "Unnamed_0": 7168,
        "Tm": "MIA",
        "Home_Away": "@",
        "Opp": "LAD",
        "W_or_L": "L",
        "R": 5.0,
        "RA": 6.0,
        "Inn": 9.0,
        "Record": "20-19",
        "Rank": 3.0,
        "GB": "2.0",
        "Win": "Haren",
        "Loss": "Koehler",
        "Save": "Jansen",
        "Time": "3:31",
        "Attendance": 37187.0,
        "Streak": -4.0,
        "Year": 2014,
        "Date": "2014-05-12",
        "Winner": "LAD"
    },
    {
        "Unnamed_0": 7169,
        "Tm": "MIA",
        "Home_Away": "@",
        "Opp": "LAD",
        "W_or_L": "L",
        "R": 1.0,
        "RA": 7.0,
        "Inn": 9.0,
        "Record": "20-20",
        "Rank": 3.0,
        "GB": "3.0",
        "Win": "Beckett",
        "Loss": "Turner",
        "Save": null,
        "Time": "3:02",
        "Attendance": 50349.0,
        "Streak": -5.0,
        "Year": 2014,
        "Date": "2014-05-13",
        "Winner": "LAD"
    },
    {
        "Unnamed_0": 7170,
        "Tm": "MIA",
        "Home_Away": "@",
        "Opp": "LAD",
        "W_or_L": "W",
        "R": 13.0,
        "RA": 3.0,
        "Inn": 9.0,
        "Record": "21-20",
        "Rank": 3.0,
        "GB": "2.0",
        "Win": "DeSclafani",
        "Loss": "Maholm",
        "Save": "Wolf",
        "Time": "3:20",
        "Attendance": 39498.0,
        "Streak": 1.0,
        "Year": 2014,
        "Date": "2014-05-14",
        "Winner": "MIA"
    },
    {
        "Unnamed_0": 7171,
        "Tm": "MIA",
        "Home_Away": "@",
        "Opp": "SFG",
        "W_or_L": "L",
        "R": 4.0,
        "RA": 6.0,
        "Inn": 9.0,
        "Record": "21-21",
        "Rank": 3.0,
        "GB": "2.5",
        "Win": "Cain",
        "Loss": "Eovaldi",
        "Save": "Romo",
        "Time": "2:53",
        "Attendance": 41597.0,
        "Streak": -1.0,
        "Year": 2014,
        "Date": "2014-05-15",
        "Winner": "SFG"
    },
    {
        "Unnamed_0": 7172,
        "Tm": "MIA",
        "Home_Away": "@",
        "Opp": "SFG",
        "W_or_L": "W",
        "R": 7.0,
        "RA": 5.0,
        "Inn": 9.0,
        "Record": "22-21",
        "Rank": 3.0,
        "GB": "1.5",
        "Win": "Dunn",
        "Loss": "Casilla",
        "Save": "Cishek",
        "Time": "3:17",
        "Attendance": 41819.0,
        "Streak": 1.0,
        "Year": 2014,
        "Date": "2014-05-16",
        "Winner": "MIA"
    },
    {
        "Unnamed_0": 7173,
        "Tm": "MIA",
        "Home_Away": "@",
        "Opp": "SFG",
        "W_or_L": "W",
        "R": 5.0,
        "RA": 0.0,
        "Inn": 9.0,
        "Record": "23-21",
        "Rank": 2.0,
        "GB": "0.5",
        "Win": "Koehler",
        "Loss": "Lincecum",
        "Save": "Cishek",
        "Time": "2:57",
        "Attendance": 41619.0,
        "Streak": 2.0,
        "Year": 2014,
        "Date": "2014-05-17",
        "Winner": "MIA"
    },
    {
        "Unnamed_0": 7174,
        "Tm": "MIA",
        "Home_Away": "@",
        "Opp": "SFG",
        "W_or_L": "L",
        "R": 1.0,
        "RA": 4.0,
        "Inn": 9.0,
        "Record": "23-22",
        "Rank": 3.0,
        "GB": "1.5",
        "Win": "Vogelsong",
        "Loss": "Turner",
        "Save": "Romo",
        "Time": "3:04",
        "Attendance": 41551.0,
        "Streak": -1.0,
        "Year": 2014,
        "Date": "2014-05-18",
        "Winner": "SFG"
    },
    {
        "Unnamed_0": 7175,
        "Tm": "MIA",
        "Home_Away": "Home",
        "Opp": "PHI",
        "W_or_L": "L",
        "R": 5.0,
        "RA": 6.0,
        "Inn": 9.0,
        "Record": "23-23",
        "Rank": 3.0,
        "GB": "3.0",
        "Win": "Burnett",
        "Loss": "DeSclafani",
        "Save": "Papelbon",
        "Time": "3:30",
        "Attendance": 18699.0,
        "Streak": -2.0,
        "Year": 2014,
        "Date": "2014-05-20",
        "Winner": "PHI"
    },
    {
        "Unnamed_0": 7176,
        "Tm": "MIA",
        "Home_Away": "Home",
        "Opp": "PHI",
        "W_or_L": "W",
        "R": 14.0,
        "RA": 5.0,
        "Inn": 9.0,
        "Record": "24-23",
        "Rank": 3.0,
        "GB": "2.0",
        "Win": "Eovaldi",
        "Loss": "Kendrick",
        "Save": null,
        "Time": "3:39",
        "Attendance": 18257.0,
        "Streak": 1.0,
        "Year": 2014,
        "Date": "2014-05-21",
        "Winner": "MIA"
    },
    {
        "Unnamed_0": 7177,
        "Tm": "MIA",
        "Home_Away": "Home",
        "Opp": "PHI",
        "W_or_L": "W-wo",
        "R": 4.0,
        "RA": 3.0,
        "Inn": 9.0,
        "Record": "25-23",
        "Rank": 2.0,
        "GB": "2.0",
        "Win": "Cishek",
        "Loss": "Diekman",
        "Save": null,
        "Time": "2:46",
        "Attendance": 25507.0,
        "Streak": 2.0,
        "Year": 2014,
        "Date": "2014-05-22",
        "Winner": "MIA-wo"
    },
    {
        "Unnamed_0": 7178,
        "Tm": "MIA",
        "Home_Away": "Home",
        "Opp": "MIL",
        "W_or_L": "L",
        "R": 5.0,
        "RA": 9.0,
        "Inn": 9.0,
        "Record": "25-24",
        "Rank": 2.0,
        "GB": "3.0",
        "Win": "Estrada",
        "Loss": "Koehler",
        "Save": null,
        "Time": "2:54",
        "Attendance": 18989.0,
        "Streak": -1.0,
        "Year": 2014,
        "Date": "2014-05-23",
        "Winner": "MIL"
    },
    {
        "Unnamed_0": 7179,
        "Tm": "MIA",
        "Home_Away": "Home",
        "Opp": "MIL",
        "W_or_L": "W",
        "R": 2.0,
        "RA": 1.0,
        "Inn": 9.0,
        "Record": "26-24",
        "Rank": 2.0,
        "GB": "2.0",
        "Win": "Turner",
        "Loss": "Peralta",
        "Save": "Cishek",
        "Time": "3:03",
        "Attendance": 25819.0,
        "Streak": 1.0,
        "Year": 2014,
        "Date": "2014-05-24",
        "Winner": "MIA"
    },
    {
        "Unnamed_0": 7180,
        "Tm": "MIA",
        "Home_Away": "Home",
        "Opp": "MIL",
        "W_or_L": "L",
        "R": 1.0,
        "RA": 7.0,
        "Inn": 9.0,
        "Record": "26-25",
        "Rank": 2.0,
        "GB": "3.0",
        "Win": "Nelson",
        "Loss": "Wolf",
        "Save": null,
        "Time": "3:16",
        "Attendance": 21897.0,
        "Streak": -1.0,
        "Year": 2014,
        "Date": "2014-05-25",
        "Winner": "MIL"
    },
    {
        "Unnamed_0": 7181,
        "Tm": "MIA",
        "Home_Away": "@",
        "Opp": "WSN",
        "W_or_L": "W",
        "R": 3.0,
        "RA": 2.0,
        "Inn": 9.0,
        "Record": "27-25",
        "Rank": 2.0,
        "GB": "2.0",
        "Win": "Eovaldi",
        "Loss": "Roark",
        "Save": "Cishek",
        "Time": "2:46",
        "Attendance": 33677.0,
        "Streak": 1.0,
        "Year": 2014,
        "Date": "2014-05-26",
        "Winner": "MIA"
    },
    {
        "Unnamed_0": 7182,
        "Tm": "MIA",
        "Home_Away": "@",
        "Opp": "WSN",
        "W_or_L": "W",
        "R": 8.0,
        "RA": 5.0,
        "Inn": 10.0,
        "Record": "28-25",
        "Rank": 2.0,
        "GB": "0.5",
        "Win": "Slowey",
        "Loss": "Blevins",
        "Save": null,
        "Time": "3:47",
        "Attendance": 24830.0,
        "Streak": 2.0,
        "Year": 2014,
        "Date": "2014-05-28",
        "Winner": "MIA"
    },
    {
        "Unnamed_0": 7183,
        "Tm": "MIA",
        "Home_Away": "Home",
        "Opp": "ATL",
        "W_or_L": "L",
        "R": 2.0,
        "RA": 3.0,
        "Inn": 9.0,
        "Record": "28-26",
        "Rank": 2.0,
        "GB": "1.0",
        "Win": "Teheran",
        "Loss": "Koehler",
        "Save": "Kimbrel",
        "Time": "2:53",
        "Attendance": 18469.0,
        "Streak": -1.0,
        "Year": 2014,
        "Date": "2014-05-30",
        "Winner": "ATL"
    },
    {
        "Unnamed_0": 7184,
        "Tm": "MIA",
        "Home_Away": "Home",
        "Opp": "ATL",
        "W_or_L": "L",
        "R": 5.0,
        "RA": 9.0,
        "Inn": 9.0,
        "Record": "28-27",
        "Rank": 2.0,
        "GB": "2.0",
        "Win": "Santana",
        "Loss": "Turner",
        "Save": "Kimbrel",
        "Time": "3:28",
        "Attendance": 26875.0,
        "Streak": -2.0,
        "Year": 2014,
        "Date": "2014-05-31",
        "Winner": "ATL"
    },
    {
        "Unnamed_0": 7185,
        "Tm": "MIA",
        "Home_Away": "Home",
        "Opp": "ATL",
        "W_or_L": "L",
        "R": 2.0,
        "RA": 4.0,
        "Inn": 9.0,
        "Record": "28-28",
        "Rank": 2.0,
        "GB": "3.0",
        "Win": "Wood",
        "Loss": "Cishek",
        "Save": "Simmons",
        "Time": "2:39",
        "Attendance": 21997.0,
        "Streak": -3.0,
        "Year": 2014,
        "Date": "2014-06-01",
        "Winner": "ATL"
    },
    {
        "Unnamed_0": 7186,
        "Tm": "MIA",
        "Home_Away": "Home",
        "Opp": "TBR",
        "W_or_L": "W",
        "R": 3.0,
        "RA": 1.0,
        "Inn": 9.0,
        "Record": "29-28",
        "Rank": 2.0,
        "GB": "2.5",
        "Win": "Wolf",
        "Loss": "Cobb",
        "Save": "Cishek",
        "Time": "2:33",
        "Attendance": 18155.0,
        "Streak": 1.0,
        "Year": 2014,
        "Date": "2014-06-02",
        "Winner": "MIA"
    },
    {
        "Unnamed_0": 7187,
        "Tm": "MIA",
        "Home_Away": "Home",
        "Opp": "TBR",
        "W_or_L": "W",
        "R": 1.0,
        "RA": 0.0,
        "Inn": 9.0,
        "Record": "30-28",
        "Rank": 2.0,
        "GB": "1.5",
        "Win": "Alvarez",
        "Loss": "Archer",
        "Save": null,
        "Time": "2:10",
        "Attendance": 21303.0,
        "Streak": 2.0,
        "Year": 2014,
        "Date": "2014-06-03",
        "Winner": "MIA"
    },
    {
        "Unnamed_0": 7188,
        "Tm": "MIA",
        "Home_Away": "@",
        "Opp": "TBR",
        "W_or_L": "W",
        "R": 5.0,
        "RA": 4.0,
        "Inn": 9.0,
        "Record": "31-28",
        "Rank": 2.0,
        "GB": "0.5",
        "Win": "Koehler",
        "Loss": "Price",
        "Save": "Cishek",
        "Time": "3:17",
        "Attendance": 10897.0,
        "Streak": 3.0,
        "Year": 2014,
        "Date": "2014-06-04",
        "Winner": "MIA"
    },
    {
        "Unnamed_0": 7189,
        "Tm": "MIA",
        "Home_Away": "@",
        "Opp": "TBR",
        "W_or_L": "W",
        "R": 11.0,
        "RA": 6.0,
        "Inn": 9.0,
        "Record": "32-28",
        "Rank": 1.0,
        "GB": "Tied",
        "Win": "Turner",
        "Loss": "Odorizzi",
        "Save": null,
        "Time": "3:45",
        "Attendance": 10442.0,
        "Streak": 4.0,
        "Year": 2014,
        "Date": "2014-06-05",
        "Winner": "MIA"
    },
    {
        "Unnamed_0": 7190,
        "Tm": "MIA",
        "Home_Away": "@",
        "Opp": "CHC",
        "W_or_L": "L-wo",
        "R": 3.0,
        "RA": 5.0,
        "Inn": 13.0,
        "Record": "32-29",
        "Rank": 2.0,
        "GB": "1.0",
        "Win": "Villanueva",
        "Loss": "Slowey",
        "Save": null,
        "Time": "4:02",
        "Attendance": 28495.0,
        "Streak": -1.0,
        "Year": 2014,
        "Date": "2014-06-06",
        "Winner": "CHC-wo"
    },
    {
        "Unnamed_0": 7191,
        "Tm": "MIA",
        "Home_Away": "@",
        "Opp": "CHC",
        "W_or_L": "L",
        "R": 2.0,
        "RA": 5.0,
        "Inn": 9.0,
        "Record": "32-30",
        "Rank": 2.0,
        "GB": "1.0",
        "Win": "Samardzija",
        "Loss": "Wolf",
        "Save": "Strop",
        "Time": "2:49",
        "Attendance": 33786.0,
        "Streak": -2.0,
        "Year": 2014,
        "Date": "2014-06-07",
        "Winner": "CHC"
    },
    {
        "Unnamed_0": 7192,
        "Tm": "MIA",
        "Home_Away": "@",
        "Opp": "CHC",
        "W_or_L": "W",
        "R": 4.0,
        "RA": 3.0,
        "Inn": 9.0,
        "Record": "33-30",
        "Rank": 1.0,
        "GB": "Tied",
        "Win": "Dunn",
        "Loss": "Strop",
        "Save": "Cishek",
        "Time": "3:18",
        "Attendance": 33134.0,
        "Streak": 1.0,
        "Year": 2014,
        "Date": "2014-06-08",
        "Winner": "MIA"
    },
    {
        "Unnamed_0": 7193,
        "Tm": "MIA",
        "Home_Away": "@",
        "Opp": "TEX",
        "W_or_L": "W",
        "R": 8.0,
        "RA": 5.0,
        "Inn": 9.0,
        "Record": "34-30",
        "Rank": 3.0,
        "GB": "0.5",
        "Win": "Morris",
        "Loss": "Frasor",
        "Save": "Cishek",
        "Time": "3:39",
        "Attendance": 28845.0,
        "Streak": 2.0,
        "Year": 2014,
        "Date": "2014-06-10",
        "Winner": "MIA"
    },
    {
        "Unnamed_0": 7194,
        "Tm": "MIA",
        "Home_Away": "@",
        "Opp": "TEX",
        "W_or_L": "L",
        "R": 0.0,
        "RA": 6.0,
        "Inn": 9.0,
        "Record": "34-31",
        "Rank": 3.0,
        "GB": "1.5",
        "Win": "Darvish",
        "Loss": "Turner",
        "Save": null,
        "Time": "2:37",
        "Attendance": 31512.0,
        "Streak": -1.0,
        "Year": 2014,
        "Date": "2014-06-11",
        "Winner": "TEX"
    },
    {
        "Unnamed_0": 7195,
        "Tm": "MIA",
        "Home_Away": "Home",
        "Opp": "PIT",
        "W_or_L": "L",
        "R": 6.0,
        "RA": 8.0,
        "Inn": 13.0,
        "Record": "34-32",
        "Rank": 3.0,
        "GB": "1.0",
        "Win": "G\u00f3mez",
        "Loss": "Dunn",
        "Save": null,
        "Time": "4:26",
        "Attendance": 19054.0,
        "Streak": -2.0,
        "Year": 2014,
        "Date": "2014-06-13",
        "Winner": "PIT"
    },
    {
        "Unnamed_0": 7196,
        "Tm": "MIA",
        "Home_Away": "Home",
        "Opp": "PIT",
        "W_or_L": "L",
        "R": 6.0,
        "RA": 8.0,
        "Inn": 9.0,
        "Record": "34-33",
        "Rank": 3.0,
        "GB": "1.0",
        "Win": "Morton",
        "Loss": "Wolf",
        "Save": "Grilli",
        "Time": "3:09",
        "Attendance": 21195.0,
        "Streak": -3.0,
        "Year": 2014,
        "Date": "2014-06-14",
        "Winner": "PIT"
    },
    {
        "Unnamed_0": 7197,
        "Tm": "MIA",
        "Home_Away": "Home",
        "Opp": "PIT",
        "W_or_L": "W-wo",
        "R": 3.0,
        "RA": 2.0,
        "Inn": 10.0,
        "Record": "35-33",
        "Rank": 2.0,
        "GB": "1.0",
        "Win": "Ramos",
        "Loss": "Hughes",
        "Save": null,
        "Time": "3:22",
        "Attendance": 25953.0,
        "Streak": 1.0,
        "Year": 2014,
        "Date": "2014-06-15",
        "Winner": "MIA-wo"
    },
    {
        "Unnamed_0": 7198,
        "Tm": "MIA",
        "Home_Away": "Home",
        "Opp": "CHC",
        "W_or_L": "L",
        "R": 4.0,
        "RA": 5.0,
        "Inn": 13.0,
        "Record": "35-34",
        "Rank": 3.0,
        "GB": "1.0",
        "Win": "Villanueva",
        "Loss": "Turner",
        "Save": "Russell",
        "Time": "4:39",
        "Attendance": 19170.0,
        "Streak": -1.0,
        "Year": 2014,
        "Date": "2014-06-16",
        "Winner": "CHC"
    },
    {
        "Unnamed_0": 7199,
        "Tm": "MIA",
        "Home_Away": "Home",
        "Opp": "CHC",
        "W_or_L": "W",
        "R": 6.0,
        "RA": 5.0,
        "Inn": 9.0,
        "Record": "36-34",
        "Rank": 2.0,
        "GB": "0.5",
        "Win": "Dyson",
        "Loss": "Schlitter",
        "Save": "Cishek",
        "Time": "3:11",
        "Attendance": 20860.0,
        "Streak": 1.0,
        "Year": 2014,
        "Date": "2014-06-17",
        "Winner": "MIA"
    },
    {
        "Unnamed_0": 7200,
        "Tm": "MIA",
        "Home_Away": "Home",
        "Opp": "CHC",
        "W_or_L": "L",
        "R": 1.0,
        "RA": 6.0,
        "Inn": 9.0,
        "Record": "36-35",
        "Rank": 2.0,
        "GB": "1.5",
        "Win": "Arrieta",
        "Loss": "Eovaldi",
        "Save": null,
        "Time": "2:54",
        "Attendance": 27032.0,
        "Streak": -1.0,
        "Year": 2014,
        "Date": "2014-06-18",
        "Winner": "CHC"
    },
    {
        "Unnamed_0": 7201,
        "Tm": "MIA",
        "Home_Away": "Home",
        "Opp": "NYM",
        "W_or_L": "L",
        "R": 0.0,
        "RA": 1.0,
        "Inn": 9.0,
        "Record": "36-36",
        "Rank": 3.0,
        "GB": "1.5",
        "Win": "Wheeler",
        "Loss": "Heaney",
        "Save": null,
        "Time": "2:35",
        "Attendance": 20334.0,
        "Streak": -2.0,
        "Year": 2014,
        "Date": "2014-06-19",
        "Winner": "NYM"
    },
    {
        "Unnamed_0": 7202,
        "Tm": "MIA",
        "Home_Away": "Home",
        "Opp": "NYM",
        "W_or_L": "W",
        "R": 3.0,
        "RA": 2.0,
        "Inn": 9.0,
        "Record": "37-36",
        "Rank": 3.0,
        "GB": "1.0",
        "Win": "Alvarez",
        "Loss": "Matsuzaka",
        "Save": "Cishek",
        "Time": "3:19",
        "Attendance": 19725.0,
        "Streak": 1.0,
        "Year": 2014,
        "Date": "2014-06-20",
        "Winner": "MIA"
    },
    {
        "Unnamed_0": 7203,
        "Tm": "MIA",
        "Home_Away": "Home",
        "Opp": "NYM",
        "W_or_L": "L",
        "R": 0.0,
        "RA": 4.0,
        "Inn": 9.0,
        "Record": "37-37",
        "Rank": 3.0,
        "GB": "1.5",
        "Win": "deGrom",
        "Loss": "Koehler",
        "Save": null,
        "Time": "2:38",
        "Attendance": 24502.0,
        "Streak": -1.0,
        "Year": 2014,
        "Date": "2014-06-21",
        "Winner": "NYM"
    },
    {
        "Unnamed_0": 7204,
        "Tm": "MIA",
        "Home_Away": "Home",
        "Opp": "NYM",
        "W_or_L": "L",
        "R": 5.0,
        "RA": 11.0,
        "Inn": 9.0,
        "Record": "37-38",
        "Rank": 3.0,
        "GB": "2.5",
        "Win": "Niese",
        "Loss": "DeSclafani",
        "Save": null,
        "Time": "3:09",
        "Attendance": 24613.0,
        "Streak": -2.0,
        "Year": 2014,
        "Date": "2014-06-22",
        "Winner": "NYM"
    },
    {
        "Unnamed_0": 7205,
        "Tm": "MIA",
        "Home_Away": "@",
        "Opp": "PHI",
        "W_or_L": "W",
        "R": 4.0,
        "RA": 0.0,
        "Inn": 9.0,
        "Record": "38-38",
        "Rank": 3.0,
        "GB": "2.5",
        "Win": "Eovaldi",
        "Loss": "Hernandez",
        "Save": null,
        "Time": "3:14",
        "Attendance": 32161.0,
        "Streak": 1.0,
        "Year": 2014,
        "Date": "2014-06-23",
        "Winner": "MIA"
    },
    {
        "Unnamed_0": 7206,
        "Tm": "MIA",
        "Home_Away": "@",
        "Opp": "PHI",
        "W_or_L": "L",
        "R": 4.0,
        "RA": 7.0,
        "Inn": 9.0,
        "Record": "38-39",
        "Rank": 3.0,
        "GB": "3.5",
        "Win": "Buchanan",
        "Loss": "Heaney",
        "Save": "Papelbon",
        "Time": "3:15",
        "Attendance": 24860.0,
        "Streak": -1.0,
        "Year": 2014,
        "Date": "2014-06-24",
        "Winner": "PHI"
    },
    {
        "Unnamed_0": 7207,
        "Tm": "MIA",
        "Home_Away": "@",
        "Opp": "PHI",
        "W_or_L": "W",
        "R": 3.0,
        "RA": 2.0,
        "Inn": 9.0,
        "Record": "39-39",
        "Rank": 3.0,
        "GB": "2.5",
        "Win": "Alvarez",
        "Loss": "Burnett",
        "Save": "Cishek",
        "Time": "2:53",
        "Attendance": 23360.0,
        "Streak": 1.0,
        "Year": 2014,
        "Date": "2014-06-25",
        "Winner": "MIA"
    },
    {
        "Unnamed_0": 7208,
        "Tm": "MIA",
        "Home_Away": "@",
        "Opp": "PHI",
        "W_or_L": "L-wo",
        "R": 3.0,
        "RA": 5.0,
        "Inn": 14.0,
        "Record": "39-40",
        "Rank": 3.0,
        "GB": "2.5",
        "Win": "De\u00a0Fratus",
        "Loss": "Hatcher",
        "Save": null,
        "Time": "4:41",
        "Attendance": 34168.0,
        "Streak": -1.0,
        "Year": 2014,
        "Date": "2014-06-26",
        "Winner": "PHI-wo"
    },
    {
        "Unnamed_0": 7209,
        "Tm": "MIA",
        "Home_Away": "Home",
        "Opp": "OAK",
        "W_or_L": "L",
        "R": 5.0,
        "RA": 9.0,
        "Inn": 9.0,
        "Record": "39-41",
        "Rank": 3.0,
        "GB": "2.5",
        "Win": "Gregerson",
        "Loss": "Cishek",
        "Save": null,
        "Time": "3:14",
        "Attendance": 18666.0,
        "Streak": -2.0,
        "Year": 2014,
        "Date": "2014-06-27",
        "Winner": "OAK"
    },
    {
        "Unnamed_0": 7210,
        "Tm": "MIA",
        "Home_Away": "Home",
        "Opp": "OAK",
        "W_or_L": "L",
        "R": 6.0,
        "RA": 7.0,
        "Inn": 14.0,
        "Record": "39-42",
        "Rank": 3.0,
        "GB": "4.0",
        "Win": "Johnson",
        "Loss": "Turner",
        "Save": "Francis",
        "Time": "4:47",
        "Attendance": 19358.0,
        "Streak": -3.0,
        "Year": 2014,
        "Date": "2014-06-28",
        "Winner": "OAK"
    },
    {
        "Unnamed_0": 7211,
        "Tm": "MIA",
        "Home_Away": "Home",
        "Opp": "OAK",
        "W_or_L": "L",
        "R": 3.0,
        "RA": 4.0,
        "Inn": 9.0,
        "Record": "39-43",
        "Rank": 3.0,
        "GB": "5.0",
        "Win": "Milone",
        "Loss": "Heaney",
        "Save": "Cook",
        "Time": "2:48",
        "Attendance": 21917.0,
        "Streak": -4.0,
        "Year": 2014,
        "Date": "2014-06-29",
        "Winner": "OAK"
    },
    {
        "Unnamed_0": 7212,
        "Tm": "MIA",
        "Home_Away": "Home",
        "Opp": "PHI",
        "W_or_L": "W-wo",
        "R": 5.0,
        "RA": 4.0,
        "Inn": 11.0,
        "Record": "40-43",
        "Rank": 3.0,
        "GB": "5.5",
        "Win": "Morris",
        "Loss": "De\u00a0Fratus",
        "Save": null,
        "Time": "3:37",
        "Attendance": 18518.0,
        "Streak": 1.0,
        "Year": 2014,
        "Date": "2014-07-01",
        "Winner": "MIA-wo"
    },
    {
        "Unnamed_0": 7213,
        "Tm": "MIA",
        "Home_Away": "Home",
        "Opp": "PHI",
        "W_or_L": "W",
        "R": 5.0,
        "RA": 0.0,
        "Inn": 9.0,
        "Record": "41-43",
        "Rank": 3.0,
        "GB": "5.5",
        "Win": "Koehler",
        "Loss": "Hamels",
        "Save": null,
        "Time": "3:11",
        "Attendance": 20084.0,
        "Streak": 2.0,
        "Year": 2014,
        "Date": "2014-07-02",
        "Winner": "MIA"
    },
    {
        "Unnamed_0": 7214,
        "Tm": "MIA",
        "Home_Away": "Home",
        "Opp": "PHI",
        "W_or_L": "L",
        "R": 4.0,
        "RA": 5.0,
        "Inn": 9.0,
        "Record": "41-44",
        "Rank": 3.0,
        "GB": "6.0",
        "Win": "Diekman",
        "Loss": "Cishek",
        "Save": "Papelbon",
        "Time": "3:12",
        "Attendance": 24915.0,
        "Streak": -1.0,
        "Year": 2014,
        "Date": "2014-07-03",
        "Winner": "PHI"
    },
    {
        "Unnamed_0": 7215,
        "Tm": "MIA",
        "Home_Away": "@",
        "Opp": "STL",
        "W_or_L": "L",
        "R": 2.0,
        "RA": 3.0,
        "Inn": 9.0,
        "Record": "41-45",
        "Rank": 3.0,
        "GB": "7.0",
        "Win": "Lynn",
        "Loss": "Eovaldi",
        "Save": "Rosenthal",
        "Time": "3:01",
        "Attendance": 46131.0,
        "Streak": -2.0,
        "Year": 2014,
        "Date": "2014-07-04",
        "Winner": "STL"
    },
    {
        "Unnamed_0": 7216,
        "Tm": "MIA",
        "Home_Away": "@",
        "Opp": "STL",
        "W_or_L": "W",
        "R": 6.0,
        "RA": 5.0,
        "Inn": 9.0,
        "Record": "42-45",
        "Rank": 3.0,
        "GB": "7.0",
        "Win": "Dunn",
        "Loss": "Rosenthal",
        "Save": "Cishek",
        "Time": "3:31",
        "Attendance": 45445.0,
        "Streak": 1.0,
        "Year": 2014,
        "Date": "2014-07-05",
        "Winner": "MIA"
    },
    {
        "Unnamed_0": 7217,
        "Tm": "MIA",
        "Home_Away": "@",
        "Opp": "STL",
        "W_or_L": "W",
        "R": 8.0,
        "RA": 4.0,
        "Inn": 9.0,
        "Record": "43-45",
        "Rank": 3.0,
        "GB": "6.0",
        "Win": "Alvarez",
        "Loss": "Gonzales",
        "Save": null,
        "Time": "3:13",
        "Attendance": 42160.0,
        "Streak": 2.0,
        "Year": 2014,
        "Date": "2014-07-06",
        "Winner": "MIA"
    },
    {
        "Unnamed_0": 7218,
        "Tm": "MIA",
        "Home_Away": "@",
        "Opp": "ARI",
        "W_or_L": "L",
        "R": 1.0,
        "RA": 9.0,
        "Inn": 9.0,
        "Record": "43-46",
        "Rank": 3.0,
        "GB": "6.0",
        "Win": "Anderson",
        "Loss": "Koehler",
        "Save": null,
        "Time": "2:56",
        "Attendance": 17103.0,
        "Streak": -1.0,
        "Year": 2014,
        "Date": "2014-07-07",
        "Winner": "ARI"
    },
    {
        "Unnamed_0": 7219,
        "Tm": "MIA",
        "Home_Away": "@",
        "Opp": "ARI",
        "W_or_L": "W",
        "R": 2.0,
        "RA": 1.0,
        "Inn": 9.0,
        "Record": "44-46",
        "Rank": 3.0,
        "GB": "5.0",
        "Win": "Dunn",
        "Loss": "Reed",
        "Save": "Cishek",
        "Time": "2:33",
        "Attendance": 18319.0,
        "Streak": 1.0,
        "Year": 2014,
        "Date": "2014-07-08",
        "Winner": "MIA"
    },
    {
        "Unnamed_0": 7220,
        "Tm": "MIA",
        "Home_Away": "@",
        "Opp": "ARI",
        "W_or_L": "L-wo",
        "R": 3.0,
        "RA": 4.0,
        "Inn": 10.0,
        "Record": "44-47",
        "Rank": 3.0,
        "GB": "6.0",
        "Win": "Ziegler",
        "Loss": "Cishek",
        "Save": null,
        "Time": "2:53",
        "Attendance": 18268.0,
        "Streak": -1.0,
        "Year": 2014,
        "Date": "2014-07-09",
        "Winner": "ARI-wo"
    },
    {
        "Unnamed_0": 7221,
        "Tm": "MIA",
        "Home_Away": "@",
        "Opp": "NYM",
        "W_or_L": "L",
        "R": 1.0,
        "RA": 7.0,
        "Inn": 9.0,
        "Record": "44-48",
        "Rank": 3.0,
        "GB": "5.5",
        "Win": "Wheeler",
        "Loss": "Alvarez",
        "Save": null,
        "Time": "2:43",
        "Attendance": 25914.0,
        "Streak": -2.0,
        "Year": 2014,
        "Date": "2014-07-11",
        "Winner": "NYM"
    },
    {
        "Unnamed_0": 7222,
        "Tm": "MIA",
        "Home_Away": "@",
        "Opp": "NYM",
        "W_or_L": "L",
        "R": 4.0,
        "RA": 5.0,
        "Inn": 9.0,
        "Record": "44-49",
        "Rank": 3.0,
        "GB": "6.5",
        "Win": "Black",
        "Loss": "Dunn",
        "Save": "Mejia",
        "Time": "2:52",
        "Attendance": 35283.0,
        "Streak": -3.0,
        "Year": 2014,
        "Date": "2014-07-12",
        "Winner": "NYM"
    },
    {
        "Unnamed_0": 7223,
        "Tm": "MIA",
        "Home_Away": "@",
        "Opp": "NYM",
        "W_or_L": "L",
        "R": 1.0,
        "RA": 9.0,
        "Inn": 9.0,
        "Record": "44-50",
        "Rank": 4.0,
        "GB": "7.5",
        "Win": "deGrom",
        "Loss": "Hand",
        "Save": null,
        "Time": "3:19",
        "Attendance": 28187.0,
        "Streak": -4.0,
        "Year": 2014,
        "Date": "2014-07-13",
        "Winner": "NYM"
    },
    {
        "Unnamed_0": 7224,
        "Tm": "MIA",
        "Home_Away": "Home",
        "Opp": "SFG",
        "W_or_L": "L",
        "R": 1.0,
        "RA": 9.0,
        "Inn": 9.0,
        "Record": "44-51",
        "Rank": 4.0,
        "GB": "8.5",
        "Win": "Bumgarner",
        "Loss": "Eovaldi",
        "Save": null,
        "Time": "3:00",
        "Attendance": 23017.0,
        "Streak": -5.0,
        "Year": 2014,
        "Date": "2014-07-18",
        "Winner": "SFG"
    },
    {
        "Unnamed_0": 7225,
        "Tm": "MIA",
        "Home_Away": "Home",
        "Opp": "SFG",
        "W_or_L": "L",
        "R": 3.0,
        "RA": 5.0,
        "Inn": 9.0,
        "Record": "44-52",
        "Rank": 4.0,
        "GB": "8.5",
        "Win": "Hudson",
        "Loss": "Alvarez",
        "Save": "Casilla",
        "Time": "3:01",
        "Attendance": 24882.0,
        "Streak": -6.0,
        "Year": 2014,
        "Date": "2014-07-19",
        "Winner": "SFG"
    },
    {
        "Unnamed_0": 7226,
        "Tm": "MIA",
        "Home_Away": "Home",
        "Opp": "SFG",
        "W_or_L": "W",
        "R": 3.0,
        "RA": 2.0,
        "Inn": 9.0,
        "Record": "45-52",
        "Rank": 4.0,
        "GB": "8.5",
        "Win": "Hand",
        "Loss": "Lincecum",
        "Save": "Cishek",
        "Time": "2:41",
        "Attendance": 25221.0,
        "Streak": 1.0,
        "Year": 2014,
        "Date": "2014-07-20",
        "Winner": "MIA"
    },
    {
        "Unnamed_0": 7227,
        "Tm": "MIA",
        "Home_Away": "@",
        "Opp": "ATL",
        "W_or_L": "W",
        "R": 3.0,
        "RA": 1.0,
        "Inn": 10.0,
        "Record": "46-52",
        "Rank": 3.0,
        "GB": "8.5",
        "Win": "Morris",
        "Loss": "Simmons",
        "Save": "Cishek",
        "Time": "3:36",
        "Attendance": 26766.0,
        "Streak": 2.0,
        "Year": 2014,
        "Date": "2014-07-21",
        "Winner": "MIA"
    },
    {
        "Unnamed_0": 7228,
        "Tm": "MIA",
        "Home_Away": "@",
        "Opp": "ATL",
        "W_or_L": "W",
        "R": 6.0,
        "RA": 5.0,
        "Inn": 9.0,
        "Record": "47-52",
        "Rank": 3.0,
        "GB": "8.5",
        "Win": "Turner",
        "Loss": "Minor",
        "Save": "Cishek",
        "Time": "3:13",
        "Attendance": 22998.0,
        "Streak": 3.0,
        "Year": 2014,
        "Date": "2014-07-22",
        "Winner": "MIA"
    },
    {
        "Unnamed_0": 7229,
        "Tm": "MIA",
        "Home_Away": "@",
        "Opp": "ATL",
        "W_or_L": "L",
        "R": 1.0,
        "RA": 6.0,
        "Inn": 9.0,
        "Record": "47-53",
        "Rank": 4.0,
        "GB": "8.5",
        "Win": "Santana",
        "Loss": "Eovaldi",
        "Save": null,
        "Time": "2:42",
        "Attendance": 20102.0,
        "Streak": -1.0,
        "Year": 2014,
        "Date": "2014-07-23",
        "Winner": "ATL"
    },
    {
        "Unnamed_0": 7230,
        "Tm": "MIA",
        "Home_Away": "@",
        "Opp": "ATL",
        "W_or_L": "W",
        "R": 3.0,
        "RA": 2.0,
        "Inn": 9.0,
        "Record": "48-53",
        "Rank": 3.0,
        "GB": "8.0",
        "Win": "Alvarez",
        "Loss": "Kimbrel",
        "Save": "Cishek",
        "Time": "2:33",
        "Attendance": 26446.0,
        "Streak": 1.0,
        "Year": 2014,
        "Date": "2014-07-24",
        "Winner": "MIA"
    },
    {
        "Unnamed_0": 7231,
        "Tm": "MIA",
        "Home_Away": "@",
        "Opp": "HOU",
        "W_or_L": "W",
        "R": 2.0,
        "RA": 0.0,
        "Inn": 9.0,
        "Record": "49-53",
        "Rank": 3.0,
        "GB": "8.0",
        "Win": "Hand",
        "Loss": "Keuchel",
        "Save": "Cishek",
        "Time": "2:59",
        "Attendance": 23132.0,
        "Streak": 2.0,
        "Year": 2014,
        "Date": "2014-07-25",
        "Winner": "MIA"
    },
    {
        "Unnamed_0": 7232,
        "Tm": "MIA",
        "Home_Away": "@",
        "Opp": "HOU",
        "W_or_L": "W",
        "R": 7.0,
        "RA": 3.0,
        "Inn": 9.0,
        "Record": "50-53",
        "Rank": 3.0,
        "GB": "7.0",
        "Win": "Koehler",
        "Loss": "Cosart",
        "Save": null,
        "Time": "3:29",
        "Attendance": 28968.0,
        "Streak": 3.0,
        "Year": 2014,
        "Date": "2014-07-26",
        "Winner": "MIA"
    },
    {
        "Unnamed_0": 7233,
        "Tm": "MIA",
        "Home_Away": "@",
        "Opp": "HOU",
        "W_or_L": "W",
        "R": 4.0,
        "RA": 2.0,
        "Inn": 9.0,
        "Record": "51-53",
        "Rank": 3.0,
        "GB": "7.0",
        "Win": "Turner",
        "Loss": "McHugh",
        "Save": "Cishek",
        "Time": "3:00",
        "Attendance": 17858.0,
        "Streak": 4.0,
        "Year": 2014,
        "Date": "2014-07-27",
        "Winner": "MIA"
    },
    {
        "Unnamed_0": 7234,
        "Tm": "MIA",
        "Home_Away": "Home",
        "Opp": "WSN",
        "W_or_L": "W-wo",
        "R": 7.0,
        "RA": 6.0,
        "Inn": 9.0,
        "Record": "52-53",
        "Rank": 3.0,
        "GB": "6.0",
        "Win": "Dunn",
        "Loss": "Soriano",
        "Save": null,
        "Time": "3:17",
        "Attendance": 20027.0,
        "Streak": 5.0,
        "Year": 2014,
        "Date": "2014-07-28",
        "Winner": "MIA-wo"
    },
    {
        "Unnamed_0": 7235,
        "Tm": "MIA",
        "Home_Away": "Home",
        "Opp": "WSN",
        "W_or_L": "W",
        "R": 3.0,
        "RA": 0.0,
        "Inn": 9.0,
        "Record": "53-53",
        "Rank": 3.0,
        "GB": "5.0",
        "Win": "Alvarez",
        "Loss": "Strasburg",
        "Save": "Cishek",
        "Time": "3:07",
        "Attendance": 22672.0,
        "Streak": 6.0,
        "Year": 2014,
        "Date": "2014-07-29",
        "Winner": "MIA"
    },
    {
        "Unnamed_0": 7236,
        "Tm": "MIA",
        "Home_Away": "Home",
        "Opp": "WSN",
        "W_or_L": "L",
        "R": 3.0,
        "RA": 4.0,
        "Inn": 9.0,
        "Record": "53-54",
        "Rank": 3.0,
        "GB": "6.0",
        "Win": "Roark",
        "Loss": "Hand",
        "Save": "Storen",
        "Time": "3:20",
        "Attendance": 26319.0,
        "Streak": -1.0,
        "Year": 2014,
        "Date": "2014-07-30",
        "Winner": "WSN"
    },
    {
        "Unnamed_0": 7237,
        "Tm": "MIA",
        "Home_Away": "Home",
        "Opp": "CIN",
        "W_or_L": "L",
        "R": 1.0,
        "RA": 3.0,
        "Inn": 9.0,
        "Record": "53-55",
        "Rank": 3.0,
        "GB": "6.0",
        "Win": "Cueto",
        "Loss": "Koehler",
        "Save": "Chapman",
        "Time": "2:43",
        "Attendance": 18056.0,
        "Streak": -2.0,
        "Year": 2014,
        "Date": "2014-07-31",
        "Winner": "CIN"
    },
    {
        "Unnamed_0": 7238,
        "Tm": "MIA",
        "Home_Away": "Home",
        "Opp": "CIN",
        "W_or_L": "L",
        "R": 2.0,
        "RA": 5.0,
        "Inn": 9.0,
        "Record": "53-56",
        "Rank": 3.0,
        "GB": "6.0",
        "Win": "Latos",
        "Loss": "Cosart",
        "Save": "Chapman",
        "Time": "2:58",
        "Attendance": 20410.0,
        "Streak": -3.0,
        "Year": 2014,
        "Date": "2014-08-01",
        "Winner": "CIN"
    },
    {
        "Unnamed_0": 7239,
        "Tm": "MIA",
        "Home_Away": "Home",
        "Opp": "CIN",
        "W_or_L": "W-wo",
        "R": 2.0,
        "RA": 1.0,
        "Inn": 10.0,
        "Record": "54-56",
        "Rank": 3.0,
        "GB": "6.0",
        "Win": "Dunn",
        "Loss": "LeCure",
        "Save": null,
        "Time": "3:11",
        "Attendance": 25159.0,
        "Streak": 1.0,
        "Year": 2014,
        "Date": "2014-08-02",
        "Winner": "MIA-wo"
    },
    {
        "Unnamed_0": 7240,
        "Tm": "MIA",
        "Home_Away": "Home",
        "Opp": "CIN",
        "W_or_L": "L",
        "R": 3.0,
        "RA": 7.0,
        "Inn": 9.0,
        "Record": "54-57",
        "Rank": 3.0,
        "GB": "7.0",
        "Win": "Leake",
        "Loss": "Turner",
        "Save": null,
        "Time": "3:05",
        "Attendance": 26707.0,
        "Streak": -1.0,
        "Year": 2014,
        "Date": "2014-08-03",
        "Winner": "CIN"
    },
    {
        "Unnamed_0": 7241,
        "Tm": "MIA",
        "Home_Away": "@",
        "Opp": "PIT",
        "W_or_L": "W",
        "R": 6.0,
        "RA": 3.0,
        "Inn": 9.0,
        "Record": "55-57",
        "Rank": 3.0,
        "GB": "5.5",
        "Win": "Ramos",
        "Loss": "Hughes",
        "Save": null,
        "Time": "3:03",
        "Attendance": 26734.0,
        "Streak": 1.0,
        "Year": 2014,
        "Date": "2014-08-05",
        "Winner": "MIA"
    },
    {
        "Unnamed_0": 7242,
        "Tm": "MIA",
        "Home_Away": "@",
        "Opp": "PIT",
        "W_or_L": "L",
        "R": 3.0,
        "RA": 7.0,
        "Inn": 9.0,
        "Record": "55-58",
        "Rank": 3.0,
        "GB": "6.5",
        "Win": "Locke",
        "Loss": "Koehler",
        "Save": null,
        "Time": "2:43",
        "Attendance": 26976.0,
        "Streak": -1.0,
        "Year": 2014,
        "Date": "2014-08-06",
        "Winner": "PIT"
    },
    {
        "Unnamed_0": 7243,
        "Tm": "MIA",
        "Home_Away": "@",
        "Opp": "PIT",
        "W_or_L": "L",
        "R": 2.0,
        "RA": 7.0,
        "Inn": 9.0,
        "Record": "55-59",
        "Rank": 3.0,
        "GB": "7.5",
        "Win": "Volquez",
        "Loss": "Flynn",
        "Save": null,
        "Time": "3:03",
        "Attendance": 29035.0,
        "Streak": -2.0,
        "Year": 2014,
        "Date": "2014-08-07",
        "Winner": "PIT"
    },
    {
        "Unnamed_0": 7244,
        "Tm": "MIA",
        "Home_Away": "@",
        "Opp": "CIN",
        "W_or_L": "W",
        "R": 2.0,
        "RA": 1.0,
        "Inn": 9.0,
        "Record": "56-59",
        "Rank": 3.0,
        "GB": "6.5",
        "Win": "Eovaldi",
        "Loss": "Leake",
        "Save": "Cishek",
        "Time": "2:40",
        "Attendance": 31193.0,
        "Streak": 1.0,
        "Year": 2014,
        "Date": "2014-08-08",
        "Winner": "MIA"
    },
    {
        "Unnamed_0": 7245,
        "Tm": "MIA",
        "Home_Away": "@",
        "Opp": "CIN",
        "W_or_L": "W",
        "R": 4.0,
        "RA": 3.0,
        "Inn": 9.0,
        "Record": "57-59",
        "Rank": 3.0,
        "GB": "6.5",
        "Win": "Penny",
        "Loss": "LeCure",
        "Save": "Cishek",
        "Time": "3:27",
        "Attendance": 34768.0,
        "Streak": 2.0,
        "Year": 2014,
        "Date": "2014-08-09",
        "Winner": "MIA"
    },
    {
        "Unnamed_0": 7246,
        "Tm": "MIA",
        "Home_Away": "@",
        "Opp": "CIN",
        "W_or_L": "L",
        "R": 2.0,
        "RA": 7.0,
        "Inn": 9.0,
        "Record": "57-60",
        "Rank": 3.0,
        "GB": "6.5",
        "Win": "Cueto",
        "Loss": "Hand",
        "Save": null,
        "Time": "2:45",
        "Attendance": 36122.0,
        "Streak": -1.0,
        "Year": 2014,
        "Date": "2014-08-10",
        "Winner": "CIN"
    },
    {
        "Unnamed_0": 7247,
        "Tm": "MIA",
        "Home_Away": "Home",
        "Opp": "STL",
        "W_or_L": "W",
        "R": 6.0,
        "RA": 5.0,
        "Inn": 9.0,
        "Record": "58-60",
        "Rank": 3.0,
        "GB": "6.0",
        "Win": "Koehler",
        "Loss": "Miller",
        "Save": "Cishek",
        "Time": "2:56",
        "Attendance": 21144.0,
        "Streak": 1.0,
        "Year": 2014,
        "Date": "2014-08-11",
        "Winner": "MIA"
    },
    {
        "Unnamed_0": 7248,
        "Tm": "MIA",
        "Home_Away": "Home",
        "Opp": "STL",
        "W_or_L": "W",
        "R": 3.0,
        "RA": 0.0,
        "Inn": 9.0,
        "Record": "59-60",
        "Rank": 3.0,
        "GB": "6.0",
        "Win": "Cosart",
        "Loss": "Wainwright",
        "Save": "Dunn",
        "Time": "2:34",
        "Attendance": 22703.0,
        "Streak": 2.0,
        "Year": 2014,
        "Date": "2014-08-12",
        "Winner": "MIA"
    },
    {
        "Unnamed_0": 7249,
        "Tm": "MIA",
        "Home_Away": "Home",
        "Opp": "STL",
        "W_or_L": "L",
        "R": 2.0,
        "RA": 5.0,
        "Inn": 9.0,
        "Record": "59-61",
        "Rank": 3.0,
        "GB": "7.0",
        "Win": "Masterson",
        "Loss": "Eovaldi",
        "Save": null,
        "Time": "2:40",
        "Attendance": 20044.0,
        "Streak": -1.0,
        "Year": 2014,
        "Date": "2014-08-13",
        "Winner": "STL"
    },
    {
        "Unnamed_0": 7250,
        "Tm": "MIA",
        "Home_Away": "Home",
        "Opp": "ARI",
        "W_or_L": "W-wo",
        "R": 5.0,
        "RA": 4.0,
        "Inn": 10.0,
        "Record": "60-61",
        "Rank": 3.0,
        "GB": "7.0",
        "Win": "Dunn",
        "Loss": "Hagens",
        "Save": null,
        "Time": "3:31",
        "Attendance": 17074.0,
        "Streak": 1.0,
        "Year": 2014,
        "Date": "2014-08-14",
        "Winner": "MIA-wo"
    },
    {
        "Unnamed_0": 7251,
        "Tm": "MIA",
        "Home_Away": "Home",
        "Opp": "ARI",
        "W_or_L": "L",
        "R": 2.0,
        "RA": 3.0,
        "Inn": 9.0,
        "Record": "60-62",
        "Rank": 3.0,
        "GB": "8.0",
        "Win": "Cahill",
        "Loss": "Hand",
        "Save": "Reed",
        "Time": "2:55",
        "Attendance": 18286.0,
        "Streak": -1.0,
        "Year": 2014,
        "Date": "2014-08-15",
        "Winner": "ARI"
    },
    {
        "Unnamed_0": 7252,
        "Tm": "MIA",
        "Home_Away": "Home",
        "Opp": "ARI",
        "W_or_L": "W",
        "R": 2.0,
        "RA": 1.0,
        "Inn": 9.0,
        "Record": "61-62",
        "Rank": 3.0,
        "GB": "8.0",
        "Win": "Alvarez",
        "Loss": "Miley",
        "Save": "Cishek",
        "Time": "2:25",
        "Attendance": 19563.0,
        "Streak": 1.0,
        "Year": 2014,
        "Date": "2014-08-16",
        "Winner": "MIA"
    },
    {
        "Unnamed_0": 7253,
        "Tm": "MIA",
        "Home_Away": "Home",
        "Opp": "ARI",
        "W_or_L": "W",
        "R": 10.0,
        "RA": 3.0,
        "Inn": 9.0,
        "Record": "62-62",
        "Rank": 3.0,
        "GB": "8.0",
        "Win": "Koehler",
        "Loss": "Collmenter",
        "Save": null,
        "Time": "2:56",
        "Attendance": 19296.0,
        "Streak": 2.0,
        "Year": 2014,
        "Date": "2014-08-17",
        "Winner": "MIA"
    },
    {
        "Unnamed_0": 7254,
        "Tm": "MIA",
        "Home_Away": "Home",
        "Opp": "TEX",
        "W_or_L": "W-wo",
        "R": 4.0,
        "RA": 3.0,
        "Inn": 10.0,
        "Record": "63-62",
        "Rank": 3.0,
        "GB": "8.5",
        "Win": "Dyson",
        "Loss": "Cotts",
        "Save": null,
        "Time": "3:59",
        "Attendance": 20277.0,
        "Streak": 3.0,
        "Year": 2014,
        "Date": "2014-08-19",
        "Winner": "MIA-wo"
    },
    {
        "Unnamed_0": 7255,
        "Tm": "MIA",
        "Home_Away": "Home",
        "Opp": "TEX",
        "W_or_L": "L",
        "R": 4.0,
        "RA": 5.0,
        "Inn": 9.0,
        "Record": "63-63",
        "Rank": 3.0,
        "GB": "9.5",
        "Win": "Martinez",
        "Loss": "Eovaldi",
        "Save": "Feliz",
        "Time": "2:55",
        "Attendance": 16672.0,
        "Streak": -1.0,
        "Year": 2014,
        "Date": "2014-08-20",
        "Winner": "TEX"
    },
    {
        "Unnamed_0": 7256,
        "Tm": "MIA",
        "Home_Away": "@",
        "Opp": "COL",
        "W_or_L": "W",
        "R": 13.0,
        "RA": 5.0,
        "Inn": 9.0,
        "Record": "64-63",
        "Rank": 3.0,
        "GB": "9.0",
        "Win": "Alvarez",
        "Loss": "Morales",
        "Save": null,
        "Time": "3:36",
        "Attendance": 30674.0,
        "Streak": 1.0,
        "Year": 2014,
        "Date": "2014-08-22",
        "Winner": "MIA"
    },
    {
        "Unnamed_0": 7257,
        "Tm": "MIA",
        "Home_Away": "@",
        "Opp": "COL",
        "W_or_L": "L-wo",
        "R": 4.0,
        "RA": 5.0,
        "Inn": 13.0,
        "Record": "64-64",
        "Rank": 3.0,
        "GB": "10.0",
        "Win": "Belisle",
        "Loss": "Dyson",
        "Save": null,
        "Time": "4:28",
        "Attendance": 31109.0,
        "Streak": -1.0,
        "Year": 2014,
        "Date": "2014-08-23",
        "Winner": "COL-wo"
    },
    {
        "Unnamed_0": 7258,
        "Tm": "MIA",
        "Home_Away": "@",
        "Opp": "COL",
        "W_or_L": "L",
        "R": 4.0,
        "RA": 7.0,
        "Inn": 9.0,
        "Record": "64-65",
        "Rank": 3.0,
        "GB": "11.0",
        "Win": "Bergman",
        "Loss": "Hand",
        "Save": "Hawkins",
        "Time": "3:07",
        "Attendance": 40509.0,
        "Streak": -2.0,
        "Year": 2014,
        "Date": "2014-08-24",
        "Winner": "COL"
    },
    {
        "Unnamed_0": 7259,
        "Tm": "MIA",
        "Home_Away": "@",
        "Opp": "LAA",
        "W_or_L": "W",
        "R": 7.0,
        "RA": 1.0,
        "Inn": 9.0,
        "Record": "65-65",
        "Rank": 3.0,
        "GB": "10.0",
        "Win": "Cosart",
        "Loss": "LeBlanc",
        "Save": null,
        "Time": "2:57",
        "Attendance": 35350.0,
        "Streak": 1.0,
        "Year": 2014,
        "Date": "2014-08-25",
        "Winner": "MIA"
    },
    {
        "Unnamed_0": 7260,
        "Tm": "MIA",
        "Home_Away": "@",
        "Opp": "LAA",
        "W_or_L": "L",
        "R": 2.0,
        "RA": 8.0,
        "Inn": 9.0,
        "Record": "65-66",
        "Rank": 3.0,
        "GB": "10.0",
        "Win": "Shoemaker",
        "Loss": "Eovaldi",
        "Save": null,
        "Time": "3:01",
        "Attendance": 33028.0,
        "Streak": -1.0,
        "Year": 2014,
        "Date": "2014-08-26",
        "Winner": "LAA"
    },
    {
        "Unnamed_0": 7261,
        "Tm": "MIA",
        "Home_Away": "@",
        "Opp": "LAA",
        "W_or_L": "L",
        "R": 1.0,
        "RA": 6.0,
        "Inn": 9.0,
        "Record": "65-67",
        "Rank": 3.0,
        "GB": "10.0",
        "Win": "Santiago",
        "Loss": "Alvarez",
        "Save": null,
        "Time": "2:51",
        "Attendance": 34657.0,
        "Streak": -2.0,
        "Year": 2014,
        "Date": "2014-08-27",
        "Winner": "LAA"
    },
    {
        "Unnamed_0": 7262,
        "Tm": "MIA",
        "Home_Away": "@",
        "Opp": "ATL",
        "W_or_L": "L",
        "R": 2.0,
        "RA": 5.0,
        "Inn": 9.0,
        "Record": "65-68",
        "Rank": 3.0,
        "GB": "11.0",
        "Win": "Carpenter",
        "Loss": "Hatcher",
        "Save": "Kimbrel",
        "Time": "3:01",
        "Attendance": 26278.0,
        "Streak": -3.0,
        "Year": 2014,
        "Date": "2014-08-29",
        "Winner": "ATL"
    },
    {
        "Unnamed_0": 7263,
        "Tm": "MIA",
        "Home_Away": "@",
        "Opp": "ATL",
        "W_or_L": "W",
        "R": 4.0,
        "RA": 0.0,
        "Inn": 9.0,
        "Record": "66-68",
        "Rank": 3.0,
        "GB": "11.0",
        "Win": "Cosart",
        "Loss": "Harang",
        "Save": null,
        "Time": "2:54",
        "Attendance": 25335.0,
        "Streak": 1.0,
        "Year": 2014,
        "Date": "2014-08-30",
        "Winner": "MIA"
    },
    {
        "Unnamed_0": 7264,
        "Tm": "MIA",
        "Home_Away": "@",
        "Opp": "ATL",
        "W_or_L": "L",
        "R": 0.0,
        "RA": 1.0,
        "Inn": 9.0,
        "Record": "66-69",
        "Rank": 3.0,
        "GB": "11.0",
        "Win": "Wood",
        "Loss": "Eovaldi",
        "Save": "Kimbrel",
        "Time": "2:33",
        "Attendance": 45754.0,
        "Streak": -1.0,
        "Year": 2014,
        "Date": "2014-08-31",
        "Winner": "ATL"
    },
    {
        "Unnamed_0": 7265,
        "Tm": "MIA",
        "Home_Away": "Home",
        "Opp": "NYM",
        "W_or_L": "W",
        "R": 9.0,
        "RA": 6.0,
        "Inn": 9.0,
        "Record": "67-69",
        "Rank": 3.0,
        "GB": "11.0",
        "Win": "Ramos",
        "Loss": "Familia",
        "Save": "Cishek",
        "Time": "3:32",
        "Attendance": 23090.0,
        "Streak": 1.0,
        "Year": 2014,
        "Date": "2014-09-01",
        "Winner": "MIA"
    },
    {
        "Unnamed_0": 7266,
        "Tm": "MIA",
        "Home_Away": "Home",
        "Opp": "NYM",
        "W_or_L": "L",
        "R": 6.0,
        "RA": 8.0,
        "Inn": 9.0,
        "Record": "67-70",
        "Rank": 3.0,
        "GB": "11.0",
        "Win": "Niese",
        "Loss": "Penny",
        "Save": "Mejia",
        "Time": "3:10",
        "Attendance": 17745.0,
        "Streak": -1.0,
        "Year": 2014,
        "Date": "2014-09-02",
        "Winner": "NYM"
    },
    {
        "Unnamed_0": 7267,
        "Tm": "MIA",
        "Home_Away": "Home",
        "Opp": "NYM",
        "W_or_L": "L",
        "R": 3.0,
        "RA": 4.0,
        "Inn": 9.0,
        "Record": "67-71",
        "Rank": 3.0,
        "GB": "12.0",
        "Win": "Torres",
        "Loss": "Dunn",
        "Save": "Mejia",
        "Time": "3:07",
        "Attendance": 17737.0,
        "Streak": -2.0,
        "Year": 2014,
        "Date": "2014-09-03",
        "Winner": "NYM"
    },
    {
        "Unnamed_0": 7268,
        "Tm": "MIA",
        "Home_Away": "Home",
        "Opp": "ATL",
        "W_or_L": "W",
        "R": 11.0,
        "RA": 3.0,
        "Inn": 9.0,
        "Record": "68-71",
        "Rank": 3.0,
        "GB": "11.0",
        "Win": "Cosart",
        "Loss": "Harang",
        "Save": null,
        "Time": "2:48",
        "Attendance": 19951.0,
        "Streak": 1.0,
        "Year": 2014,
        "Date": "2014-09-05",
        "Winner": "MIA"
    },
    {
        "Unnamed_0": 7269,
        "Tm": "MIA",
        "Home_Away": "Home",
        "Opp": "ATL",
        "W_or_L": "L",
        "R": 3.0,
        "RA": 4.0,
        "Inn": 10.0,
        "Record": "68-72",
        "Rank": 3.0,
        "GB": "11.0",
        "Win": "Carpenter",
        "Loss": "Morris",
        "Save": "Kimbrel",
        "Time": "3:28",
        "Attendance": 25485.0,
        "Streak": -1.0,
        "Year": 2014,
        "Date": "2014-09-06",
        "Winner": "ATL"
    },
    {
        "Unnamed_0": 7270,
        "Tm": "MIA",
        "Home_Away": "Home",
        "Opp": "ATL",
        "W_or_L": "W",
        "R": 4.0,
        "RA": 0.0,
        "Inn": 9.0,
        "Record": "69-72",
        "Rank": 3.0,
        "GB": "11.0",
        "Win": "Hand",
        "Loss": "Teheran",
        "Save": null,
        "Time": "2:44",
        "Attendance": 20013.0,
        "Streak": 1.0,
        "Year": 2014,
        "Date": "2014-09-07",
        "Winner": "MIA"
    },
    {
        "Unnamed_0": 7271,
        "Tm": "MIA",
        "Home_Away": "@",
        "Opp": "MIL",
        "W_or_L": "W",
        "R": 6.0,
        "RA": 4.0,
        "Inn": 9.0,
        "Record": "70-72",
        "Rank": 3.0,
        "GB": "11.0",
        "Win": "Penny",
        "Loss": "Gallardo",
        "Save": "Cishek",
        "Time": "2:50",
        "Attendance": 31203.0,
        "Streak": 2.0,
        "Year": 2014,
        "Date": "2014-09-08",
        "Winner": "MIA"
    },
    {
        "Unnamed_0": 7272,
        "Tm": "MIA",
        "Home_Away": "@",
        "Opp": "MIL",
        "W_or_L": "W",
        "R": 6.0,
        "RA": 3.0,
        "Inn": 9.0,
        "Record": "71-72",
        "Rank": 3.0,
        "GB": "11.0",
        "Win": "Morris",
        "Loss": "Rodr\u00edguez",
        "Save": "Cishek",
        "Time": "3:50",
        "Attendance": 29590.0,
        "Streak": 3.0,
        "Year": 2014,
        "Date": "2014-09-09",
        "Winner": "MIA"
    },
    {
        "Unnamed_0": 7273,
        "Tm": "MIA",
        "Home_Away": "@",
        "Opp": "MIL",
        "W_or_L": "L",
        "R": 1.0,
        "RA": 4.0,
        "Inn": 9.0,
        "Record": "71-73",
        "Rank": 3.0,
        "GB": "11.0",
        "Win": "Peralta",
        "Loss": "Cosart",
        "Save": "Rodr\u00edguez",
        "Time": "2:59",
        "Attendance": 25219.0,
        "Streak": -1.0,
        "Year": 2014,
        "Date": "2014-09-10",
        "Winner": "MIL"
    },
    {
        "Unnamed_0": 7274,
        "Tm": "MIA",
        "Home_Away": "@",
        "Opp": "MIL",
        "W_or_L": "L",
        "R": 2.0,
        "RA": 4.0,
        "Inn": 9.0,
        "Record": "71-74",
        "Rank": 3.0,
        "GB": "12.0",
        "Win": "Fiers",
        "Loss": "Eovaldi",
        "Save": "Rodr\u00edguez",
        "Time": "3:19",
        "Attendance": 34028.0,
        "Streak": -2.0,
        "Year": 2014,
        "Date": "2014-09-11",
        "Winner": "MIL"
    },
    {
        "Unnamed_0": 7275,
        "Tm": "MIA",
        "Home_Away": "@",
        "Opp": "PHI",
        "W_or_L": "L-wo",
        "R": 1.0,
        "RA": 3.0,
        "Inn": 10.0,
        "Record": "71-75",
        "Rank": 3.0,
        "GB": "12.0",
        "Win": "Diekman",
        "Loss": "Jennings",
        "Save": null,
        "Time": "3:02",
        "Attendance": 27039.0,
        "Streak": -3.0,
        "Year": 2014,
        "Date": "2014-09-12",
        "Winner": "PHI-wo"
    },
    {
        "Unnamed_0": 7276,
        "Tm": "MIA",
        "Home_Away": "@",
        "Opp": "PHI",
        "W_or_L": "L",
        "R": 1.0,
        "RA": 2.0,
        "Inn": 9.0,
        "Record": "71-76",
        "Rank": 3.0,
        "GB": "13.0",
        "Win": "Kendrick",
        "Loss": "Hand",
        "Save": "Papelbon",
        "Time": "2:33",
        "Attendance": 26163.0,
        "Streak": -4.0,
        "Year": 2014,
        "Date": "2014-09-13",
        "Winner": "PHI"
    },
    {
        "Unnamed_0": 7277,
        "Tm": "MIA",
        "Home_Away": "@",
        "Opp": "PHI",
        "W_or_L": "W",
        "R": 5.0,
        "RA": 4.0,
        "Inn": 9.0,
        "Record": "72-76",
        "Rank": 3.0,
        "GB": "13.0",
        "Win": "DeSclafani",
        "Loss": "Papelbon",
        "Save": "Cishek",
        "Time": "3:20",
        "Attendance": 30201.0,
        "Streak": 1.0,
        "Year": 2014,
        "Date": "2014-09-14",
        "Winner": "MIA"
    },
    {
        "Unnamed_0": 7278,
        "Tm": "MIA",
        "Home_Away": "@",
        "Opp": "NYM",
        "W_or_L": "W",
        "R": 6.0,
        "RA": 5.0,
        "Inn": 9.0,
        "Record": "73-76",
        "Rank": 3.0,
        "GB": "13.0",
        "Win": "Dyson",
        "Loss": "Familia",
        "Save": "Cishek",
        "Time": "3:10",
        "Attendance": 23027.0,
        "Streak": 2.0,
        "Year": 2014,
        "Date": "2014-09-15",
        "Winner": "MIA"
    },
    {
        "Unnamed_0": 7279,
        "Tm": "MIA",
        "Home_Away": "@",
        "Opp": "NYM",
        "W_or_L": "L",
        "R": 1.0,
        "RA": 9.0,
        "Inn": 9.0,
        "Record": "73-77",
        "Rank": 3.0,
        "GB": "14.0",
        "Win": "Colon",
        "Loss": "Eovaldi",
        "Save": null,
        "Time": "2:47",
        "Attendance": 21602.0,
        "Streak": -1.0,
        "Year": 2014,
        "Date": "2014-09-16",
        "Winner": "NYM"
    },
    {
        "Unnamed_0": 7280,
        "Tm": "MIA",
        "Home_Away": "@",
        "Opp": "NYM",
        "W_or_L": "W",
        "R": 4.0,
        "RA": 3.0,
        "Inn": 9.0,
        "Record": "74-77",
        "Rank": 3.0,
        "GB": "13.0",
        "Win": "Alvarez",
        "Loss": "Gee",
        "Save": "Cishek",
        "Time": "3:07",
        "Attendance": 23892.0,
        "Streak": 1.0,
        "Year": 2014,
        "Date": "2014-09-17",
        "Winner": "MIA"
    },
    {
        "Unnamed_0": 7281,
        "Tm": "MIA",
        "Home_Away": "Home",
        "Opp": "WSN",
        "W_or_L": "L",
        "R": 2.0,
        "RA": 6.0,
        "Inn": 9.0,
        "Record": "74-78",
        "Rank": 3.0,
        "GB": "14.0",
        "Win": "Gonzalez",
        "Loss": "Hand",
        "Save": null,
        "Time": "2:46",
        "Attendance": 18010.0,
        "Streak": -1.0,
        "Year": 2014,
        "Date": "2014-09-18",
        "Winner": "WSN"
    },
    {
        "Unnamed_0": 7282,
        "Tm": "MIA",
        "Home_Away": "Home",
        "Opp": "WSN",
        "W_or_L": "L",
        "R": 2.0,
        "RA": 3.0,
        "Inn": 9.0,
        "Record": "74-79",
        "Rank": 3.0,
        "GB": "15.0",
        "Win": "Fister",
        "Loss": "Koehler",
        "Save": "Storen",
        "Time": "2:47",
        "Attendance": 19815.0,
        "Streak": -2.0,
        "Year": 2014,
        "Date": "2014-09-19",
        "Winner": "WSN"
    },
    {
        "Unnamed_0": 7283,
        "Tm": "MIA",
        "Home_Away": "Home",
        "Opp": "WSN",
        "W_or_L": "L",
        "R": 2.0,
        "RA": 3.0,
        "Inn": 9.0,
        "Record": "74-80",
        "Rank": 4.0,
        "GB": "16.0",
        "Win": "Zimmermann",
        "Loss": "Cosart",
        "Save": "Storen",
        "Time": "2:59",
        "Attendance": 20983.0,
        "Streak": -3.0,
        "Year": 2014,
        "Date": "2014-09-20",
        "Winner": "WSN"
    },
    {
        "Unnamed_0": 7284,
        "Tm": "MIA",
        "Home_Away": "Home",
        "Opp": "WSN",
        "W_or_L": "L",
        "R": 1.0,
        "RA": 2.0,
        "Inn": 9.0,
        "Record": "74-81",
        "Rank": 4.0,
        "GB": "17.0",
        "Win": "Strasburg",
        "Loss": "Eovaldi",
        "Save": "Soriano",
        "Time": "2:30",
        "Attendance": 22806.0,
        "Streak": -4.0,
        "Year": 2014,
        "Date": "2014-09-21",
        "Winner": "WSN"
    },
    {
        "Unnamed_0": 7285,
        "Tm": "MIA",
        "Home_Away": "Home",
        "Opp": "PHI",
        "W_or_L": "W",
        "R": 2.0,
        "RA": 0.0,
        "Inn": 9.0,
        "Record": "75-81",
        "Rank": 4.0,
        "GB": "17.0",
        "Win": "Alvarez",
        "Loss": "Hamels",
        "Save": "Cishek",
        "Time": "2:20",
        "Attendance": 18969.0,
        "Streak": 1.0,
        "Year": 2014,
        "Date": "2014-09-23",
        "Winner": "MIA"
    },
    {
        "Unnamed_0": 7286,
        "Tm": "MIA",
        "Home_Away": "Home",
        "Opp": "PHI",
        "W_or_L": "L",
        "R": 1.0,
        "RA": 2.0,
        "Inn": 9.0,
        "Record": "75-82",
        "Rank": 4.0,
        "GB": "17.5",
        "Win": "Kendrick",
        "Loss": "Hatcher",
        "Save": "Papelbon",
        "Time": "2:54",
        "Attendance": 22491.0,
        "Streak": -1.0,
        "Year": 2014,
        "Date": "2014-09-24",
        "Winner": "PHI"
    },
    {
        "Unnamed_0": 7287,
        "Tm": "MIA",
        "Home_Away": "Home",
        "Opp": "PHI",
        "W_or_L": "W",
        "R": 6.0,
        "RA": 4.0,
        "Inn": 9.0,
        "Record": "76-82",
        "Rank": 4.0,
        "GB": "17.0",
        "Win": "Koehler",
        "Loss": "Diekman",
        "Save": "Cishek",
        "Time": "3:01",
        "Attendance": 24259.0,
        "Streak": 1.0,
        "Year": 2014,
        "Date": "2014-09-25",
        "Winner": "MIA"
    },
    {
        "Unnamed_0": 7288,
        "Tm": "MIA",
        "Home_Away": "@",
        "Opp": "WSN",
        "W_or_L": "L",
        "R": 0.0,
        "RA": 4.0,
        "Inn": 9.0,
        "Record": "76-83",
        "Rank": 2.0,
        "GB": "17.0",
        "Win": "Fister",
        "Loss": "Cosart",
        "Save": null,
        "Time": "2:31",
        "Attendance": 27920.0,
        "Streak": -1.0,
        "Year": 2014,
        "Date": "2014-09-26",
        "Winner": "WSN"
    },
    {
        "Unnamed_0": 7289,
        "Tm": "MIA",
        "Home_Away": "@",
        "Opp": "WSN",
        "W_or_L": "W",
        "R": 15.0,
        "RA": 7.0,
        "Inn": 9.0,
        "Record": "77-83",
        "Rank": 2.0,
        "GB": "17.0",
        "Win": "Ramos",
        "Loss": "Hill",
        "Save": null,
        "Time": "3:34",
        "Attendance": 34190.0,
        "Streak": 1.0,
        "Year": 2014,
        "Date": "2014-09-26",
        "Winner": "MIA"
    },
    {
        "Unnamed_0": 7290,
        "Tm": "MIA",
        "Home_Away": "@",
        "Opp": "WSN",
        "W_or_L": "L",
        "R": 1.0,
        "RA": 5.0,
        "Inn": 9.0,
        "Record": "77-84",
        "Rank": 4.0,
        "GB": "18.0",
        "Win": "Strasburg",
        "Loss": "Eovaldi",
        "Save": null,
        "Time": "2:57",
        "Attendance": 37529.0,
        "Streak": -1.0,
        "Year": 2014,
        "Date": "2014-09-27",
        "Winner": "WSN"
    },
    {
        "Unnamed_0": 7291,
        "Tm": "MIA",
        "Home_Away": "@",
        "Opp": "WSN",
        "W_or_L": "L",
        "R": 0.0,
        "RA": 1.0,
        "Inn": 9.0,
        "Record": "77-85",
        "Rank": 4.0,
        "GB": "19.0",
        "Win": "Zimmermann",
        "Loss": "Alvarez",
        "Save": null,
        "Time": "2:01",
        "Attendance": 35085.0,
        "Streak": -2.0,
        "Year": 2014,
        "Date": "2014-09-28",
        "Winner": "WSN"
    }
]}