{"team_games": [
    {
        "Unnamed_0": 1296,
        "Tm": "COL",
        "Home_Away": "@",
        "Opp": "MIL",
        "W_or_L": "L-wo",
        "R": 4.0,
        "RA": 5.0,
        "Inn": 10.0,
        "Record": "0-1",
        "Rank": 3.0,
        "GB": "1.0",
        "Win": "Henderson",
        "Loss": "Ottavino",
        "Save": null,
        "Time": "3:13",
        "Attendance": 45781.0,
        "Streak": -1.0,
        "Year": 2013,
        "Date": "2013-04-01",
        "Winner": "MIL-wo"
    },
    {
        "Unnamed_0": 1297,
        "Tm": "COL",
        "Home_Away": "@",
        "Opp": "MIL",
        "W_or_L": "W",
        "R": 8.0,
        "RA": 4.0,
        "Inn": 9.0,
        "Record": "1-1",
        "Rank": 1.0,
        "GB": "Tied",
        "Win": "Escalona",
        "Loss": "Gonzalez",
        "Save": "Betancourt",
        "Time": "3:22",
        "Attendance": 24753.0,
        "Streak": 1.0,
        "Year": 2013,
        "Date": "2013-04-02",
        "Winner": "COL"
    },
    {
        "Unnamed_0": 1298,
        "Tm": "COL",
        "Home_Away": "@",
        "Opp": "MIL",
        "W_or_L": "W",
        "R": 7.0,
        "RA": 3.0,
        "Inn": 9.0,
        "Record": "2-1",
        "Rank": 1.0,
        "GB": "Tied",
        "Win": "Nicasio",
        "Loss": "Peralta",
        "Save": null,
        "Time": "3:31",
        "Attendance": 25766.0,
        "Streak": 2.0,
        "Year": 2013,
        "Date": "2013-04-03",
        "Winner": "COL"
    },
    {
        "Unnamed_0": 1299,
        "Tm": "COL",
        "Home_Away": "Home",
        "Opp": "SDP",
        "W_or_L": "W",
        "R": 5.0,
        "RA": 2.0,
        "Inn": 9.0,
        "Record": "3-1",
        "Rank": 1.0,
        "GB": "Tied",
        "Win": "Francis",
        "Loss": "Marquis",
        "Save": "Betancourt",
        "Time": "2:45",
        "Attendance": 49077.0,
        "Streak": 3.0,
        "Year": 2013,
        "Date": "2013-04-05",
        "Winner": "COL"
    },
    {
        "Unnamed_0": 1300,
        "Tm": "COL",
        "Home_Away": "Home",
        "Opp": "SDP",
        "W_or_L": "W",
        "R": 6.0,
        "RA": 3.0,
        "Inn": 9.0,
        "Record": "4-1",
        "Rank": 1.0,
        "GB": "Tied",
        "Win": "Garland",
        "Loss": "Ross",
        "Save": "Betancourt",
        "Time": "2:54",
        "Attendance": 31133.0,
        "Streak": 4.0,
        "Year": 2013,
        "Date": "2013-04-06",
        "Winner": "COL"
    },
    {
        "Unnamed_0": 1301,
        "Tm": "COL",
        "Home_Away": "Home",
        "Opp": "SDP",
        "W_or_L": "W",
        "R": 9.0,
        "RA": 1.0,
        "Inn": 9.0,
        "Record": "5-1",
        "Rank": 1.0,
        "GB": "Tied",
        "Win": "Chac\u00edn",
        "Loss": "Volquez",
        "Save": null,
        "Time": "2:53",
        "Attendance": 31060.0,
        "Streak": 5.0,
        "Year": 2013,
        "Date": "2013-04-07",
        "Winner": "COL"
    },
    {
        "Unnamed_0": 1302,
        "Tm": "COL",
        "Home_Away": "@",
        "Opp": "SFG",
        "W_or_L": "L",
        "R": 2.0,
        "RA": 4.0,
        "Inn": 9.0,
        "Record": "5-2",
        "Rank": 1.0,
        "GB": "Tied",
        "Win": "Bumgarner",
        "Loss": "De\u00a0La\u00a0Rosa",
        "Save": "Romo",
        "Time": "2:52",
        "Attendance": 41133.0,
        "Streak": -1.0,
        "Year": 2013,
        "Date": "2013-04-08",
        "Winner": "SFG"
    },
    {
        "Unnamed_0": 1303,
        "Tm": "COL",
        "Home_Away": "@",
        "Opp": "SFG",
        "W_or_L": "L",
        "R": 6.0,
        "RA": 9.0,
        "Inn": 9.0,
        "Record": "5-3",
        "Rank": 1.0,
        "GB": "Tied",
        "Win": "Casilla",
        "Loss": "Belisle",
        "Save": "Romo",
        "Time": "3:11",
        "Attendance": 41910.0,
        "Streak": -2.0,
        "Year": 2013,
        "Date": "2013-04-09",
        "Winner": "SFG"
    },
    {
        "Unnamed_0": 1304,
        "Tm": "COL",
        "Home_Away": "@",
        "Opp": "SFG",
        "W_or_L": "L",
        "R": 0.0,
        "RA": 10.0,
        "Inn": 9.0,
        "Record": "5-4",
        "Rank": 4.0,
        "GB": "1.0",
        "Win": "Zito",
        "Loss": "Francis",
        "Save": null,
        "Time": "3:08",
        "Attendance": 41606.0,
        "Streak": -3.0,
        "Year": 2013,
        "Date": "2013-04-10",
        "Winner": "SFG"
    },
    {
        "Unnamed_0": 1305,
        "Tm": "COL",
        "Home_Away": "@",
        "Opp": "SDP",
        "W_or_L": "W",
        "R": 7.0,
        "RA": 5.0,
        "Inn": 9.0,
        "Record": "6-4",
        "Rank": 3.0,
        "GB": "1.0",
        "Win": "Brothers",
        "Loss": "Street",
        "Save": "Betancourt",
        "Time": "3:06",
        "Attendance": 21814.0,
        "Streak": 1.0,
        "Year": 2013,
        "Date": "2013-04-12",
        "Winner": "COL"
    },
    {
        "Unnamed_0": 1306,
        "Tm": "COL",
        "Home_Away": "@",
        "Opp": "SDP",
        "W_or_L": "W",
        "R": 9.0,
        "RA": 5.0,
        "Inn": 9.0,
        "Record": "7-4",
        "Rank": 2.0,
        "GB": "0.5",
        "Win": "Chac\u00edn",
        "Loss": "Volquez",
        "Save": null,
        "Time": "3:20",
        "Attendance": 29523.0,
        "Streak": 2.0,
        "Year": 2013,
        "Date": "2013-04-13",
        "Winner": "COL"
    },
    {
        "Unnamed_0": 1307,
        "Tm": "COL",
        "Home_Away": "@",
        "Opp": "SDP",
        "W_or_L": "W",
        "R": 2.0,
        "RA": 1.0,
        "Inn": 9.0,
        "Record": "8-4",
        "Rank": 2.0,
        "GB": "0.5",
        "Win": "De\u00a0La\u00a0Rosa",
        "Loss": "Thayer",
        "Save": "Betancourt",
        "Time": "2:52",
        "Attendance": 21337.0,
        "Streak": 3.0,
        "Year": 2013,
        "Date": "2013-04-14",
        "Winner": "COL"
    },
    {
        "Unnamed_0": 1308,
        "Tm": "COL",
        "Home_Away": "Home",
        "Opp": "NYM",
        "W_or_L": "W",
        "R": 8.0,
        "RA": 4.0,
        "Inn": 9.0,
        "Record": "9-4",
        "Rank": 1.0,
        "GB": "up 1.0",
        "Win": "Nicasio",
        "Loss": "Gee",
        "Save": null,
        "Time": "2:59",
        "Attendance": 21510.0,
        "Streak": 4.0,
        "Year": 2013,
        "Date": "2013-04-16",
        "Winner": "COL"
    },
    {
        "Unnamed_0": 1309,
        "Tm": "COL",
        "Home_Away": "Home",
        "Opp": "NYM",
        "W_or_L": "W-wo",
        "R": 9.0,
        "RA": 8.0,
        "Inn": 10.0,
        "Record": "10-4",
        "Rank": 1.0,
        "GB": "up 1.0",
        "Win": "Betancourt",
        "Loss": "Burke",
        "Save": null,
        "Time": "4:19",
        "Attendance": 20239.0,
        "Streak": 5.0,
        "Year": 2013,
        "Date": "2013-04-16",
        "Winner": "COL-wo"
    },
    {
        "Unnamed_0": 1310,
        "Tm": "COL",
        "Home_Away": "Home",
        "Opp": "NYM",
        "W_or_L": "W",
        "R": 11.0,
        "RA": 3.0,
        "Inn": 9.0,
        "Record": "11-4",
        "Rank": 1.0,
        "GB": "up 2.0",
        "Win": "Garland",
        "Loss": "Niese",
        "Save": null,
        "Time": "2:54",
        "Attendance": 18341.0,
        "Streak": 6.0,
        "Year": 2013,
        "Date": "2013-04-18",
        "Winner": "COL"
    },
    {
        "Unnamed_0": 1311,
        "Tm": "COL",
        "Home_Away": "Home",
        "Opp": "ARI",
        "W_or_L": "W",
        "R": 3.0,
        "RA": 1.0,
        "Inn": 9.0,
        "Record": "12-4",
        "Rank": 1.0,
        "GB": "up 2.5",
        "Win": "Chac\u00edn",
        "Loss": "Kennedy",
        "Save": "Betancourt",
        "Time": "2:46",
        "Attendance": 23445.0,
        "Streak": 7.0,
        "Year": 2013,
        "Date": "2013-04-19",
        "Winner": "COL"
    },
    {
        "Unnamed_0": 1312,
        "Tm": "COL",
        "Home_Away": "Home",
        "Opp": "ARI",
        "W_or_L": "W",
        "R": 4.0,
        "RA": 3.0,
        "Inn": 9.0,
        "Record": "13-4",
        "Rank": 1.0,
        "GB": "up 2.5",
        "Win": "De\u00a0La\u00a0Rosa",
        "Loss": "Cahill",
        "Save": "Betancourt",
        "Time": "2:50",
        "Attendance": 30380.0,
        "Streak": 8.0,
        "Year": 2013,
        "Date": "2013-04-20",
        "Winner": "COL"
    },
    {
        "Unnamed_0": 1313,
        "Tm": "COL",
        "Home_Away": "Home",
        "Opp": "ARI",
        "W_or_L": "L",
        "R": 4.0,
        "RA": 5.0,
        "Inn": 9.0,
        "Record": "13-5",
        "Rank": 1.0,
        "GB": "up 1.5",
        "Win": "Bell",
        "Loss": "Lopez",
        "Save": "Putz",
        "Time": "3:15",
        "Attendance": 42507.0,
        "Streak": -1.0,
        "Year": 2013,
        "Date": "2013-04-21",
        "Winner": "ARI"
    },
    {
        "Unnamed_0": 1314,
        "Tm": "COL",
        "Home_Away": "Home",
        "Opp": "ATL",
        "W_or_L": "L",
        "R": 3.0,
        "RA": 4.0,
        "Inn": 9.0,
        "Record": "13-6",
        "Rank": 1.0,
        "GB": "up 0.5",
        "Win": "Minor",
        "Loss": "Francis",
        "Save": "Kimbrel",
        "Time": "2:37",
        "Attendance": 19124.0,
        "Streak": -2.0,
        "Year": 2013,
        "Date": "2013-04-23",
        "Winner": "ATL"
    },
    {
        "Unnamed_0": 1315,
        "Tm": "COL",
        "Home_Away": "Home",
        "Opp": "ATL",
        "W_or_L": "L",
        "R": 2.0,
        "RA": 10.0,
        "Inn": 9.0,
        "Record": "13-7",
        "Rank": 1.0,
        "GB": "up 0.5",
        "Win": "Teheran",
        "Loss": "Garland",
        "Save": null,
        "Time": "2:51",
        "Attendance": 21724.0,
        "Streak": -3.0,
        "Year": 2013,
        "Date": "2013-04-23",
        "Winner": "ATL"
    },
    {
        "Unnamed_0": 1316,
        "Tm": "COL",
        "Home_Away": "Home",
        "Opp": "ATL",
        "W_or_L": "W-wo",
        "R": 6.0,
        "RA": 5.0,
        "Inn": 12.0,
        "Record": "14-7",
        "Rank": 1.0,
        "GB": "up 1.5",
        "Win": "Belisle",
        "Loss": "Ayala",
        "Save": null,
        "Time": "3:48",
        "Attendance": 35234.0,
        "Streak": 1.0,
        "Year": 2013,
        "Date": "2013-04-24",
        "Winner": "COL-wo"
    },
    {
        "Unnamed_0": 1317,
        "Tm": "COL",
        "Home_Away": "@",
        "Opp": "ARI",
        "W_or_L": "L",
        "R": 2.0,
        "RA": 3.0,
        "Inn": 9.0,
        "Record": "14-8",
        "Rank": 1.0,
        "GB": "up 1.0",
        "Win": "Cahill",
        "Loss": "De\u00a0La\u00a0Rosa",
        "Save": "Putz",
        "Time": "3:09",
        "Attendance": 24532.0,
        "Streak": -1.0,
        "Year": 2013,
        "Date": "2013-04-25",
        "Winner": "ARI"
    },
    {
        "Unnamed_0": 1318,
        "Tm": "COL",
        "Home_Away": "@",
        "Opp": "ARI",
        "W_or_L": "W",
        "R": 6.0,
        "RA": 3.0,
        "Inn": 9.0,
        "Record": "15-8",
        "Rank": 1.0,
        "GB": "up 2.0",
        "Win": "Nicasio",
        "Loss": "McCarthy",
        "Save": "Betancourt",
        "Time": "3:08",
        "Attendance": 28801.0,
        "Streak": 1.0,
        "Year": 2013,
        "Date": "2013-04-26",
        "Winner": "COL"
    },
    {
        "Unnamed_0": 1319,
        "Tm": "COL",
        "Home_Away": "@",
        "Opp": "ARI",
        "W_or_L": "L-wo",
        "R": 2.0,
        "RA": 3.0,
        "Inn": 10.0,
        "Record": "15-9",
        "Rank": 1.0,
        "GB": "up 1.0",
        "Win": "Putz",
        "Loss": "Escalona",
        "Save": null,
        "Time": "3:29",
        "Attendance": 31019.0,
        "Streak": -1.0,
        "Year": 2013,
        "Date": "2013-04-27",
        "Winner": "ARI-wo"
    },
    {
        "Unnamed_0": 1320,
        "Tm": "COL",
        "Home_Away": "@",
        "Opp": "ARI",
        "W_or_L": "L",
        "R": 2.0,
        "RA": 4.0,
        "Inn": 9.0,
        "Record": "15-10",
        "Rank": 1.0,
        "GB": "Tied",
        "Win": "Corbin",
        "Loss": "Garland",
        "Save": "Putz",
        "Time": "2:33",
        "Attendance": 24852.0,
        "Streak": -2.0,
        "Year": 2013,
        "Date": "2013-04-28",
        "Winner": "ARI"
    },
    {
        "Unnamed_0": 1321,
        "Tm": "COL",
        "Home_Away": "@",
        "Opp": "LAD",
        "W_or_L": "W",
        "R": 12.0,
        "RA": 2.0,
        "Inn": 9.0,
        "Record": "16-10",
        "Rank": 1.0,
        "GB": "up 1.0",
        "Win": "Chatwood",
        "Loss": "Lilly",
        "Save": null,
        "Time": "3:22",
        "Attendance": 31570.0,
        "Streak": 1.0,
        "Year": 2013,
        "Date": "2013-04-29",
        "Winner": "COL"
    },
    {
        "Unnamed_0": 1322,
        "Tm": "COL",
        "Home_Away": "@",
        "Opp": "LAD",
        "W_or_L": "L",
        "R": 2.0,
        "RA": 6.0,
        "Inn": 9.0,
        "Record": "16-11",
        "Rank": 1.0,
        "GB": "up 1.0",
        "Win": "Ryu",
        "Loss": "De\u00a0La\u00a0Rosa",
        "Save": null,
        "Time": "3:02",
        "Attendance": 47602.0,
        "Streak": -1.0,
        "Year": 2013,
        "Date": "2013-04-30",
        "Winner": "LAD"
    },
    {
        "Unnamed_0": 1323,
        "Tm": "COL",
        "Home_Away": "@",
        "Opp": "LAD",
        "W_or_L": "W",
        "R": 7.0,
        "RA": 3.0,
        "Inn": 9.0,
        "Record": "17-11",
        "Rank": 1.0,
        "GB": "up 1.0",
        "Win": "Outman",
        "Loss": "Beckett",
        "Save": null,
        "Time": "3:54",
        "Attendance": 32848.0,
        "Streak": 1.0,
        "Year": 2013,
        "Date": "2013-05-01",
        "Winner": "COL"
    },
    {
        "Unnamed_0": 1324,
        "Tm": "COL",
        "Home_Away": "Home",
        "Opp": "TBR",
        "W_or_L": "L",
        "R": 4.0,
        "RA": 7.0,
        "Inn": 10.0,
        "Record": "17-12",
        "Rank": 1.0,
        "GB": "Tied",
        "Win": "Farnsworth",
        "Loss": "Belisle",
        "Save": "Rodney",
        "Time": "3:35",
        "Attendance": 30255.0,
        "Streak": -1.0,
        "Year": 2013,
        "Date": "2013-05-03",
        "Winner": "TBR"
    },
    {
        "Unnamed_0": 1325,
        "Tm": "COL",
        "Home_Away": "Home",
        "Opp": "TBR",
        "W_or_L": "W",
        "R": 9.0,
        "RA": 3.0,
        "Inn": 9.0,
        "Record": "18-12",
        "Rank": 1.0,
        "GB": "Tied",
        "Win": "Garland",
        "Loss": "Price",
        "Save": null,
        "Time": "3:04",
        "Attendance": 29099.0,
        "Streak": 1.0,
        "Year": 2013,
        "Date": "2013-05-04",
        "Winner": "COL"
    },
    {
        "Unnamed_0": 1326,
        "Tm": "COL",
        "Home_Away": "Home",
        "Opp": "TBR",
        "W_or_L": "L",
        "R": 3.0,
        "RA": 8.0,
        "Inn": 9.0,
        "Record": "18-13",
        "Rank": 2.0,
        "GB": "1.0",
        "Win": "Cobb",
        "Loss": "Chac\u00edn",
        "Save": null,
        "Time": "3:00",
        "Attendance": 39220.0,
        "Streak": -1.0,
        "Year": 2013,
        "Date": "2013-05-05",
        "Winner": "TBR"
    },
    {
        "Unnamed_0": 1327,
        "Tm": "COL",
        "Home_Away": "Home",
        "Opp": "NYY",
        "W_or_L": "W",
        "R": 2.0,
        "RA": 0.0,
        "Inn": 9.0,
        "Record": "19-13",
        "Rank": 1.0,
        "GB": "up 0.5",
        "Win": "De\u00a0La\u00a0Rosa",
        "Loss": "Kuroda",
        "Save": "Betancourt",
        "Time": "2:47",
        "Attendance": 41595.0,
        "Streak": 1.0,
        "Year": 2013,
        "Date": "2013-05-07",
        "Winner": "COL"
    },
    {
        "Unnamed_0": 1328,
        "Tm": "COL",
        "Home_Away": "Home",
        "Opp": "NYY",
        "W_or_L": "L",
        "R": 2.0,
        "RA": 3.0,
        "Inn": 9.0,
        "Record": "19-14",
        "Rank": 2.0,
        "GB": "0.5",
        "Win": "Robertson",
        "Loss": "Betancourt",
        "Save": "Rivera",
        "Time": "2:53",
        "Attendance": 40148.0,
        "Streak": -1.0,
        "Year": 2013,
        "Date": "2013-05-08",
        "Winner": "NYY"
    },
    {
        "Unnamed_0": 1329,
        "Tm": "COL",
        "Home_Away": "Home",
        "Opp": "NYY",
        "W_or_L": "L",
        "R": 1.0,
        "RA": 3.0,
        "Inn": 9.0,
        "Record": "19-15",
        "Rank": 3.0,
        "GB": "0.5",
        "Win": "Warren",
        "Loss": "Francis",
        "Save": "Rivera",
        "Time": "2:41",
        "Attendance": 40972.0,
        "Streak": -2.0,
        "Year": 2013,
        "Date": "2013-05-09",
        "Winner": "NYY"
    },
    {
        "Unnamed_0": 1330,
        "Tm": "COL",
        "Home_Away": "@",
        "Opp": "STL",
        "W_or_L": "L",
        "R": 0.0,
        "RA": 3.0,
        "Inn": 9.0,
        "Record": "19-16",
        "Rank": 3.0,
        "GB": "1.5",
        "Win": "Miller",
        "Loss": "Garland",
        "Save": null,
        "Time": "2:36",
        "Attendance": 37800.0,
        "Streak": -3.0,
        "Year": 2013,
        "Date": "2013-05-10",
        "Winner": "STL"
    },
    {
        "Unnamed_0": 1331,
        "Tm": "COL",
        "Home_Away": "@",
        "Opp": "STL",
        "W_or_L": "L",
        "R": 0.0,
        "RA": 3.0,
        "Inn": 9.0,
        "Record": "19-17",
        "Rank": 3.0,
        "GB": "2.5",
        "Win": "Wainwright",
        "Loss": "Chac\u00edn",
        "Save": null,
        "Time": "2:40",
        "Attendance": 43050.0,
        "Streak": -4.0,
        "Year": 2013,
        "Date": "2013-05-11",
        "Winner": "STL"
    },
    {
        "Unnamed_0": 1332,
        "Tm": "COL",
        "Home_Away": "@",
        "Opp": "STL",
        "W_or_L": "W",
        "R": 8.0,
        "RA": 2.0,
        "Inn": 9.0,
        "Record": "20-17",
        "Rank": 3.0,
        "GB": "2.5",
        "Win": "De\u00a0La\u00a0Rosa",
        "Loss": "Garc\u00eda",
        "Save": null,
        "Time": "3:05",
        "Attendance": 40881.0,
        "Streak": 1.0,
        "Year": 2013,
        "Date": "2013-05-12",
        "Winner": "COL"
    },
    {
        "Unnamed_0": 1333,
        "Tm": "COL",
        "Home_Away": "@",
        "Opp": "CHC",
        "W_or_L": "L",
        "R": 1.0,
        "RA": 9.0,
        "Inn": 9.0,
        "Record": "20-18",
        "Rank": 3.0,
        "GB": "3.0",
        "Win": "Wood",
        "Loss": "Nicasio",
        "Save": null,
        "Time": "2:41",
        "Attendance": 35080.0,
        "Streak": -1.0,
        "Year": 2013,
        "Date": "2013-05-13",
        "Winner": "CHC"
    },
    {
        "Unnamed_0": 1334,
        "Tm": "COL",
        "Home_Away": "@",
        "Opp": "CHC",
        "W_or_L": "W",
        "R": 9.0,
        "RA": 4.0,
        "Inn": 9.0,
        "Record": "21-18",
        "Rank": 3.0,
        "GB": "2.0",
        "Win": "Francis",
        "Loss": "Villanueva",
        "Save": null,
        "Time": "2:52",
        "Attendance": 38123.0,
        "Streak": 1.0,
        "Year": 2013,
        "Date": "2013-05-14",
        "Winner": "COL"
    },
    {
        "Unnamed_0": 1335,
        "Tm": "COL",
        "Home_Away": "@",
        "Opp": "CHC",
        "W_or_L": "L",
        "R": 3.0,
        "RA": 6.0,
        "Inn": 9.0,
        "Record": "21-19",
        "Rank": 3.0,
        "GB": "2.0",
        "Win": "Samardzija",
        "Loss": "Garland",
        "Save": null,
        "Time": "2:47",
        "Attendance": 38083.0,
        "Streak": -1.0,
        "Year": 2013,
        "Date": "2013-05-15",
        "Winner": "CHC"
    },
    {
        "Unnamed_0": 1336,
        "Tm": "COL",
        "Home_Away": "Home",
        "Opp": "SFG",
        "W_or_L": "L",
        "R": 6.0,
        "RA": 8.0,
        "Inn": 9.0,
        "Record": "21-20",
        "Rank": 3.0,
        "GB": "3.0",
        "Win": "Cain",
        "Loss": "Chac\u00edn",
        "Save": "Romo",
        "Time": "3:06",
        "Attendance": 33128.0,
        "Streak": -2.0,
        "Year": 2013,
        "Date": "2013-05-16",
        "Winner": "SFG"
    },
    {
        "Unnamed_0": 1337,
        "Tm": "COL",
        "Home_Away": "Home",
        "Opp": "SFG",
        "W_or_L": "W",
        "R": 10.0,
        "RA": 9.0,
        "Inn": 9.0,
        "Record": "22-20",
        "Rank": 3.0,
        "GB": "2.0",
        "Win": "De\u00a0La\u00a0Rosa",
        "Loss": "Bumgarner",
        "Save": "Betancourt",
        "Time": "3:48",
        "Attendance": 43365.0,
        "Streak": 1.0,
        "Year": 2013,
        "Date": "2013-05-17",
        "Winner": "COL"
    },
    {
        "Unnamed_0": 1338,
        "Tm": "COL",
        "Home_Away": "Home",
        "Opp": "SFG",
        "W_or_L": "W",
        "R": 10.0,
        "RA": 2.0,
        "Inn": 9.0,
        "Record": "23-20",
        "Rank": 3.0,
        "GB": "2.0",
        "Win": "Chatwood",
        "Loss": "Lincecum",
        "Save": null,
        "Time": "2:58",
        "Attendance": 41412.0,
        "Streak": 2.0,
        "Year": 2013,
        "Date": "2013-05-18",
        "Winner": "COL"
    },
    {
        "Unnamed_0": 1339,
        "Tm": "COL",
        "Home_Away": "Home",
        "Opp": "SFG",
        "W_or_L": "W",
        "R": 5.0,
        "RA": 0.0,
        "Inn": 9.0,
        "Record": "24-20",
        "Rank": 2.0,
        "GB": "1.0",
        "Win": "Nicasio",
        "Loss": "Zito",
        "Save": null,
        "Time": "3:10",
        "Attendance": 47494.0,
        "Streak": 3.0,
        "Year": 2013,
        "Date": "2013-05-19",
        "Winner": "COL"
    },
    {
        "Unnamed_0": 1340,
        "Tm": "COL",
        "Home_Away": "Home",
        "Opp": "ARI",
        "W_or_L": "L",
        "R": 1.0,
        "RA": 5.0,
        "Inn": 9.0,
        "Record": "24-21",
        "Rank": 3.0,
        "GB": "2.0",
        "Win": "Corbin",
        "Loss": "Garland",
        "Save": null,
        "Time": "2:32",
        "Attendance": 23053.0,
        "Streak": -1.0,
        "Year": 2013,
        "Date": "2013-05-20",
        "Winner": "ARI"
    },
    {
        "Unnamed_0": 1341,
        "Tm": "COL",
        "Home_Away": "Home",
        "Opp": "ARI",
        "W_or_L": "W-wo",
        "R": 5.0,
        "RA": 4.0,
        "Inn": 10.0,
        "Record": "25-21",
        "Rank": 3.0,
        "GB": "1.0",
        "Win": "Lopez",
        "Loss": "Reynolds",
        "Save": null,
        "Time": "3:07",
        "Attendance": 27096.0,
        "Streak": 1.0,
        "Year": 2013,
        "Date": "2013-05-21",
        "Winner": "COL-wo"
    },
    {
        "Unnamed_0": 1342,
        "Tm": "COL",
        "Home_Away": "Home",
        "Opp": "ARI",
        "W_or_L": "W",
        "R": 4.0,
        "RA": 1.0,
        "Inn": 9.0,
        "Record": "26-21",
        "Rank": 1.0,
        "GB": "Tied",
        "Win": "De\u00a0La\u00a0Rosa",
        "Loss": "Cahill",
        "Save": "Brothers",
        "Time": "2:52",
        "Attendance": 31763.0,
        "Streak": 2.0,
        "Year": 2013,
        "Date": "2013-05-22",
        "Winner": "COL"
    },
    {
        "Unnamed_0": 1343,
        "Tm": "COL",
        "Home_Away": "@",
        "Opp": "SFG",
        "W_or_L": "W",
        "R": 5.0,
        "RA": 0.0,
        "Inn": 9.0,
        "Record": "27-21",
        "Rank": 1.0,
        "GB": "Tied",
        "Win": "Chatwood",
        "Loss": "Lincecum",
        "Save": null,
        "Time": "2:25",
        "Attendance": 41881.0,
        "Streak": 3.0,
        "Year": 2013,
        "Date": "2013-05-24",
        "Winner": "COL"
    },
    {
        "Unnamed_0": 1344,
        "Tm": "COL",
        "Home_Away": "@",
        "Opp": "SFG",
        "W_or_L": "L-wo",
        "R": 5.0,
        "RA": 6.0,
        "Inn": 10.0,
        "Record": "27-22",
        "Rank": 1.0,
        "GB": "Tied",
        "Win": "Romo",
        "Loss": "Betancourt",
        "Save": null,
        "Time": "3:45",
        "Attendance": 41784.0,
        "Streak": -1.0,
        "Year": 2013,
        "Date": "2013-05-25",
        "Winner": "SFG-wo"
    },
    {
        "Unnamed_0": 1345,
        "Tm": "COL",
        "Home_Away": "@",
        "Opp": "SFG",
        "W_or_L": "L",
        "R": 3.0,
        "RA": 7.0,
        "Inn": 9.0,
        "Record": "27-23",
        "Rank": 3.0,
        "GB": "1.0",
        "Win": "Cain",
        "Loss": "Garland",
        "Save": null,
        "Time": "3:37",
        "Attendance": 42597.0,
        "Streak": -2.0,
        "Year": 2013,
        "Date": "2013-05-26",
        "Winner": "SFG"
    },
    {
        "Unnamed_0": 1346,
        "Tm": "COL",
        "Home_Away": "@",
        "Opp": "HOU",
        "W_or_L": "L-wo",
        "R": 2.0,
        "RA": 3.0,
        "Inn": 12.0,
        "Record": "27-24",
        "Rank": 3.0,
        "GB": "2.5",
        "Win": "Clemens",
        "Loss": "Lopez",
        "Save": null,
        "Time": "4:21",
        "Attendance": 16044.0,
        "Streak": -3.0,
        "Year": 2013,
        "Date": "2013-05-27",
        "Winner": "HOU-wo"
    },
    {
        "Unnamed_0": 1347,
        "Tm": "COL",
        "Home_Away": "@",
        "Opp": "HOU",
        "W_or_L": "W",
        "R": 2.0,
        "RA": 1.0,
        "Inn": 9.0,
        "Record": "28-24",
        "Rank": 2.0,
        "GB": "2.0",
        "Win": "Belisle",
        "Loss": "Veras",
        "Save": "Betancourt",
        "Time": "3:05",
        "Attendance": 11974.0,
        "Streak": 1.0,
        "Year": 2013,
        "Date": "2013-05-28",
        "Winner": "COL"
    },
    {
        "Unnamed_0": 1348,
        "Tm": "COL",
        "Home_Away": "Home",
        "Opp": "HOU",
        "W_or_L": "L",
        "R": 3.0,
        "RA": 6.0,
        "Inn": 9.0,
        "Record": "28-25",
        "Rank": 2.0,
        "GB": "2.5",
        "Win": "Clemens",
        "Loss": "Escalona",
        "Save": null,
        "Time": "3:29",
        "Attendance": 26881.0,
        "Streak": -1.0,
        "Year": 2013,
        "Date": "2013-05-29",
        "Winner": "HOU"
    },
    {
        "Unnamed_0": 1349,
        "Tm": "COL",
        "Home_Away": "Home",
        "Opp": "HOU",
        "W_or_L": "L",
        "R": 5.0,
        "RA": 7.0,
        "Inn": 9.0,
        "Record": "28-26",
        "Rank": 3.0,
        "GB": "2.5",
        "Win": "Harrell",
        "Loss": "Nicasio",
        "Save": "Ambriz",
        "Time": "3:21",
        "Attendance": 26239.0,
        "Streak": -2.0,
        "Year": 2013,
        "Date": "2013-05-30",
        "Winner": "HOU"
    },
    {
        "Unnamed_0": 1350,
        "Tm": "COL",
        "Home_Away": "Home",
        "Opp": "LAD",
        "W_or_L": "L",
        "R": 5.0,
        "RA": 7.0,
        "Inn": 10.0,
        "Record": "28-27",
        "Rank": 3.0,
        "GB": "2.5",
        "Win": "League",
        "Loss": "Betancourt",
        "Save": "Belisario",
        "Time": "3:23",
        "Attendance": 37923.0,
        "Streak": -3.0,
        "Year": 2013,
        "Date": "2013-05-31",
        "Winner": "LAD"
    },
    {
        "Unnamed_0": 1351,
        "Tm": "COL",
        "Home_Away": "Home",
        "Opp": "LAD",
        "W_or_L": "W-wo",
        "R": 7.0,
        "RA": 6.0,
        "Inn": 10.0,
        "Record": "29-27",
        "Rank": 2.0,
        "GB": "2.5",
        "Win": "Belisle",
        "Loss": "Guerrier",
        "Save": null,
        "Time": "3:39",
        "Attendance": 36703.0,
        "Streak": 1.0,
        "Year": 2013,
        "Date": "2013-06-01",
        "Winner": "COL-wo"
    },
    {
        "Unnamed_0": 1352,
        "Tm": "COL",
        "Home_Away": "Home",
        "Opp": "LAD",
        "W_or_L": "W",
        "R": 7.0,
        "RA": 2.0,
        "Inn": 9.0,
        "Record": "30-27",
        "Rank": 2.0,
        "GB": "2.5",
        "Win": "De\u00a0La\u00a0Rosa",
        "Loss": "Magill",
        "Save": null,
        "Time": "2:36",
        "Attendance": 41536.0,
        "Streak": 2.0,
        "Year": 2013,
        "Date": "2013-06-02",
        "Winner": "COL"
    },
    {
        "Unnamed_0": 1353,
        "Tm": "COL",
        "Home_Away": "@",
        "Opp": "CIN",
        "W_or_L": "L",
        "R": 0.0,
        "RA": 3.0,
        "Inn": 9.0,
        "Record": "30-28",
        "Rank": 3.0,
        "GB": "2.5",
        "Win": "Arroyo",
        "Loss": "Chatwood",
        "Save": "Chapman",
        "Time": "2:54",
        "Attendance": 18498.0,
        "Streak": -1.0,
        "Year": 2013,
        "Date": "2013-06-03",
        "Winner": "CIN"
    },
    {
        "Unnamed_0": 1354,
        "Tm": "COL",
        "Home_Away": "@",
        "Opp": "CIN",
        "W_or_L": "W",
        "R": 5.0,
        "RA": 4.0,
        "Inn": 9.0,
        "Record": "31-28",
        "Rank": 3.0,
        "GB": "2.5",
        "Win": "Outman",
        "Loss": "LeCure",
        "Save": "Brothers",
        "Time": "3:19",
        "Attendance": 27031.0,
        "Streak": 1.0,
        "Year": 2013,
        "Date": "2013-06-04",
        "Winner": "COL"
    },
    {
        "Unnamed_0": 1355,
        "Tm": "COL",
        "Home_Away": "@",
        "Opp": "CIN",
        "W_or_L": "W",
        "R": 12.0,
        "RA": 4.0,
        "Inn": 9.0,
        "Record": "32-28",
        "Rank": 2.0,
        "GB": "2.5",
        "Win": "Garland",
        "Loss": "Villarreal",
        "Save": null,
        "Time": "3:19",
        "Attendance": 26665.0,
        "Streak": 2.0,
        "Year": 2013,
        "Date": "2013-06-05",
        "Winner": "COL"
    },
    {
        "Unnamed_0": 1356,
        "Tm": "COL",
        "Home_Away": "Home",
        "Opp": "SDP",
        "W_or_L": "L",
        "R": 5.0,
        "RA": 6.0,
        "Inn": 12.0,
        "Record": "32-29",
        "Rank": 2.0,
        "GB": "2.5",
        "Win": "Gregerson",
        "Loss": "Corpas",
        "Save": "Boxberger",
        "Time": "4:04",
        "Attendance": 29840.0,
        "Streak": -1.0,
        "Year": 2013,
        "Date": "2013-06-06",
        "Winner": "SDP"
    },
    {
        "Unnamed_0": 1357,
        "Tm": "COL",
        "Home_Away": "Home",
        "Opp": "SDP",
        "W_or_L": "W-wo",
        "R": 10.0,
        "RA": 9.0,
        "Inn": 9.0,
        "Record": "33-29",
        "Rank": 2.0,
        "GB": "2.5",
        "Win": "Belisle",
        "Loss": "Thatcher",
        "Save": null,
        "Time": "3:26",
        "Attendance": 30477.0,
        "Streak": 1.0,
        "Year": 2013,
        "Date": "2013-06-07",
        "Winner": "COL-wo"
    },
    {
        "Unnamed_0": 1358,
        "Tm": "COL",
        "Home_Away": "Home",
        "Opp": "SDP",
        "W_or_L": "L",
        "R": 2.0,
        "RA": 4.0,
        "Inn": 9.0,
        "Record": "33-30",
        "Rank": 2.0,
        "GB": "2.5",
        "Win": "Stults",
        "Loss": "Francis",
        "Save": "Gregerson",
        "Time": "3:21",
        "Attendance": 34590.0,
        "Streak": -1.0,
        "Year": 2013,
        "Date": "2013-06-08",
        "Winner": "SDP"
    },
    {
        "Unnamed_0": 1359,
        "Tm": "COL",
        "Home_Away": "Home",
        "Opp": "SDP",
        "W_or_L": "W-wo",
        "R": 8.0,
        "RA": 7.0,
        "Inn": 10.0,
        "Record": "34-30",
        "Rank": 2.0,
        "GB": "1.5",
        "Win": "Brothers",
        "Loss": "Ross",
        "Save": null,
        "Time": "3:21",
        "Attendance": 33668.0,
        "Streak": 1.0,
        "Year": 2013,
        "Date": "2013-06-09",
        "Winner": "COL-wo"
    },
    {
        "Unnamed_0": 1360,
        "Tm": "COL",
        "Home_Away": "Home",
        "Opp": "WSN",
        "W_or_L": "W",
        "R": 8.0,
        "RA": 3.0,
        "Inn": 9.0,
        "Record": "35-30",
        "Rank": 2.0,
        "GB": "1.0",
        "Win": "Chac\u00edn",
        "Loss": "Haren",
        "Save": null,
        "Time": "3:03",
        "Attendance": 33736.0,
        "Streak": 2.0,
        "Year": 2013,
        "Date": "2013-06-11",
        "Winner": "COL"
    },
    {
        "Unnamed_0": 1361,
        "Tm": "COL",
        "Home_Away": "Home",
        "Opp": "WSN",
        "W_or_L": "L",
        "R": 1.0,
        "RA": 5.0,
        "Inn": 9.0,
        "Record": "35-31",
        "Rank": 2.0,
        "GB": "2.0",
        "Win": "Ohlendorf",
        "Loss": "De\u00a0La\u00a0Rosa",
        "Save": null,
        "Time": "3:16",
        "Attendance": 30304.0,
        "Streak": -1.0,
        "Year": 2013,
        "Date": "2013-06-12",
        "Winner": "WSN"
    },
    {
        "Unnamed_0": 1362,
        "Tm": "COL",
        "Home_Away": "Home",
        "Opp": "WSN",
        "W_or_L": "L",
        "R": 4.0,
        "RA": 5.0,
        "Inn": 9.0,
        "Record": "35-32",
        "Rank": 2.0,
        "GB": "2.5",
        "Win": "Stammen",
        "Loss": "Belisle",
        "Save": "Soriano",
        "Time": "3:05",
        "Attendance": 37017.0,
        "Streak": -2.0,
        "Year": 2013,
        "Date": "2013-06-13",
        "Winner": "WSN"
    },
    {
        "Unnamed_0": 1363,
        "Tm": "COL",
        "Home_Away": "Home",
        "Opp": "PHI",
        "W_or_L": "L",
        "R": 7.0,
        "RA": 8.0,
        "Inn": 9.0,
        "Record": "35-33",
        "Rank": 3.0,
        "GB": "2.5",
        "Win": "Stutes",
        "Loss": "Lopez",
        "Save": "Papelbon",
        "Time": "3:23",
        "Attendance": 36114.0,
        "Streak": -3.0,
        "Year": 2013,
        "Date": "2013-06-14",
        "Winner": "PHI"
    },
    {
        "Unnamed_0": 1364,
        "Tm": "COL",
        "Home_Away": "Home",
        "Opp": "PHI",
        "W_or_L": "W",
        "R": 10.0,
        "RA": 5.0,
        "Inn": 9.0,
        "Record": "36-33",
        "Rank": 2.0,
        "GB": "1.5",
        "Win": "Chatwood",
        "Loss": "Pettibone",
        "Save": null,
        "Time": "3:08",
        "Attendance": 35516.0,
        "Streak": 1.0,
        "Year": 2013,
        "Date": "2013-06-15",
        "Winner": "COL"
    },
    {
        "Unnamed_0": 1365,
        "Tm": "COL",
        "Home_Away": "Home",
        "Opp": "PHI",
        "W_or_L": "W",
        "R": 5.0,
        "RA": 2.0,
        "Inn": 9.0,
        "Record": "37-33",
        "Rank": 2.0,
        "GB": "0.5",
        "Win": "Chac\u00edn",
        "Loss": "Hamels",
        "Save": "Brothers",
        "Time": "2:18",
        "Attendance": 45186.0,
        "Streak": 2.0,
        "Year": 2013,
        "Date": "2013-06-16",
        "Winner": "COL"
    },
    {
        "Unnamed_0": 1366,
        "Tm": "COL",
        "Home_Away": "@",
        "Opp": "TOR",
        "W_or_L": "L",
        "R": 0.0,
        "RA": 2.0,
        "Inn": 9.0,
        "Record": "37-34",
        "Rank": 2.0,
        "GB": "0.5",
        "Win": "Cecil",
        "Loss": "Belisle",
        "Save": "Janssen",
        "Time": "2:24",
        "Attendance": 20496.0,
        "Streak": -1.0,
        "Year": 2013,
        "Date": "2013-06-17",
        "Winner": "TOR"
    },
    {
        "Unnamed_0": 1367,
        "Tm": "COL",
        "Home_Away": "@",
        "Opp": "TOR",
        "W_or_L": "L",
        "R": 3.0,
        "RA": 8.0,
        "Inn": 9.0,
        "Record": "37-35",
        "Rank": 2.0,
        "GB": "1.5",
        "Win": "Rogers",
        "Loss": "Francis",
        "Save": null,
        "Time": "2:20",
        "Attendance": 22852.0,
        "Streak": -2.0,
        "Year": 2013,
        "Date": "2013-06-18",
        "Winner": "TOR"
    },
    {
        "Unnamed_0": 1368,
        "Tm": "COL",
        "Home_Away": "@",
        "Opp": "TOR",
        "W_or_L": "L",
        "R": 2.0,
        "RA": 5.0,
        "Inn": 9.0,
        "Record": "37-36",
        "Rank": 3.0,
        "GB": "2.5",
        "Win": "Buehrle",
        "Loss": "Nicasio",
        "Save": "Janssen",
        "Time": "2:58",
        "Attendance": 27235.0,
        "Streak": -3.0,
        "Year": 2013,
        "Date": "2013-06-19",
        "Winner": "TOR"
    },
    {
        "Unnamed_0": 1369,
        "Tm": "COL",
        "Home_Away": "@",
        "Opp": "WSN",
        "W_or_L": "L",
        "R": 1.0,
        "RA": 5.0,
        "Inn": 9.0,
        "Record": "37-37",
        "Rank": 4.0,
        "GB": "3.0",
        "Win": "Zimmermann",
        "Loss": "Oswalt",
        "Save": null,
        "Time": "2:49",
        "Attendance": 31927.0,
        "Streak": -4.0,
        "Year": 2013,
        "Date": "2013-06-20",
        "Winner": "WSN"
    },
    {
        "Unnamed_0": 1370,
        "Tm": "COL",
        "Home_Away": "@",
        "Opp": "WSN",
        "W_or_L": "L",
        "R": 1.0,
        "RA": 2.0,
        "Inn": 9.0,
        "Record": "37-38",
        "Rank": 4.0,
        "GB": "4.0",
        "Win": "Strasburg",
        "Loss": "Corpas",
        "Save": "Soriano",
        "Time": "2:32",
        "Attendance": 34917.0,
        "Streak": -5.0,
        "Year": 2013,
        "Date": "2013-06-21",
        "Winner": "WSN"
    },
    {
        "Unnamed_0": 1371,
        "Tm": "COL",
        "Home_Away": "@",
        "Opp": "WSN",
        "W_or_L": "W",
        "R": 7.0,
        "RA": 1.0,
        "Inn": 9.0,
        "Record": "38-38",
        "Rank": 4.0,
        "GB": "4.0",
        "Win": "Chac\u00edn",
        "Loss": "Haren",
        "Save": null,
        "Time": "2:45",
        "Attendance": 35787.0,
        "Streak": 1.0,
        "Year": 2013,
        "Date": "2013-06-22",
        "Winner": "COL"
    },
    {
        "Unnamed_0": 1372,
        "Tm": "COL",
        "Home_Away": "@",
        "Opp": "WSN",
        "W_or_L": "W",
        "R": 7.0,
        "RA": 6.0,
        "Inn": 9.0,
        "Record": "39-38",
        "Rank": 2.0,
        "GB": "3.0",
        "Win": "De\u00a0La\u00a0Rosa",
        "Loss": "Detwiler",
        "Save": "Brothers",
        "Time": "3:05",
        "Attendance": 39307.0,
        "Streak": 2.0,
        "Year": 2013,
        "Date": "2013-06-23",
        "Winner": "COL"
    },
    {
        "Unnamed_0": 1373,
        "Tm": "COL",
        "Home_Away": "@",
        "Opp": "BOS",
        "W_or_L": "L",
        "R": 4.0,
        "RA": 11.0,
        "Inn": 9.0,
        "Record": "39-39",
        "Rank": 2.0,
        "GB": "3.0",
        "Win": "Dempster",
        "Loss": "Nicasio",
        "Save": null,
        "Time": "3:40",
        "Attendance": 36286.0,
        "Streak": -1.0,
        "Year": 2013,
        "Date": "2013-06-25",
        "Winner": "BOS"
    },
    {
        "Unnamed_0": 1374,
        "Tm": "COL",
        "Home_Away": "@",
        "Opp": "BOS",
        "W_or_L": "L",
        "R": 3.0,
        "RA": 5.0,
        "Inn": 9.0,
        "Record": "39-40",
        "Rank": 2.0,
        "GB": "3.0",
        "Win": "Lackey",
        "Loss": "Oswalt",
        "Save": "Uehara",
        "Time": "2:36",
        "Attendance": 34632.0,
        "Streak": -2.0,
        "Year": 2013,
        "Date": "2013-06-26",
        "Winner": "BOS"
    },
    {
        "Unnamed_0": 1375,
        "Tm": "COL",
        "Home_Away": "Home",
        "Opp": "NYM",
        "W_or_L": "L",
        "R": 2.0,
        "RA": 3.0,
        "Inn": 9.0,
        "Record": "39-41",
        "Rank": 3.0,
        "GB": "4.0",
        "Win": "Hawkins",
        "Loss": "Belisle",
        "Save": "Parnell",
        "Time": "2:51",
        "Attendance": 34387.0,
        "Streak": -3.0,
        "Year": 2013,
        "Date": "2013-06-27",
        "Winner": "NYM"
    },
    {
        "Unnamed_0": 1376,
        "Tm": "COL",
        "Home_Away": "Home",
        "Opp": "SFG",
        "W_or_L": "W",
        "R": 4.0,
        "RA": 1.0,
        "Inn": 9.0,
        "Record": "40-41",
        "Rank": 3.0,
        "GB": "3.0",
        "Win": "Chac\u00edn",
        "Loss": "Zito",
        "Save": null,
        "Time": "2:47",
        "Attendance": 38428.0,
        "Streak": 1.0,
        "Year": 2013,
        "Date": "2013-06-28",
        "Winner": "COL"
    },
    {
        "Unnamed_0": 1377,
        "Tm": "COL",
        "Home_Away": "Home",
        "Opp": "SFG",
        "W_or_L": "W-wo",
        "R": 2.0,
        "RA": 1.0,
        "Inn": 9.0,
        "Record": "41-41",
        "Rank": 2.0,
        "GB": "2.0",
        "Win": "Betancourt",
        "Loss": "Affeldt",
        "Save": null,
        "Time": "2:44",
        "Attendance": 44612.0,
        "Streak": 2.0,
        "Year": 2013,
        "Date": "2013-06-29",
        "Winner": "COL-wo"
    },
    {
        "Unnamed_0": 1378,
        "Tm": "COL",
        "Home_Away": "Home",
        "Opp": "SFG",
        "W_or_L": "L",
        "R": 2.0,
        "RA": 5.0,
        "Inn": 9.0,
        "Record": "41-42",
        "Rank": 2.0,
        "GB": "2.0",
        "Win": "Bumgarner",
        "Loss": "Pomeranz",
        "Save": "Romo",
        "Time": "3:16",
        "Attendance": 41845.0,
        "Streak": -1.0,
        "Year": 2013,
        "Date": "2013-06-30",
        "Winner": "SFG"
    },
    {
        "Unnamed_0": 1379,
        "Tm": "COL",
        "Home_Away": "Home",
        "Opp": "LAD",
        "W_or_L": "L",
        "R": 0.0,
        "RA": 8.0,
        "Inn": 9.0,
        "Record": "41-43",
        "Rank": 2.0,
        "GB": "1.5",
        "Win": "Kershaw",
        "Loss": "Oswalt",
        "Save": null,
        "Time": "2:35",
        "Attendance": 37419.0,
        "Streak": -2.0,
        "Year": 2013,
        "Date": "2013-07-02",
        "Winner": "LAD"
    },
    {
        "Unnamed_0": 1380,
        "Tm": "COL",
        "Home_Away": "Home",
        "Opp": "LAD",
        "W_or_L": "L",
        "R": 8.0,
        "RA": 10.0,
        "Inn": 9.0,
        "Record": "41-44",
        "Rank": 2.0,
        "GB": "2.5",
        "Win": "Greinke",
        "Loss": "Chatwood",
        "Save": "Jansen",
        "Time": "3:37",
        "Attendance": 48628.0,
        "Streak": -3.0,
        "Year": 2013,
        "Date": "2013-07-03",
        "Winner": "LAD"
    },
    {
        "Unnamed_0": 1381,
        "Tm": "COL",
        "Home_Away": "Home",
        "Opp": "LAD",
        "W_or_L": "W",
        "R": 9.0,
        "RA": 5.0,
        "Inn": 9.0,
        "Record": "42-44",
        "Rank": 2.0,
        "GB": "2.5",
        "Win": "Chac\u00edn",
        "Loss": "Capuano",
        "Save": null,
        "Time": "3:19",
        "Attendance": 48794.0,
        "Streak": 1.0,
        "Year": 2013,
        "Date": "2013-07-04",
        "Winner": "COL"
    },
    {
        "Unnamed_0": 1382,
        "Tm": "COL",
        "Home_Away": "@",
        "Opp": "ARI",
        "W_or_L": "L",
        "R": 0.0,
        "RA": 5.0,
        "Inn": 9.0,
        "Record": "42-45",
        "Rank": 2.0,
        "GB": "3.5",
        "Win": "Skaggs",
        "Loss": "De\u00a0La\u00a0Rosa",
        "Save": null,
        "Time": "2:40",
        "Attendance": 45505.0,
        "Streak": -1.0,
        "Year": 2013,
        "Date": "2013-07-05",
        "Winner": "ARI"
    },
    {
        "Unnamed_0": 1383,
        "Tm": "COL",
        "Home_Away": "@",
        "Opp": "ARI",
        "W_or_L": "L",
        "R": 1.0,
        "RA": 11.0,
        "Inn": 9.0,
        "Record": "42-46",
        "Rank": 2.0,
        "GB": "4.5",
        "Win": "Miley",
        "Loss": "Pomeranz",
        "Save": null,
        "Time": "2:47",
        "Attendance": 22395.0,
        "Streak": -2.0,
        "Year": 2013,
        "Date": "2013-07-06",
        "Winner": "ARI"
    },
    {
        "Unnamed_0": 1384,
        "Tm": "COL",
        "Home_Away": "@",
        "Opp": "ARI",
        "W_or_L": "L",
        "R": 1.0,
        "RA": 6.0,
        "Inn": 9.0,
        "Record": "42-47",
        "Rank": 3.0,
        "GB": "5.5",
        "Win": "Corbin",
        "Loss": "Oswalt",
        "Save": null,
        "Time": "2:33",
        "Attendance": 22090.0,
        "Streak": -3.0,
        "Year": 2013,
        "Date": "2013-07-07",
        "Winner": "ARI"
    },
    {
        "Unnamed_0": 1385,
        "Tm": "COL",
        "Home_Away": "@",
        "Opp": "SDP",
        "W_or_L": "W",
        "R": 4.0,
        "RA": 2.0,
        "Inn": 9.0,
        "Record": "43-47",
        "Rank": 3.0,
        "GB": "4.5",
        "Win": "Chatwood",
        "Loss": "Volquez",
        "Save": "Betancourt",
        "Time": "3:03",
        "Attendance": 20400.0,
        "Streak": 1.0,
        "Year": 2013,
        "Date": "2013-07-08",
        "Winner": "COL"
    },
    {
        "Unnamed_0": 1386,
        "Tm": "COL",
        "Home_Away": "@",
        "Opp": "SDP",
        "W_or_L": "L",
        "R": 1.0,
        "RA": 2.0,
        "Inn": 9.0,
        "Record": "43-48",
        "Rank": 3.0,
        "GB": "4.5",
        "Win": "Stults",
        "Loss": "Chac\u00edn",
        "Save": null,
        "Time": "2:32",
        "Attendance": 22733.0,
        "Streak": -1.0,
        "Year": 2013,
        "Date": "2013-07-09",
        "Winner": "SDP"
    },
    {
        "Unnamed_0": 1387,
        "Tm": "COL",
        "Home_Away": "@",
        "Opp": "SDP",
        "W_or_L": "W",
        "R": 5.0,
        "RA": 4.0,
        "Inn": 9.0,
        "Record": "44-48",
        "Rank": 3.0,
        "GB": "3.5",
        "Win": "De\u00a0La\u00a0Rosa",
        "Loss": "Cashner",
        "Save": "Betancourt",
        "Time": "3:33",
        "Attendance": 19411.0,
        "Streak": 1.0,
        "Year": 2013,
        "Date": "2013-07-10",
        "Winner": "COL"
    },
    {
        "Unnamed_0": 1388,
        "Tm": "COL",
        "Home_Away": "@",
        "Opp": "LAD",
        "W_or_L": "L",
        "R": 1.0,
        "RA": 6.0,
        "Inn": 9.0,
        "Record": "44-49",
        "Rank": 3.0,
        "GB": "4.5",
        "Win": "Capuano",
        "Loss": "Pomeranz",
        "Save": null,
        "Time": "3:13",
        "Attendance": 52740.0,
        "Streak": -1.0,
        "Year": 2013,
        "Date": "2013-07-11",
        "Winner": "LAD"
    },
    {
        "Unnamed_0": 1389,
        "Tm": "COL",
        "Home_Away": "@",
        "Opp": "LAD",
        "W_or_L": "W",
        "R": 3.0,
        "RA": 0.0,
        "Inn": 9.0,
        "Record": "45-49",
        "Rank": 3.0,
        "GB": "4.5",
        "Win": "Nicasio",
        "Loss": "Kershaw",
        "Save": "Betancourt",
        "Time": "3:13",
        "Attendance": 50796.0,
        "Streak": 1.0,
        "Year": 2013,
        "Date": "2013-07-12",
        "Winner": "COL"
    },
    {
        "Unnamed_0": 1390,
        "Tm": "COL",
        "Home_Away": "@",
        "Opp": "LAD",
        "W_or_L": "L",
        "R": 0.0,
        "RA": 1.0,
        "Inn": 9.0,
        "Record": "45-50",
        "Rank": 3.0,
        "GB": "5.5",
        "Win": "Greinke",
        "Loss": "Chatwood",
        "Save": null,
        "Time": "2:17",
        "Attendance": 51992.0,
        "Streak": -1.0,
        "Year": 2013,
        "Date": "2013-07-13",
        "Winner": "LAD"
    },
    {
        "Unnamed_0": 1391,
        "Tm": "COL",
        "Home_Away": "@",
        "Opp": "LAD",
        "W_or_L": "W",
        "R": 3.0,
        "RA": 1.0,
        "Inn": 9.0,
        "Record": "46-50",
        "Rank": 3.0,
        "GB": "4.5",
        "Win": "Chac\u00edn",
        "Loss": "Nolasco",
        "Save": "Betancourt",
        "Time": "3:16",
        "Attendance": 51402.0,
        "Streak": 1.0,
        "Year": 2013,
        "Date": "2013-07-14",
        "Winner": "COL"
    },
    {
        "Unnamed_0": 1392,
        "Tm": "COL",
        "Home_Away": "Home",
        "Opp": "CHC",
        "W_or_L": "L",
        "R": 1.0,
        "RA": 3.0,
        "Inn": 9.0,
        "Record": "46-51",
        "Rank": 3.0,
        "GB": "4.5",
        "Win": "Samardzija",
        "Loss": "Escalona",
        "Save": "Gregg",
        "Time": "2:59",
        "Attendance": 43976.0,
        "Streak": -1.0,
        "Year": 2013,
        "Date": "2013-07-19",
        "Winner": "CHC"
    },
    {
        "Unnamed_0": 1393,
        "Tm": "COL",
        "Home_Away": "Home",
        "Opp": "CHC",
        "W_or_L": "W",
        "R": 9.0,
        "RA": 3.0,
        "Inn": 9.0,
        "Record": "47-51",
        "Rank": 3.0,
        "GB": "3.5",
        "Win": "Nicasio",
        "Loss": "Villanueva",
        "Save": null,
        "Time": "3:29",
        "Attendance": 45616.0,
        "Streak": 1.0,
        "Year": 2013,
        "Date": "2013-07-20",
        "Winner": "COL"
    },
    {
        "Unnamed_0": 1394,
        "Tm": "COL",
        "Home_Away": "Home",
        "Opp": "CHC",
        "W_or_L": "W",
        "R": 4.0,
        "RA": 3.0,
        "Inn": 9.0,
        "Record": "48-51",
        "Rank": 3.0,
        "GB": "3.5",
        "Win": "Chatwood",
        "Loss": "Jackson",
        "Save": "Brothers",
        "Time": "3:11",
        "Attendance": 43108.0,
        "Streak": 2.0,
        "Year": 2013,
        "Date": "2013-07-21",
        "Winner": "COL"
    },
    {
        "Unnamed_0": 1395,
        "Tm": "COL",
        "Home_Away": "Home",
        "Opp": "MIA",
        "W_or_L": "L",
        "R": 1.0,
        "RA": 3.0,
        "Inn": 9.0,
        "Record": "48-52",
        "Rank": 3.0,
        "GB": "4.0",
        "Win": "Koehler",
        "Loss": "Pomeranz",
        "Save": "Cishek",
        "Time": "2:40",
        "Attendance": 31913.0,
        "Streak": -1.0,
        "Year": 2013,
        "Date": "2013-07-22",
        "Winner": "MIA"
    },
    {
        "Unnamed_0": 1396,
        "Tm": "COL",
        "Home_Away": "Home",
        "Opp": "MIA",
        "W_or_L": "L",
        "R": 2.0,
        "RA": 4.0,
        "Inn": 9.0,
        "Record": "48-53",
        "Rank": 3.0,
        "GB": "5.0",
        "Win": "Fern\u00e1ndez",
        "Loss": "Chac\u00edn",
        "Save": "Cishek",
        "Time": "2:43",
        "Attendance": 34223.0,
        "Streak": -2.0,
        "Year": 2013,
        "Date": "2013-07-23",
        "Winner": "MIA"
    },
    {
        "Unnamed_0": 1397,
        "Tm": "COL",
        "Home_Away": "Home",
        "Opp": "MIA",
        "W_or_L": "W",
        "R": 2.0,
        "RA": 1.0,
        "Inn": 9.0,
        "Record": "49-53",
        "Rank": 3.0,
        "GB": "5.0",
        "Win": "De\u00a0La\u00a0Rosa",
        "Loss": "Turner",
        "Save": "Brothers",
        "Time": "2:54",
        "Attendance": 30900.0,
        "Streak": 1.0,
        "Year": 2013,
        "Date": "2013-07-24",
        "Winner": "COL"
    },
    {
        "Unnamed_0": 1398,
        "Tm": "COL",
        "Home_Away": "Home",
        "Opp": "MIA",
        "W_or_L": "L",
        "R": 3.0,
        "RA": 5.0,
        "Inn": 9.0,
        "Record": "49-54",
        "Rank": 3.0,
        "GB": "5.0",
        "Win": "Jennings",
        "Loss": "Ottavino",
        "Save": "Cishek",
        "Time": "2:34",
        "Attendance": 33165.0,
        "Streak": -1.0,
        "Year": 2013,
        "Date": "2013-07-25",
        "Winner": "MIA"
    },
    {
        "Unnamed_0": 1399,
        "Tm": "COL",
        "Home_Away": "Home",
        "Opp": "MIL",
        "W_or_L": "W",
        "R": 8.0,
        "RA": 3.0,
        "Inn": 9.0,
        "Record": "50-54",
        "Rank": 3.0,
        "GB": "5.0",
        "Win": "Chatwood",
        "Loss": "Peralta",
        "Save": null,
        "Time": "2:41",
        "Attendance": 32740.0,
        "Streak": 1.0,
        "Year": 2013,
        "Date": "2013-07-26",
        "Winner": "COL"
    },
    {
        "Unnamed_0": 1400,
        "Tm": "COL",
        "Home_Away": "Home",
        "Opp": "MIL",
        "W_or_L": "L",
        "R": 5.0,
        "RA": 7.0,
        "Inn": 9.0,
        "Record": "50-55",
        "Rank": 3.0,
        "GB": "6.0",
        "Win": "Gorzelanny",
        "Loss": "McHugh",
        "Save": "Henderson",
        "Time": "2:59",
        "Attendance": 38012.0,
        "Streak": -1.0,
        "Year": 2013,
        "Date": "2013-07-27",
        "Winner": "MIL"
    },
    {
        "Unnamed_0": 1401,
        "Tm": "COL",
        "Home_Away": "Home",
        "Opp": "MIL",
        "W_or_L": "W",
        "R": 6.0,
        "RA": 5.0,
        "Inn": 9.0,
        "Record": "51-55",
        "Rank": 3.0,
        "GB": "6.0",
        "Win": "Belisle",
        "Loss": "Axford",
        "Save": "Brothers",
        "Time": "2:42",
        "Attendance": 33237.0,
        "Streak": 1.0,
        "Year": 2013,
        "Date": "2013-07-28",
        "Winner": "COL"
    },
    {
        "Unnamed_0": 1402,
        "Tm": "COL",
        "Home_Away": "@",
        "Opp": "ATL",
        "W_or_L": "L-wo",
        "R": 8.0,
        "RA": 9.0,
        "Inn": 10.0,
        "Record": "51-56",
        "Rank": 3.0,
        "GB": "6.5",
        "Win": "Downs",
        "Loss": "Escalona",
        "Save": null,
        "Time": "3:46",
        "Attendance": 31218.0,
        "Streak": -1.0,
        "Year": 2013,
        "Date": "2013-07-29",
        "Winner": "ATL-wo"
    },
    {
        "Unnamed_0": 1403,
        "Tm": "COL",
        "Home_Away": "@",
        "Opp": "ATL",
        "W_or_L": "L",
        "R": 3.0,
        "RA": 11.0,
        "Inn": 9.0,
        "Record": "51-57",
        "Rank": 3.0,
        "GB": "7.5",
        "Win": "Wood",
        "Loss": "Nicasio",
        "Save": null,
        "Time": "2:49",
        "Attendance": 28107.0,
        "Streak": -2.0,
        "Year": 2013,
        "Date": "2013-07-30",
        "Winner": "ATL"
    },
    {
        "Unnamed_0": 1404,
        "Tm": "COL",
        "Home_Away": "@",
        "Opp": "ATL",
        "W_or_L": "L",
        "R": 0.0,
        "RA": 9.0,
        "Inn": 9.0,
        "Record": "51-58",
        "Rank": 3.0,
        "GB": "7.5",
        "Win": "Minor",
        "Loss": "Chatwood",
        "Save": null,
        "Time": "3:00",
        "Attendance": 22097.0,
        "Streak": -3.0,
        "Year": 2013,
        "Date": "2013-07-31",
        "Winner": "ATL"
    },
    {
        "Unnamed_0": 1405,
        "Tm": "COL",
        "Home_Away": "@",
        "Opp": "ATL",
        "W_or_L": "L",
        "R": 2.0,
        "RA": 11.0,
        "Inn": 9.0,
        "Record": "51-59",
        "Rank": 3.0,
        "GB": "8.5",
        "Win": "Teheran",
        "Loss": "Bettis",
        "Save": null,
        "Time": "3:15",
        "Attendance": 30069.0,
        "Streak": -4.0,
        "Year": 2013,
        "Date": "2013-08-01",
        "Winner": "ATL"
    },
    {
        "Unnamed_0": 1406,
        "Tm": "COL",
        "Home_Away": "@",
        "Opp": "PIT",
        "W_or_L": "W",
        "R": 4.0,
        "RA": 2.0,
        "Inn": 9.0,
        "Record": "52-59",
        "Rank": 3.0,
        "GB": "8.5",
        "Win": "Chac\u00edn",
        "Loss": "Cole",
        "Save": "Brothers",
        "Time": "2:55",
        "Attendance": 37487.0,
        "Streak": 1.0,
        "Year": 2013,
        "Date": "2013-08-02",
        "Winner": "COL"
    },
    {
        "Unnamed_0": 1407,
        "Tm": "COL",
        "Home_Away": "@",
        "Opp": "PIT",
        "W_or_L": "L",
        "R": 2.0,
        "RA": 5.0,
        "Inn": 9.0,
        "Record": "52-60",
        "Rank": 3.0,
        "GB": "9.5",
        "Win": "Liriano",
        "Loss": "De\u00a0La\u00a0Rosa",
        "Save": "Melancon",
        "Time": "3:15",
        "Attendance": 38424.0,
        "Streak": -1.0,
        "Year": 2013,
        "Date": "2013-08-03",
        "Winner": "PIT"
    },
    {
        "Unnamed_0": 1408,
        "Tm": "COL",
        "Home_Away": "@",
        "Opp": "PIT",
        "W_or_L": "L",
        "R": 1.0,
        "RA": 5.0,
        "Inn": 9.0,
        "Record": "52-61",
        "Rank": 4.0,
        "GB": "10.5",
        "Win": "Burnett",
        "Loss": "Nicasio",
        "Save": null,
        "Time": "2:52",
        "Attendance": 37980.0,
        "Streak": -2.0,
        "Year": 2013,
        "Date": "2013-08-04",
        "Winner": "PIT"
    },
    {
        "Unnamed_0": 1409,
        "Tm": "COL",
        "Home_Away": "@",
        "Opp": "NYM",
        "W_or_L": "L",
        "R": 2.0,
        "RA": 3.0,
        "Inn": 9.0,
        "Record": "52-62",
        "Rank": 4.0,
        "GB": "11.0",
        "Win": "Atchison",
        "Loss": "Lopez",
        "Save": "Hawkins",
        "Time": "3:19",
        "Attendance": 27198.0,
        "Streak": -3.0,
        "Year": 2013,
        "Date": "2013-08-06",
        "Winner": "NYM"
    },
    {
        "Unnamed_0": 1410,
        "Tm": "COL",
        "Home_Away": "@",
        "Opp": "NYM",
        "W_or_L": "L",
        "R": 0.0,
        "RA": 5.0,
        "Inn": 9.0,
        "Record": "52-63",
        "Rank": 4.0,
        "GB": "12.0",
        "Win": "Harvey",
        "Loss": "Chac\u00edn",
        "Save": null,
        "Time": "2:20",
        "Attendance": 27581.0,
        "Streak": -4.0,
        "Year": 2013,
        "Date": "2013-08-07",
        "Winner": "NYM"
    },
    {
        "Unnamed_0": 1411,
        "Tm": "COL",
        "Home_Away": "@",
        "Opp": "NYM",
        "W_or_L": "L",
        "R": 1.0,
        "RA": 2.0,
        "Inn": 9.0,
        "Record": "52-64",
        "Rank": 4.0,
        "GB": "13.0",
        "Win": "Gee",
        "Loss": "Manship",
        "Save": "Hawkins",
        "Time": "2:44",
        "Attendance": 26618.0,
        "Streak": -5.0,
        "Year": 2013,
        "Date": "2013-08-08",
        "Winner": "NYM"
    },
    {
        "Unnamed_0": 1412,
        "Tm": "COL",
        "Home_Away": "Home",
        "Opp": "PIT",
        "W_or_L": "W",
        "R": 10.0,
        "RA": 1.0,
        "Inn": 9.0,
        "Record": "53-64",
        "Rank": 3.0,
        "GB": "13.0",
        "Win": "De\u00a0La\u00a0Rosa",
        "Loss": "Liriano",
        "Save": null,
        "Time": "3:19",
        "Attendance": 37444.0,
        "Streak": 1.0,
        "Year": 2013,
        "Date": "2013-08-09",
        "Winner": "COL"
    },
    {
        "Unnamed_0": 1413,
        "Tm": "COL",
        "Home_Away": "Home",
        "Opp": "PIT",
        "W_or_L": "W",
        "R": 6.0,
        "RA": 4.0,
        "Inn": 9.0,
        "Record": "54-64",
        "Rank": 3.0,
        "GB": "13.0",
        "Win": "Lopez",
        "Loss": "Burnett",
        "Save": "Brothers",
        "Time": "3:10",
        "Attendance": 40728.0,
        "Streak": 2.0,
        "Year": 2013,
        "Date": "2013-08-10",
        "Winner": "COL"
    },
    {
        "Unnamed_0": 1414,
        "Tm": "COL",
        "Home_Away": "Home",
        "Opp": "PIT",
        "W_or_L": "W",
        "R": 3.0,
        "RA": 2.0,
        "Inn": 9.0,
        "Record": "55-64",
        "Rank": 3.0,
        "GB": "13.0",
        "Win": "Corpas",
        "Loss": "Morris",
        "Save": "Brothers",
        "Time": "2:41",
        "Attendance": 44657.0,
        "Streak": 3.0,
        "Year": 2013,
        "Date": "2013-08-11",
        "Winner": "COL"
    },
    {
        "Unnamed_0": 1415,
        "Tm": "COL",
        "Home_Away": "Home",
        "Opp": "SDP",
        "W_or_L": "W",
        "R": 14.0,
        "RA": 2.0,
        "Inn": 9.0,
        "Record": "56-64",
        "Rank": 3.0,
        "GB": "13.0",
        "Win": "Chac\u00edn",
        "Loss": "Volquez",
        "Save": null,
        "Time": "2:35",
        "Attendance": 30986.0,
        "Streak": 4.0,
        "Year": 2013,
        "Date": "2013-08-12",
        "Winner": "COL"
    },
    {
        "Unnamed_0": 1416,
        "Tm": "COL",
        "Home_Away": "Home",
        "Opp": "SDP",
        "W_or_L": "L",
        "R": 5.0,
        "RA": 7.0,
        "Inn": 9.0,
        "Record": "56-65",
        "Rank": 3.0,
        "GB": "14.0",
        "Win": "Stauffer",
        "Loss": "Manship",
        "Save": "Street",
        "Time": "3:01",
        "Attendance": 30366.0,
        "Streak": -1.0,
        "Year": 2013,
        "Date": "2013-08-13",
        "Winner": "SDP"
    },
    {
        "Unnamed_0": 1417,
        "Tm": "COL",
        "Home_Away": "Home",
        "Opp": "SDP",
        "W_or_L": "W",
        "R": 4.0,
        "RA": 2.0,
        "Inn": 9.0,
        "Record": "57-65",
        "Rank": 3.0,
        "GB": "14.0",
        "Win": "De\u00a0La\u00a0Rosa",
        "Loss": "Cashner",
        "Save": "Brothers",
        "Time": "2:31",
        "Attendance": 30099.0,
        "Streak": 1.0,
        "Year": 2013,
        "Date": "2013-08-14",
        "Winner": "COL"
    },
    {
        "Unnamed_0": 1418,
        "Tm": "COL",
        "Home_Away": "@",
        "Opp": "BAL",
        "W_or_L": "W",
        "R": 6.0,
        "RA": 3.0,
        "Inn": 9.0,
        "Record": "58-65",
        "Rank": 3.0,
        "GB": "14.0",
        "Win": "Nicasio",
        "Loss": "Chen",
        "Save": null,
        "Time": "2:53",
        "Attendance": 31438.0,
        "Streak": 2.0,
        "Year": 2013,
        "Date": "2013-08-16",
        "Winner": "COL"
    },
    {
        "Unnamed_0": 1419,
        "Tm": "COL",
        "Home_Away": "@",
        "Opp": "BAL",
        "W_or_L": "L",
        "R": 4.0,
        "RA": 8.0,
        "Inn": 9.0,
        "Record": "58-66",
        "Rank": 3.0,
        "GB": "15.0",
        "Win": "Norris",
        "Loss": "Bettis",
        "Save": null,
        "Time": "3:24",
        "Attendance": 31089.0,
        "Streak": -1.0,
        "Year": 2013,
        "Date": "2013-08-17",
        "Winner": "BAL"
    },
    {
        "Unnamed_0": 1420,
        "Tm": "COL",
        "Home_Away": "@",
        "Opp": "BAL",
        "W_or_L": "L",
        "R": 2.0,
        "RA": 7.0,
        "Inn": 9.0,
        "Record": "58-67",
        "Rank": 3.0,
        "GB": "15.0",
        "Win": "Feldman",
        "Loss": "Chac\u00edn",
        "Save": null,
        "Time": "3:19",
        "Attendance": 22238.0,
        "Streak": -2.0,
        "Year": 2013,
        "Date": "2013-08-18",
        "Winner": "BAL"
    },
    {
        "Unnamed_0": 1421,
        "Tm": "COL",
        "Home_Away": "@",
        "Opp": "PHI",
        "W_or_L": "L",
        "R": 4.0,
        "RA": 5.0,
        "Inn": 9.0,
        "Record": "58-68",
        "Rank": 3.0,
        "GB": "15.0",
        "Win": "Martin",
        "Loss": "Manship",
        "Save": "Papelbon",
        "Time": "2:51",
        "Attendance": 35269.0,
        "Streak": -3.0,
        "Year": 2013,
        "Date": "2013-08-19",
        "Winner": "PHI"
    },
    {
        "Unnamed_0": 1422,
        "Tm": "COL",
        "Home_Away": "@",
        "Opp": "PHI",
        "W_or_L": "W",
        "R": 5.0,
        "RA": 3.0,
        "Inn": 9.0,
        "Record": "59-68",
        "Rank": 3.0,
        "GB": "15.0",
        "Win": "De\u00a0La\u00a0Rosa",
        "Loss": "Cloyd",
        "Save": "Betancourt",
        "Time": "3:06",
        "Attendance": 34018.0,
        "Streak": 1.0,
        "Year": 2013,
        "Date": "2013-08-20",
        "Winner": "COL"
    },
    {
        "Unnamed_0": 1423,
        "Tm": "COL",
        "Home_Away": "@",
        "Opp": "PHI",
        "W_or_L": "L-wo",
        "R": 3.0,
        "RA": 4.0,
        "Inn": 9.0,
        "Record": "59-69",
        "Rank": 3.0,
        "GB": "16.0",
        "Win": "Diekman",
        "Loss": "Betancourt",
        "Save": null,
        "Time": "3:12",
        "Attendance": 36578.0,
        "Streak": -1.0,
        "Year": 2013,
        "Date": "2013-08-21",
        "Winner": "PHI-wo"
    },
    {
        "Unnamed_0": 1424,
        "Tm": "COL",
        "Home_Away": "@",
        "Opp": "PHI",
        "W_or_L": "L-wo",
        "R": 4.0,
        "RA": 5.0,
        "Inn": 9.0,
        "Record": "59-70",
        "Rank": 3.0,
        "GB": "17.0",
        "Win": "Jimenez",
        "Loss": "Betancourt",
        "Save": null,
        "Time": "3:17",
        "Attendance": 31619.0,
        "Streak": -2.0,
        "Year": 2013,
        "Date": "2013-08-22",
        "Winner": "PHI-wo"
    },
    {
        "Unnamed_0": 1425,
        "Tm": "COL",
        "Home_Away": "@",
        "Opp": "MIA",
        "W_or_L": "W",
        "R": 3.0,
        "RA": 2.0,
        "Inn": 9.0,
        "Record": "60-70",
        "Rank": 3.0,
        "GB": "17.0",
        "Win": "Chac\u00edn",
        "Loss": "Qualls",
        "Save": "Brothers",
        "Time": "2:44",
        "Attendance": 19253.0,
        "Streak": 1.0,
        "Year": 2013,
        "Date": "2013-08-23",
        "Winner": "COL"
    },
    {
        "Unnamed_0": 1426,
        "Tm": "COL",
        "Home_Away": "@",
        "Opp": "MIA",
        "W_or_L": "L",
        "R": 0.0,
        "RA": 3.0,
        "Inn": 9.0,
        "Record": "60-71",
        "Rank": 3.0,
        "GB": "17.0",
        "Win": "Fern\u00e1ndez",
        "Loss": "Manship",
        "Save": "Cishek",
        "Time": "2:30",
        "Attendance": 23333.0,
        "Streak": -1.0,
        "Year": 2013,
        "Date": "2013-08-24",
        "Winner": "MIA"
    },
    {
        "Unnamed_0": 1427,
        "Tm": "COL",
        "Home_Away": "@",
        "Opp": "MIA",
        "W_or_L": "W",
        "R": 4.0,
        "RA": 3.0,
        "Inn": 9.0,
        "Record": "61-71",
        "Rank": 3.0,
        "GB": "16.0",
        "Win": "De\u00a0La\u00a0Rosa",
        "Loss": "Turner",
        "Save": "Brothers",
        "Time": "3:16",
        "Attendance": 20191.0,
        "Streak": 1.0,
        "Year": 2013,
        "Date": "2013-08-25",
        "Winner": "COL"
    },
    {
        "Unnamed_0": 1428,
        "Tm": "COL",
        "Home_Away": "Home",
        "Opp": "SFG",
        "W_or_L": "W",
        "R": 6.0,
        "RA": 1.0,
        "Inn": 9.0,
        "Record": "62-71",
        "Rank": 3.0,
        "GB": "16.0",
        "Win": "Nicasio",
        "Loss": "Zito",
        "Save": null,
        "Time": "2:49",
        "Attendance": 30364.0,
        "Streak": 2.0,
        "Year": 2013,
        "Date": "2013-08-26",
        "Winner": "COL"
    },
    {
        "Unnamed_0": 1429,
        "Tm": "COL",
        "Home_Away": "Home",
        "Opp": "SFG",
        "W_or_L": "L",
        "R": 3.0,
        "RA": 5.0,
        "Inn": 9.0,
        "Record": "62-72",
        "Rank": 3.0,
        "GB": "16.0",
        "Win": "Petit",
        "Loss": "Bettis",
        "Save": "Romo",
        "Time": "3:03",
        "Attendance": 26601.0,
        "Streak": -1.0,
        "Year": 2013,
        "Date": "2013-08-27",
        "Winner": "SFG"
    },
    {
        "Unnamed_0": 1430,
        "Tm": "COL",
        "Home_Away": "Home",
        "Opp": "SFG",
        "W_or_L": "W",
        "R": 5.0,
        "RA": 4.0,
        "Inn": 9.0,
        "Record": "63-72",
        "Rank": 3.0,
        "GB": "16.0",
        "Win": "Chac\u00edn",
        "Loss": "Bumgarner",
        "Save": "Brothers",
        "Time": "3:02",
        "Attendance": 27268.0,
        "Streak": 1.0,
        "Year": 2013,
        "Date": "2013-08-28",
        "Winner": "COL"
    },
    {
        "Unnamed_0": 1431,
        "Tm": "COL",
        "Home_Away": "Home",
        "Opp": "CIN",
        "W_or_L": "W",
        "R": 9.0,
        "RA": 6.0,
        "Inn": 9.0,
        "Record": "64-72",
        "Rank": 3.0,
        "GB": "16.0",
        "Win": "De\u00a0La\u00a0Rosa",
        "Loss": "Arroyo",
        "Save": null,
        "Time": "3:12",
        "Attendance": 29415.0,
        "Streak": 2.0,
        "Year": 2013,
        "Date": "2013-08-30",
        "Winner": "COL"
    },
    {
        "Unnamed_0": 1432,
        "Tm": "COL",
        "Home_Away": "Home",
        "Opp": "CIN",
        "W_or_L": "L",
        "R": 3.0,
        "RA": 8.0,
        "Inn": 9.0,
        "Record": "64-73",
        "Rank": 3.0,
        "GB": "17.0",
        "Win": "Reynolds",
        "Loss": "Nicasio",
        "Save": null,
        "Time": "2:58",
        "Attendance": 37616.0,
        "Streak": -1.0,
        "Year": 2013,
        "Date": "2013-08-31",
        "Winner": "CIN"
    },
    {
        "Unnamed_0": 1433,
        "Tm": "COL",
        "Home_Away": "Home",
        "Opp": "CIN",
        "W_or_L": "W",
        "R": 7.0,
        "RA": 4.0,
        "Inn": 9.0,
        "Record": "65-73",
        "Rank": 3.0,
        "GB": "17.0",
        "Win": "Ottavino",
        "Loss": "Leake",
        "Save": null,
        "Time": "3:28",
        "Attendance": 30594.0,
        "Streak": 1.0,
        "Year": 2013,
        "Date": "2013-09-01",
        "Winner": "COL"
    },
    {
        "Unnamed_0": 1434,
        "Tm": "COL",
        "Home_Away": "Home",
        "Opp": "LAD",
        "W_or_L": "L",
        "R": 8.0,
        "RA": 10.0,
        "Inn": 9.0,
        "Record": "65-74",
        "Rank": 3.0,
        "GB": "18.0",
        "Win": "Kershaw",
        "Loss": "Manship",
        "Save": "Jansen",
        "Time": "3:38",
        "Attendance": 36822.0,
        "Streak": -1.0,
        "Year": 2013,
        "Date": "2013-09-02",
        "Winner": "LAD"
    },
    {
        "Unnamed_0": 1435,
        "Tm": "COL",
        "Home_Away": "Home",
        "Opp": "LAD",
        "W_or_L": "L",
        "R": 4.0,
        "RA": 7.0,
        "Inn": 9.0,
        "Record": "65-75",
        "Rank": 3.0,
        "GB": "19.0",
        "Win": "Nolasco",
        "Loss": "Chac\u00edn",
        "Save": "Withrow",
        "Time": "3:10",
        "Attendance": 25807.0,
        "Streak": -2.0,
        "Year": 2013,
        "Date": "2013-09-03",
        "Winner": "LAD"
    },
    {
        "Unnamed_0": 1436,
        "Tm": "COL",
        "Home_Away": "Home",
        "Opp": "LAD",
        "W_or_L": "W",
        "R": 7.0,
        "RA": 5.0,
        "Inn": 9.0,
        "Record": "66-75",
        "Rank": 3.0,
        "GB": "18.0",
        "Win": "De\u00a0La\u00a0Rosa",
        "Loss": "Volquez",
        "Save": "Brothers",
        "Time": "3:35",
        "Attendance": 28439.0,
        "Streak": 1.0,
        "Year": 2013,
        "Date": "2013-09-04",
        "Winner": "COL"
    },
    {
        "Unnamed_0": 1437,
        "Tm": "COL",
        "Home_Away": "@",
        "Opp": "SDP",
        "W_or_L": "L-wo",
        "R": 3.0,
        "RA": 4.0,
        "Inn": 9.0,
        "Record": "66-76",
        "Rank": 3.0,
        "GB": "18.0",
        "Win": "Street",
        "Loss": "Brothers",
        "Save": null,
        "Time": "3:07",
        "Attendance": 21476.0,
        "Streak": -1.0,
        "Year": 2013,
        "Date": "2013-09-06",
        "Winner": "SDP-wo"
    },
    {
        "Unnamed_0": 1438,
        "Tm": "COL",
        "Home_Away": "@",
        "Opp": "SDP",
        "W_or_L": "L",
        "R": 1.0,
        "RA": 2.0,
        "Inn": 9.0,
        "Record": "66-77",
        "Rank": 3.0,
        "GB": "18.0",
        "Win": "Gregerson",
        "Loss": "Belisle",
        "Save": "Street",
        "Time": "2:26",
        "Attendance": 25272.0,
        "Streak": -2.0,
        "Year": 2013,
        "Date": "2013-09-07",
        "Winner": "SDP"
    },
    {
        "Unnamed_0": 1439,
        "Tm": "COL",
        "Home_Away": "@",
        "Opp": "SDP",
        "W_or_L": "L",
        "R": 2.0,
        "RA": 5.0,
        "Inn": 9.0,
        "Record": "66-78",
        "Rank": 3.0,
        "GB": "18.0",
        "Win": "Vincent",
        "Loss": "Oswalt",
        "Save": "Street",
        "Time": "2:52",
        "Attendance": 18656.0,
        "Streak": -3.0,
        "Year": 2013,
        "Date": "2013-09-08",
        "Winner": "SDP"
    },
    {
        "Unnamed_0": 1440,
        "Tm": "COL",
        "Home_Away": "@",
        "Opp": "SFG",
        "W_or_L": "L-wo",
        "R": 2.0,
        "RA": 3.0,
        "Inn": 10.0,
        "Record": "66-79",
        "Rank": 4.0,
        "GB": "19.0",
        "Win": "Casilla",
        "Loss": "Ottavino",
        "Save": null,
        "Time": "3:04",
        "Attendance": 41078.0,
        "Streak": -4.0,
        "Year": 2013,
        "Date": "2013-09-09",
        "Winner": "SFG-wo"
    },
    {
        "Unnamed_0": 1441,
        "Tm": "COL",
        "Home_Away": "@",
        "Opp": "SFG",
        "W_or_L": "W",
        "R": 9.0,
        "RA": 8.0,
        "Inn": 9.0,
        "Record": "67-79",
        "Rank": 4.0,
        "GB": "19.0",
        "Win": "Lopez",
        "Loss": "Romo",
        "Save": "Brothers",
        "Time": "4:02",
        "Attendance": 41171.0,
        "Streak": 1.0,
        "Year": 2013,
        "Date": "2013-09-10",
        "Winner": "COL"
    },
    {
        "Unnamed_0": 1442,
        "Tm": "COL",
        "Home_Away": "@",
        "Opp": "SFG",
        "W_or_L": "L",
        "R": 3.0,
        "RA": 4.0,
        "Inn": 9.0,
        "Record": "67-80",
        "Rank": 4.0,
        "GB": "19.0",
        "Win": "Moscoso",
        "Loss": "Belisle",
        "Save": "Casilla",
        "Time": "3:19",
        "Attendance": 41128.0,
        "Streak": -1.0,
        "Year": 2013,
        "Date": "2013-09-11",
        "Winner": "SFG"
    },
    {
        "Unnamed_0": 1443,
        "Tm": "COL",
        "Home_Away": "@",
        "Opp": "ARI",
        "W_or_L": "W",
        "R": 7.0,
        "RA": 5.0,
        "Inn": 9.0,
        "Record": "68-80",
        "Rank": 3.0,
        "GB": "18.5",
        "Win": "Outman",
        "Loss": "Harris",
        "Save": "Brothers",
        "Time": "3:39",
        "Attendance": 31713.0,
        "Streak": 1.0,
        "Year": 2013,
        "Date": "2013-09-13",
        "Winner": "COL"
    },
    {
        "Unnamed_0": 1444,
        "Tm": "COL",
        "Home_Away": "@",
        "Opp": "ARI",
        "W_or_L": "L",
        "R": 2.0,
        "RA": 9.0,
        "Inn": 9.0,
        "Record": "68-81",
        "Rank": 3.0,
        "GB": "18.5",
        "Win": "Miley",
        "Loss": "Oswalt",
        "Save": null,
        "Time": "3:05",
        "Attendance": 32237.0,
        "Streak": -1.0,
        "Year": 2013,
        "Date": "2013-09-14",
        "Winner": "ARI"
    },
    {
        "Unnamed_0": 1445,
        "Tm": "COL",
        "Home_Away": "@",
        "Opp": "ARI",
        "W_or_L": "L",
        "R": 2.0,
        "RA": 8.0,
        "Inn": 9.0,
        "Record": "68-82",
        "Rank": 5.0,
        "GB": "18.5",
        "Win": "Delgado",
        "Loss": "Chac\u00edn",
        "Save": null,
        "Time": "2:47",
        "Attendance": 26845.0,
        "Streak": -2.0,
        "Year": 2013,
        "Date": "2013-09-15",
        "Winner": "ARI"
    },
    {
        "Unnamed_0": 1446,
        "Tm": "COL",
        "Home_Away": "Home",
        "Opp": "STL",
        "W_or_L": "W",
        "R": 6.0,
        "RA": 2.0,
        "Inn": 9.0,
        "Record": "69-82",
        "Rank": 5.0,
        "GB": "17.5",
        "Win": "Bettis",
        "Loss": "Rosenthal",
        "Save": null,
        "Time": "2:51",
        "Attendance": 31117.0,
        "Streak": 1.0,
        "Year": 2013,
        "Date": "2013-09-16",
        "Winner": "COL"
    },
    {
        "Unnamed_0": 1447,
        "Tm": "COL",
        "Home_Away": "Home",
        "Opp": "STL",
        "W_or_L": "L",
        "R": 4.0,
        "RA": 11.0,
        "Inn": 9.0,
        "Record": "69-83",
        "Rank": 5.0,
        "GB": "18.5",
        "Win": "Kelly",
        "Loss": "Nicasio",
        "Save": null,
        "Time": "3:23",
        "Attendance": 27107.0,
        "Streak": -1.0,
        "Year": 2013,
        "Date": "2013-09-17",
        "Winner": "STL"
    },
    {
        "Unnamed_0": 1448,
        "Tm": "COL",
        "Home_Away": "Home",
        "Opp": "STL",
        "W_or_L": "L",
        "R": 3.0,
        "RA": 4.0,
        "Inn": 9.0,
        "Record": "69-84",
        "Rank": 5.0,
        "GB": "18.5",
        "Win": "Wainwright",
        "Loss": "Chatwood",
        "Save": "Mujica",
        "Time": "2:53",
        "Attendance": 26955.0,
        "Streak": -2.0,
        "Year": 2013,
        "Date": "2013-09-18",
        "Winner": "STL"
    },
    {
        "Unnamed_0": 1449,
        "Tm": "COL",
        "Home_Away": "Home",
        "Opp": "STL",
        "W_or_L": "W-wo",
        "R": 7.0,
        "RA": 6.0,
        "Inn": 15.0,
        "Record": "70-84",
        "Rank": 5.0,
        "GB": "18.5",
        "Win": "Scahill",
        "Loss": "Salas",
        "Save": null,
        "Time": "5:09",
        "Attendance": 33258.0,
        "Streak": 1.0,
        "Year": 2013,
        "Date": "2013-09-19",
        "Winner": "COL-wo"
    },
    {
        "Unnamed_0": 1450,
        "Tm": "COL",
        "Home_Away": "Home",
        "Opp": "ARI",
        "W_or_L": "W",
        "R": 9.0,
        "RA": 4.0,
        "Inn": 9.0,
        "Record": "71-84",
        "Rank": 5.0,
        "GB": "17.5",
        "Win": "Chac\u00edn",
        "Loss": "Sipp",
        "Save": null,
        "Time": "3:17",
        "Attendance": 38247.0,
        "Streak": 2.0,
        "Year": 2013,
        "Date": "2013-09-20",
        "Winner": "COL"
    },
    {
        "Unnamed_0": 1451,
        "Tm": "COL",
        "Home_Away": "Home",
        "Opp": "ARI",
        "W_or_L": "L",
        "R": 2.0,
        "RA": 7.0,
        "Inn": 9.0,
        "Record": "71-85",
        "Rank": 5.0,
        "GB": "18.5",
        "Win": "Cahill",
        "Loss": "McHugh",
        "Save": null,
        "Time": "3:00",
        "Attendance": 36005.0,
        "Streak": -1.0,
        "Year": 2013,
        "Date": "2013-09-21",
        "Winner": "ARI"
    },
    {
        "Unnamed_0": 1452,
        "Tm": "COL",
        "Home_Away": "Home",
        "Opp": "ARI",
        "W_or_L": "L",
        "R": 9.0,
        "RA": 13.0,
        "Inn": 9.0,
        "Record": "71-86",
        "Rank": 5.0,
        "GB": "19.5",
        "Win": "Harris",
        "Loss": "Nicasio",
        "Save": null,
        "Time": "3:45",
        "Attendance": 43736.0,
        "Streak": -2.0,
        "Year": 2013,
        "Date": "2013-09-22",
        "Winner": "ARI"
    },
    {
        "Unnamed_0": 1453,
        "Tm": "COL",
        "Home_Away": "Home",
        "Opp": "BOS",
        "W_or_L": "W",
        "R": 8.0,
        "RA": 3.0,
        "Inn": 9.0,
        "Record": "72-86",
        "Rank": 5.0,
        "GB": "19.5",
        "Win": "Chatwood",
        "Loss": "Lackey",
        "Save": null,
        "Time": "2:40",
        "Attendance": 32315.0,
        "Streak": 1.0,
        "Year": 2013,
        "Date": "2013-09-24",
        "Winner": "COL"
    },
    {
        "Unnamed_0": 1454,
        "Tm": "COL",
        "Home_Away": "Home",
        "Opp": "BOS",
        "W_or_L": "L",
        "R": 5.0,
        "RA": 15.0,
        "Inn": 9.0,
        "Record": "72-87",
        "Rank": 5.0,
        "GB": "19.5",
        "Win": "Peavy",
        "Loss": "Chac\u00edn",
        "Save": null,
        "Time": "3:30",
        "Attendance": 48775.0,
        "Streak": -1.0,
        "Year": 2013,
        "Date": "2013-09-25",
        "Winner": "BOS"
    },
    {
        "Unnamed_0": 1455,
        "Tm": "COL",
        "Home_Away": "@",
        "Opp": "LAD",
        "W_or_L": "L",
        "R": 0.0,
        "RA": 11.0,
        "Inn": 9.0,
        "Record": "72-88",
        "Rank": 5.0,
        "GB": "20.0",
        "Win": "Kershaw",
        "Loss": "McHugh",
        "Save": null,
        "Time": "2:53",
        "Attendance": 52367.0,
        "Streak": -2.0,
        "Year": 2013,
        "Date": "2013-09-27",
        "Winner": "LAD"
    },
    {
        "Unnamed_0": 1456,
        "Tm": "COL",
        "Home_Away": "@",
        "Opp": "LAD",
        "W_or_L": "W",
        "R": 1.0,
        "RA": 0.0,
        "Inn": 9.0,
        "Record": "73-88",
        "Rank": 5.0,
        "GB": "19.0",
        "Win": "Nicasio",
        "Loss": "Greinke",
        "Save": "Brothers",
        "Time": "3:11",
        "Attendance": 52879.0,
        "Streak": 1.0,
        "Year": 2013,
        "Date": "2013-09-28",
        "Winner": "COL"
    },
    {
        "Unnamed_0": 1457,
        "Tm": "COL",
        "Home_Away": "@",
        "Opp": "LAD",
        "W_or_L": "W",
        "R": 2.0,
        "RA": 1.0,
        "Inn": 9.0,
        "Record": "74-88",
        "Rank": 5.0,
        "GB": "18.0",
        "Win": "Francis",
        "Loss": "Ryu",
        "Save": "Brothers",
        "Time": "3:08",
        "Attendance": 52396.0,
        "Streak": 2.0,
        "Year": 2013,
        "Date": "2013-09-29",
        "Winner": "COL"
    }
]}